Workbook

Sheet Памятка заполнения
A2: Памятка по заполнению формы Бюджета ДДС на ИТ и программу цифровой трансформации
A4: 1. | B4: Форма предполагает заполнение вкладок: Сведения об Организации, Программа ЦТ и План
A8: 2. | B8: Для корректного заполнения формы План необходимо внести сведения по Наименованию Организации и Перечню филиалов на вкладке Сведения об Организации, а также перечень мероприятий программы Цифровой трансформации на вкладке Программа ЦТ
A13: 3. | B13: Заполнение Программы ЦТ является обязательным, если Организации разрабатывала Стратегию Цифровой трансформации. Информация об утверждении Программы ЦТ отражается на вкладке Сведения об Организации
A17: 4. | B17: План расходов включает в себя сведения по всем источникам финансирования, применяемые Организацией, в случае потребности в ИТ товарах/услугах, как для собственных нужд, так и при реализации внешних заказов
A21: 5. | B21: Сводные сведения по расходам на ИТ в разрезе различных источников финансирования на основе сведений Плана представлены на вкладке Свод ДДС
A25: 6. | B25: Дополнительно на вкладке Свод БДДС собирается аналитика по закупкам у Отраслевого оператора по ИТ направлению, а также аналитика о закупке Программного обеспечения, которое включено в реестр
A29: 7. | B29: Для внесения сведений в План о ПО из реестра необходимо внести сведения по номеру записи в поле: Номер в реестре отеч ПО (9), сведения по классу и наименованию ПО будут автоматически заполнены, столбцы: Класс предмета закупки (10) и Предмет закупки(11)
A34: 8. | B34: Если сведения из реестра по какой-то причине не получены, например, неполон перечен ПО на вкладке Реестр отеч ПО или вкладка отсутствует, то внесение сведений проводится в Ручном режиме
A38: 9. | B38: Для определения номера в Реестре отечественного ПО можно использовать вкладки: Реестр отеч ПО или Выдержка из реестра, или использовать поиск на сайте: https://reestr.digital.gov.ru/
A42: 10. | B42: Для планируемого к приобретению ПО вне реестра сведения в План вносятся в ручном режиме, обязательны к заполнению поля: Класс предмета (10) и Предмет закупки(11) или Подробное описание предмета закупки(12)
A46: 11. | B46: При заполнении Плана необходимо отразить расходы, связанные с реализацией мероприятий Программы ЦТ. Сведения по реализации всех мероприятий программы должны найти отражение в Плане
A50: 12. | B50: Если при реализации мероприятия требуется закупка ПО, Оборудования или услуг, то в Плане отражаются расходы отдельными строками с указанием ссылки на номер и наименование мероприятия из Программы ЦТ
... A85: 19. | B85: При работе пользователя с файлом применяется цветовая индикация проверок, которая позволяет определить состав обязательных к заполнению полей по различным типам закупок/расходов. Легенда цветовой индикации представлена справа от заполняемой пользователем формы. Наличие цветовых маркеров не влияет на способность сохранения вносимых сведений в форму, но может стать основанием возврата пользователю форм для доработки

Sheet Сведения об Организации
A1: Контактная информация
A2: Полное наименование организации | C2: Федеральное государственное унитарное предприятие "Научно-технический центр "Заря"
A3: Сокращенное наименование организации | C3: ФГУП "НТЦ "Заря"
A4: Ответственное лицо организации в части информационных технологий (заместитель ГД по ИТ, руководитель подразделения и пр.) | C4: Афонин Владимир Николаевич, Заместитель директора по информационной безопасности
A5: Электронная почта | C5: afonin.vn@ ntc-zarya.ru
A6: Юридический адрес | C6: 123056, г. Москва, ул. 2-я Брестская, дом 9 стр. 1
A7: Фактический адрес | C7: 123056, г. Москва, ул. 2-я Брестская, дом 9 стр. 1
A8: Контактный телефон | C8: +7 (499) 766-22-05, доб 43-04
A9: ИНН организации | C9: 7710030179
A10: Основной вид деятельности (ОКВЭД2) | C10: 74.90.9
A12: Контактные данные ответственного за подготовку отчета работника ИТ-подразделения
A13: ФИО (полностью) | C13: Матвеев Степан Евгеньевич
A14: Наименование подразделения | C14: Отдел технической поддержки
A15: Должность | C15: Главный эксперт
A16: Контактный телефон | C16: (499) 766-22-05 доб. 33-39
A17: Электронная почта | C17: matveev.se@ntc-zarya.ru
A19: Дополнительная информация
A20: Ответственное лицо организации в части цифровизации (заместитель ГД, руководитель по цифровой трансформации и пр.) | C20: Афонин Владимир Николаевич, заместитель директора по информационной безопасности
A21: Стратегия Цифровой трансформации Организации | C21: Утверждена
A22: Программа цифровой трансформации | C22: Да
A24: Дорожная карта по переходу на безбумажный конструкторский и технологический документооборот | C24: Не утверждена
A25: Подключение к ЕСПД | C25: Да
A27: Количество АРМ | C27: 196
A28: в т.ч.
A29: АРМ со сроком полезного использования до 1 года
A30: АРМ со сроком полезного использования от 1 года до 3 лет
A31: АРМ со сроком полезного использования от 3 до 5 лет | C31: 87
A32: АРМ со сроком полезного использования от 5 до 10 лет | C32: 32
A33: АРМ со сроком полезного использования более 10 лет | C33: 5
A34: Количество АРМ с подключением к ЕСПД | C34: 72
A36: Численность организации (вкл. филиалы)* | C36: 182
A37: в т.ч.
B38: 1.1.1. Основные рабочие
B39: 1.1.2.1 ИТР - Конструкторы
B40: 1.1.2.2. ИТР -Технологи
B41: 1.1.2.3. ИТР - Инженеры-испытатели
B42: 1.1.2.4. ИТР - Прочие специалисты | C42: 111.3
B43: 1.1.2.5. ИТР - Руководители | C43: 16
B44: 1.2.1. Вспомогательные рабочие | C44: 7
B45: 1.3.1.1. Руководители - Высший менеджмент | C45: 6
B46: 1.3.1.2.Руководители - Средний менеджмент | C46: 5.8
B47: 1.3.1.3. Руководители - Менеджмент
B48: 1.3.2.1. Специалисты - Конструкторы
B49: 1.3.2.2. Специалисты - Технологи
B50: 1.3.2.3. Специалисты - Прочие специалисты | C50: 42.3
B51: 1.3.3. Служащие | C51: 0
B52: 2. Персонал непромышленной сферы | C52: 0
A53: Численность персонала подразделений, обеспечивающих развитие и эксплуатацию информационных систем, инфраструктуры (включая телефонию и кабельные сети), в том числе обеспечивающие внедрение и поддержание систем для собственных нужд (вкл. филиалы) | C53: 6
A54: в т.ч.
A55: эксплуатация серверной инфраструктуры | C55: 1
A56: эксплуатация сетевой инфраструктуры | C56: 1
A57: экплуатация телефонии и кабельных сетей | C57: 1
A58: поддержка АРМ (в т.ч. сервисов коммуникации, первая линия поддержки) | C58: 2
A59: сопрововождение информационных систем | C59: 1
A60: команды разработки
A61: создание продуктов, внедрение систем (проектный офис)
A62: аналитики (процессный офис)
A63: управление данными
A64: прочие
A66: Среднемесячный совокупный ФОТ сотрудников по ИТ функции | C66: 414,65 тыс.руб.
A67: Доля расходов на содержание ИТ функции в составе Накладных расходов | C67: 3,05%
A70: Список филиалов
A71: № п/п | B71: Полное наименование филиала (без сокращений) | C71: ИНН | D71: Контактный телефон | E71: Фактический адрес
A72: 1
A73: 2
A74: 3
A75: 4
A76: 5
A77: 6
A78: 7
A79: 8
A80: 9
A81: 10
A82: 11
A83: 12

Sheet План Факт 2025
A1: Наименование организации | B1: Наименование филиала | C1: Источник финансирования | D1: Статья затрат | E1: Код статьи БДДС | F1: Статья БДДС 3 уровень | G1: ID инвестиционного проекта | H1: Отметка о типе проекта | I1: Объем финансирования инвестиционного проекта, всего, тыс. руб. | J1: Пункт мероприятия Программы ЦТ (Стратегии ЦТ) | K1: Номер в реестре отеч ПО | L1: Класс предмета закупки | M1: Предмет закупки | N1: Подробное описание объекта закупки (товара, работы или услуги) | O1: Отметка о закупке у Отраслевого оператора (Да/Нет) | Q1: Сумма с НДС, тыс. руб
P2: Контрагент | Q2: План 2025 | R2: План (след. Год) | S2: 1-й квартал 2025 | T2: 2-й квартал 2025 | U2: Ожидаемое исполнение 2025 | V2: 3-й квартал 2025 | W2: 4-й квартал 2025 | X2: Месяц поставки | Y2: Год поставки | Z2: План (след. Год+1) | AA2: План (след. Год+2) | AB2: 6 мес 2025 г. | AC2: 6 мес 2025 г. | AD2: Отклонение (руб.) | AE2: Не планировали | AF2: Отклонение (%)_ | AG2: Отклонение (%) | AH2: Комметарии по отклонению от плана
S3: План | T3: План | V3: План | W3: План | X3: План | Y3: План | AB3: План | AC3: Факт
A4: 1 | B4: 2 | C4: 3 | D4: 4 | E4: 5 | F4: 6 | G4: 7 | H4: 8 | I4: 9 | J4: 10 | K4: 11 | L4: 12 | M4: 13 | N4: 14 | O4: 15 | P4: 16 | Q4: 17 | R4: 15 | S4: 18 | T4: 19 | U4: 20 | V4: 21 | W4: 22 | X4: 20 | Y4: 21 | Z4: 22 | AA4: 23 | AB4: 23 | AC4: 24 | AD4: 25 | AE4: 32 | AF4: 14 | AG4: 26 | AH4: 27
A5: ФГУП "НТЦ"Заря" | C5: Инвестиционный_проект | D5: ИТ_оборудование_и_комплектующие_ИП | E5: 42210100. Приобретение, создание, строительство ОС (ИД) | F5: 42210103. Приобретение оборудования для ИТ-инфраструктуры | G5: 075-00011-НП | I5: =SUM(R5,Z5,AA5) -> 1500 | L5: 2. Серверное оборудование, СХД | M5: Закупка системмы хранения данных (отечественного производства) | N5: Совершенствование ИТ-инфраструктуры предприятия с учетом импорьозамещения | O5: Да | Q5: =AB5+V5+W5 -> 1500 | R5: =SUM(S5+T5+V5+W5) -> 1500 | U5: =IF(ISBLANK(AC5),"",AC5+V5+W5) | V5: 1500 | X5: сентябрь | Y5: 2025 | AB5: =SUM(S5:T5) -> 0 | AD5: =IF(ISBLANK(AC5),"",IF(AB5=0,"Поступлений не планировалось",AC5-AB5)) | AE5: =IF($AB5=0,0,1) -> 0 | AF5: =AC5*100/AB5 -> #DIV/0! | AG5: =IF(ISBLANK(AC5),"",AF5-100) | AH5: =IF(($AC5=$AB5),"",IF(ISBLANK($AC5),"", "Укажите причину отклонения"))
A6: ФГУП "НТЦ"Заря" | C6: Инвестиционный_проект | D6: ИТ_оборудование_и_комплектующие_ИП | E6: 42210100. Приобретение, создание, строительство ОС (ИД) | F6: 42210103. Приобретение оборудования для ИТ-инфраструктуры | G6: 075-00011-НП | I6: =SUM(R6,Z6,AA6) -> 19100 | L6: 2. Серверное оборудование, СХД | M6: Серверное оборудование (отечественного производства - DEPO) | N6: Совершенствование ИТ-инфраструктуры предприятия с учетом импортозамещения | O6: Да | P6: ООО "РК-ЦИФРА" | Q6: =AB6+V6+W6 -> 7500 | R6: =SUM(S6+T6+V6+W6) -> 7500 | T6: 7500 | U6: =IF(ISBLANK(AC6),"",AC6+V6+W6) -> 3674.6697 | X6: июнь | Y6: 2025 | Z6: 7600 | AA6: 4000 | AB6: =SUM(S6:T6) -> 7500 | AC6: 3674.6697 | AD6: =IF(ISBLANK(AC6),"",IF(AB6=0,"Поступлений не планировалось",AC6-AB6)) -> -3825.3303 | AE6: =IF($AB6=0,0,1) -> 1 | AF6: =AC6*100/AB6 -> 48.995595 | AG6: =IF(ISBLANK(AC6),"",AF6-100) -> -51.004405 | AH6: Потребность реализована
A7: ФГУП "НТЦ"Заря" | C7: Инвестиционный_проект | D7: ИТ_оборудование_и_комплектующие_ИП | E7: 42210100. Приобретение, создание, строительство ОС (ИД) | F7: 42210103. Приобретение оборудования для ИТ-инфраструктуры | G7: 075-00011-НП | I7: =SUM(R7,Z7,AA7) -> 7840 | L7: 1. Персональные компьютеры, ноутбуки, мониторы, терминалы | M7: АРМ, Ноутбук,ПЭВМ "ЛИС-40" | N7: Закупка ноутбука | O7: Да | P7: ООО "РК-ЦИФРА" | Q7: =AB7+V7+W7 -> 350 | R7: =SUM(S7+T7+V7+W7) -> 350 | T7: 350 | U7: =IF(ISBLANK(AC7),"",AC7+V7+W7) -> 286.4336 | X7: июнь | Y7: 2025 | Z7: =3050+140 -> 3190 | AA7: 4300 | AB7: =SUM(S7:T7) -> 350 | AC7: 286.4336 | AD7: =IF(ISBLANK(AC7),"",IF(AB7=0,"Поступлений не планировалось",AC7-AB7)) -> -63.5664 | AE7: =IF($AB7=0,0,1) -> 1 | AF7: =AC7*100/AB7 -> 81.838171 | AG7: =IF(ISBLANK(AC7),"",AF7-100) -> -18.161829 | AH7: Потребность реализована
A8: ФГУП "НТЦ"Заря" | C8: Операционный_бюджет | D8: ИТ_оборудование_и_комплектующие | L8: 7. Прочее оборудование | M8: Комплектующие для АРМ | N8: Закупка комплектующих для АРМ | O8: Да | Q8: =AB8+V8+W8 -> 660 | R8: =SUM(S8+T8+V8+W8) -> 660 | T8: 660 | U8: =IF(ISBLANK(AC8),"",AC8+V8+W8) | X8: июнь | Y8: 2025 | Z8: 680 | AA8: 690 | AB8: =SUM(S8:T8) -> 660 | AD8: =IF(ISBLANK(AC8),"",IF(AB8=0,"Поступлений не планировалось",AC8-AB8)) | AE8: =IF($AB8=0,0,1) -> 1 | AF8: =AC8*100/AB8 -> 0 | AG8: =IF(ISBLANK(AC8),"",AF8-100)
A9: ФГУП "НТЦ"Заря" | C9: Операционный_бюджет | D9: Запчасти_и_расходные_материалы_к_ИТ_оборудованию | L9: 6. Печатное оборудование и сканеры | M9: Картриджи для принтеров | N9: Закупка картриджей для принтеров | O9: Да | Q9: =AB9+V9+W9 -> 1200 | R9: =SUM(S9+T9+V9+W9) -> 1200 | U9: =IF(ISBLANK(AC9),"",AC9+V9+W9) | V9: 1200 | X9: сентябрь | Y9: 2025 | Z9: 1500 | AA9: 1600 | AB9: =SUM(S9:T9) -> 0 | AD9: =IF(ISBLANK(AC9),"",IF(AB9=0,"Поступлений не планировалось",AC9-AB9)) | AE9: =IF($AB9=0,0,1) -> 0 | AF9: =AC9*100/AB9 -> #DIV/0! | AG9: =IF(ISBLANK(AC9),"",AF9-100)
A10: ФГУП "НТЦ"Заря" | C10: Операционный_бюджет | D10: ИТ_оборудование_и_комплектующие | L10: 7. Прочее оборудование | M10: Системные блоки | N10: Закупка системных блоков | O10: Да | Q10: =AB10+V10+W10 -> 4000 | R10: =SUM(S10+T10+V10+W10) -> 4000 | U10: =IF(ISBLANK(AC10),"",AC10+V10+W10) | V10: 4000 | X10: сентябрь | Y10: 2025 | Z10: 4300 | AA10: 4500 | AB10: =SUM(S10:T10) -> 0 | AD10: =IF(ISBLANK(AC10),"",IF(AB10=0,"Поступлений не планировалось",AC10-AB10)) | AE10: =IF($AB10=0,0,1) -> 0 | AF10: =AC10*100/AB10 -> #DIV/0! | AG10: =IF(ISBLANK(AC10),"",AF10-100)
A11: ФГУП "НТЦ"Заря" | C11: Операционный_бюджет | D11: Программное_обеспечение_лицензии | L11: 2.2 - Программы обслуживания | M11: БД "Госзаказ" Лицензия | N11: Закупка лицензии БД "Госзаказ" | O11: Нет | Q11: =AB11+V11+W11 -> 100 | R11: =SUM(S11+T11+V11+W11) -> 100 | S11: 100 | U11: =IF(ISBLANK(AC11),"",AC11+V11+W11) | X11: март | Y11: 2025 | Z11: 130 | AA11: 150 | AB11: =SUM(S11:T11) -> 100 | AD11: =IF(ISBLANK(AC11),"",IF(AB11=0,"Поступлений не планировалось",AC11-AB11)) | AE11: =IF($AB11=0,0,1) -> 1 | AF11: =AC11*100/AB11 -> 0 | AG11: =IF(ISBLANK(AC11),"",AF11-100)
A12: ФГУП "НТЦ"Заря" | C12: Операционный_бюджет | D12: Программное_обеспечение_лицензии | K12: 212 | L12: 2.2 - Программы обслуживания | M12: Лицензия Консультант Плюс | N12: Закупка лицензий Когсультант плюс | O12: Нет | P12: ООО "ЭЛКОД" | Q12: =AB12+V12+W12 -> 1000 | R12: =SUM(S12+T12+V12+W12) -> 1000 | U12: =IF(ISBLANK(AC12),"",AC12+V12+W12) -> 2200 | W12: 1000 | X12: ноябрь | Y12: 2025 | Z12: 1100 | AA12: 1200 | AB12: =SUM(S12:T12) -> 0 | AC12: 1200 | AD12: =IF(ISBLANK(AC12),"",IF(AB12=0,"Поступлений не планировалось",AC12-AB12)) -> Поступлений не планировалось | AE12: =IF($AB12=0,0,1) -> 0 | AF12: =AC12*100/AB12 -> #DIV/0! | AG12: =IF(ISBLANK(AC12),"",AF12-100) -> #DIV/0! | AH12: Удорожание лицензий
A13: ФГУП "НТЦ"Заря" | C13: Операционный_бюджет | D13: Программное_обеспечение_лицензии | L13: 2.2 - Программы обслуживания | M13: Автоматизированная система АС ФинПлан | N13: Закупка автоматезированной системы АС ФинПлан | O13: Нет | Q13: =AB13+V13+W13 -> 100 | R13: =SUM(S13+T13+V13+W13) -> 100 | S13: 100 | U13: =IF(ISBLANK(AC13),"",AC13+V13+W13) | X13: март | Y13: 2025 | Z13: 120 | AA13: 140 | AB13: =SUM(S13:T13) -> 100 | AD13: =IF(ISBLANK(AC13),"",IF(AB13=0,"Поступлений не планировалось",AC13-AB13)) | AE13: =IF($AB13=0,0,1) -> 1 | AF13: =AC13*100/AB13 -> 0 | AG13: =IF(ISBLANK(AC13),"",AF13-100)
A14: ФГУП "НТЦ"Заря" | C14: Операционный_бюджет | D14: Программное_обеспечение_лицензии | K14: 20157 | L14: 1.4 - Программное обеспечение интернета вещей, робототехники и сенсорики | M14: Сопровождение сайта | N14: Сопровождение сайта | O14: Нет | Q14: =AB14+V14+W14 -> 700 | R14: =SUM(S14+T14+V14+W14) -> 700 | T14: 700 | U14: =IF(ISBLANK(AC14),"",AC14+V14+W14) | X14: июнь | Y14: 2025 | Z14: 750 | AA14: 900 | AB14: =SUM(S14:T14) -> 700 | AD14: =IF(ISBLANK(AC14),"",IF(AB14=0,"Поступлений не планировалось",AC14-AB14)) | AE14: =IF($AB14=0,0,1) -> 1 | AF14: =AC14*100/AB14 -> 0 | AG14: =IF(ISBLANK(AC14),"",AF14-100)
A15: ФГУП "НТЦ"Заря" | C15: Операционный_бюджет | D15: ИТ_оборудование_и_комплектующие | L15: 7. Прочее оборудование | M15: Оптические диски | N15: Закупка оптических дисков | O15: Да | P15: ИП Столбов Геннадий Сергеевич | Q15: =AB15+V15+W15 -> 90 | R15: =SUM(S15+T15+V15+W15) -> 90 | T15: 90 | U15: =IF(ISBLANK(AC15),"",AC15+V15+W15) -> 50 | X15: июнь | Y15: 2025 | Z15: 100 | AA15: 110 | AB15: =SUM(S15:T15) -> 90 | AC15: 50 | AD15: =IF(ISBLANK(AC15),"",IF(AB15=0,"Поступлений не планировалось",AC15-AB15)) -> -40 | AE15: =IF($AB15=0,0,1) -> 1 | AF15: =AC15*100/AB15 -> 55.555556 | AG15: =IF(ISBLANK(AC15),"",AF15-100) -> -44.444444 | AH15: Укажите причину отклонения
A16: ФГУП "НТЦ"Заря" | C16: Операционный_бюджет | D16: Услуги_связи | L16: 2.2 - Программы обслуживания | M16: Интернет, выделенный канал связи | N16: Интернет, выделенный канал связи | O16: Нет | P16: ООО "Наука-Связь" | Q16: =AB16+V16+W16 -> 1100 | R16: =SUM(S16+T16+V16+W16) -> 1100 | S16: 1100 | U16: =IF(ISBLANK(AC16),"",AC16+V16+W16) -> 546 | X16: март | Y16: 2025 | Z16: 1200 | AA16: 1300 | AB16: =SUM(S16:T16) -> 1100 | AC16: 546 | AD16: =IF(ISBLANK(AC16),"",IF(AB16=0,"Поступлений не планировалось",AC16-AB16)) -> -554 | AE16: =IF($AB16=0,0,1) -> 1 | AF16: =AC16*100/AB16 -> 49.636364 | AG16: =IF(ISBLANK(AC16),"",AF16-100) -> -50.363636 | AH16: Скидка провайдера
A17: ФГУП "НТЦ"Заря" | C17: Операционный_бюджет | D17: Программное_обеспечение_лицензии | L17: 2.2 - Программы обслуживания | M17: Электронный журнал "Финансовый директор" | N17: Закупка электронного журнала "Финансовый директор" | O17: Нет | Q17: =AB17+V17+W17 -> 30 | R17: =SUM(S17+T17+V17+W17) -> 30 | S17: 30 | U17: =IF(ISBLANK(AC17),"",AC17+V17+W17) | X17: март | Y17: 2025 | Z17: 50 | AA17: 70 | AB17: =SUM(S17:T17) -> 30 | AD17: =IF(ISBLANK(AC17),"",IF(AB17=0,"Поступлений не планировалось",AC17-AB17)) | AE17: =IF($AB17=0,0,1) -> 1 | AF17: =AC17*100/AB17 -> 0 | AG17: =IF(ISBLANK(AC17),"",AF17-100)
A18: ФГУП "НТЦ"Заря" | C18: Операционный_бюджет | D18: ИТ_оборудование_и_комплектующие | L18: 7. Прочее оборудование | M18: Мониторы для АРМ | N18: Закупка мониторов для АРМ | O18: Да | Q18: =AB18+V18+W18 -> 1000 | R18: =SUM(S18+T18+V18+W18) -> 1000 | U18: =IF(ISBLANK(AC18),"",AC18+V18+W18) | V18: 1000 | X18: сентябрь | Y18: 2025 | Z18: 1200 | AA18: 1500 | AB18: =SUM(S18:T18) -> 0 | AD18: =IF(ISBLANK(AC18),"",IF(AB18=0,"Поступлений не планировалось",AC18-AB18)) | AE18: =IF($AB18=0,0,1) -> 0 | AF18: =AC18*100/AB18 -> #DIV/0! | AG18: =IF(ISBLANK(AC18),"",AF18-100)
A19: ФГУП "НТЦ"Заря" | C19: Операционный_бюджет | D19: Услуги_внешней_техподдержки | L19: 2.2 - Программы обслуживания | M19: Техническая поддержка UserGate | N19: Техническая поддержка UserGate | O19: Нет | Q19: =AB19+V19+W19 -> 1200 | R19: =SUM(S19+T19+V19+W19) -> 1200 | T19: 1200 | U19: =IF(ISBLANK(AC19),"",AC19+V19+W19) | X19: июнь | Y19: 2025 | Z19: 1400 | AA19: 1600 | AB19: =SUM(S19:T19) -> 1200 | AD19: =IF(ISBLANK(AC19),"",IF(AB19=0,"Поступлений не планировалось",AC19-AB19)) | AE19: =IF($AB19=0,0,1) -> 1 | AF19: =AC19*100/AB19 -> 0 | AG19: =IF(ISBLANK(AC19),"",AF19-100)
A20: ФГУП "НТЦ"Заря" | C20: Операционный_бюджет | D20: Программное_обеспечение_лицензии | L20: 2.2 - Программы обслуживания | M20: Сопровождение 1С | N20: Сопровождение 1С | O20: Да | P20: АО "Организация "Агат" | Q20: =AB20+V20+W20 -> 5500 | R20: =SUM(S20+T20+V20+W20) -> 5500 | U20: =IF(ISBLANK(AC20),"",AC20+V20+W20) -> 8730 | W20: 5500 | X20: ноябрь | Y20: 2025 | Z20: 6000 | AA20: 6500 | AB20: =SUM(S20:T20) -> 0 | AC20: 3230 | AD20: =IF(ISBLANK(AC20),"",IF(AB20=0,"Поступлений не планировалось",AC20-AB20)) -> Поступлений не планировалось | AE20: =IF($AB20=0,0,1) -> 0 | AF20: =AC20*100/AB20 -> #DIV/0! | AG20: =IF(ISBLANK(AC20),"",AF20-100) -> #DIV/0! | AH20: Отказ от модуля 1С:РМ
A21: ФГУП "НТЦ"Заря" | C21: Операционный_бюджет | D21: Программное_обеспечение_лицензии | L21: 2.2 - Программы обслуживания | M21: Сопровождение планово целевого планирования | N21: Сопровождение планово целевого планирования | O21: Да | Q21: =AB21+V21+W21 -> 1100 | R21: =SUM(S21+T21+V21+W21) -> 1100 | T21: 1100 | U21: =IF(ISBLANK(AC21),"",AC21+V21+W21) | X21: июнь | Y21: 2025 | Z21: 1300 | AA21: 1500 | AB21: =SUM(S21:T21) -> 1100 | AD21: =IF(ISBLANK(AC21),"",IF(AB21=0,"Поступлений не планировалось",AC21-AB21)) | AE21: =IF($AB21=0,0,1) -> 1 | AF21: =AC21*100/AB21 -> 0 | AG21: =IF(ISBLANK(AC21),"",AF21-100)
A22: ФГУП "НТЦ"Заря" | C22: Операционный_бюджет | D22: ИТ_оборудование_и_комплектующие | L22: 7. Прочее оборудование | M22: Внедрение системы видеоинформирования | N22: Закупка телевизоров | O22: Да | P22: ООО "МВМ" | Q22: =AB22+V22+W22 -> 600 | R22: =SUM(S22+T22+V22+W22) -> 600 | T22: 600 | U22: =IF(ISBLANK(AC22),"",AC22+V22+W22) -> 98 | X22: июнь | Y22: 2025 | Z22: 200 | AA22: 200 | AB22: =SUM(S22:T22) -> 600 | AC22: 98 | AD22: =IF(ISBLANK(AC22),"",IF(AB22=0,"Поступлений не планировалось",AC22-AB22)) -> -502 | AE22: =IF($AB22=0,0,1) -> 1 | AF22: =AC22*100/AB22 -> 16.333333 | AG22: =IF(ISBLANK(AC22),"",AF22-100) -> -83.666667 | AH22: Потребность реализована
A23: ФГУП "НТЦ"Заря" | C23: Операционный_бюджет | D23: Программное_обеспечение_лицензии | K23: 1247 | L23: 2.2 - Программы обслуживания | M23: Открытая система обработки заявок | N23: Закупка открытой системы обработки заявок | O23: Нет | Q23: =AB23+V23+W23 -> 300 | R23: =SUM(S23+T23+V23+W23) -> 300 | T23: 300 | U23: =IF(ISBLANK(AC23),"",AC23+V23+W23) | X23: июнь | Y23: 2025 | Z23: 400 | AA23: 500 | AB23: =SUM(S23:T23) -> 300 | AD23: =IF(ISBLANK(AC23),"",IF(AB23=0,"Поступлений не планировалось",AC23-AB23)) | AE23: =IF($AB23=0,0,1) -> 1 | AF23: =AC23*100/AB23 -> 0 | AG23: =IF(ISBLANK(AC23),"",AF23-100)
A24: ФГУП "НТЦ"Заря" | C24: Операционный_бюджет | D24: Программное_обеспечение_лицензии | K24: 14647 | L24: 2.2 - Программы обслуживания | M24: Отечественная корпоротивная почта | N24: Закупка отечественной корпоротивной почты | O24: Нет | Q24: =AB24+V24+W24 -> 1000 | R24: =SUM(S24+T24+V24+W24) -> 1000 | T24: 1000 | U24: =IF(ISBLANK(AC24),"",AC24+V24+W24) | X24: июнь | Y24: 2025 | Z24: 120 | AA24: 140 | AB24: =SUM(S24:T24) -> 1000 | AD24: =IF(ISBLANK(AC24),"",IF(AB24=0,"Поступлений не планировалось",AC24-AB24)) | AE24: =IF($AB24=0,0,1) -> 1 | AF24: =AC24*100/AB24 -> 0 | AG24: =IF(ISBLANK(AC24),"",AF24-100)
A25: ФГУП "НТЦ"Заря" | C25: Операционный_бюджет | D25: Программное_обеспечение_лицензии | K25: 5256 | L25: 2.2 - Программы обслуживания | M25: Отечественное офисное приложение | N25: Закупка отечественного офисного приложения | O25: Нет | Q25: =AB25+V25+W25 -> 800 | R25: =SUM(S25+T25+V25+W25) -> 800 | T25: 800 | U25: =IF(ISBLANK(AC25),"",AC25+V25+W25) | X25: июнь | Y25: 2025 | Z25: 300 | AA25: 350 | AB25: =SUM(S25:T25) -> 800 | AD25: =IF(ISBLANK(AC25),"",IF(AB25=0,"Поступлений не планировалось",AC25-AB25)) | AE25: =IF($AB25=0,0,1) -> 1 | AF25: =AC25*100/AB25 -> 0 | AG25: =IF(ISBLANK(AC25),"",AF25-100)
A26: ФГУП "НТЦ"Заря" | C26: Операционный_бюджет | D26: Программное_обеспечение_лицензии | L26: 2.2 - Программы обслуживания | M26: Техническая поддержка для многофункциональных устройств | N26: Техническая поддержка для многофункциональных устройств | O26: Нет | Q26: =AB26+V26+W26 -> 200 | R26: =SUM(S26+T26+V26+W26) -> 200 | T26: 200 | U26: =IF(ISBLANK(AC26),"",AC26+V26+W26) | X26: июнь | Y26: 2025 | Z26: 250 | AA26: 300 | AB26: =SUM(S26:T26) -> 200 | AD26: =IF(ISBLANK(AC26),"",IF(AB26=0,"Поступлений не планировалось",AC26-AB26)) | AE26: =IF($AB26=0,0,1) -> 1 | AF26: =AC26*100/AB26 -> 0 | AG26: =IF(ISBLANK(AC26),"",AF26-100)
A27: ФГУП "НТЦ"Заря" | C27: Операционный_бюджет | D27: Программное_обеспечение_лицензии | L27: 2.2 - Программы обслуживания | M27: Техническая поддержка АТС | N27: Доработка телефонной станции | O27: Нет | Q27: =AB27+V27+W27 -> 500 | R27: =SUM(S27+T27+V27+W27) -> 500 | T27: 500 | U27: =IF(ISBLANK(AC27),"",AC27+V27+W27) | X27: июнь | Y27: 2025 | Z27: 700 | AA27: 850 | AB27: =SUM(S27:T27) -> 500 | AD27: =IF(ISBLANK(AC27),"",IF(AB27=0,"Поступлений не планировалось",AC27-AB27)) | AE27: =IF($AB27=0,0,1) -> 1 | AF27: =AC27*100/AB27 -> 0 | AG27: =IF(ISBLANK(AC27),"",AF27-100)
A28: ФГУП "НТЦ"Заря" | C28: Операционный_бюджет | D28: Программное_обеспечение_лицензии | K28: 113 | L28: 2.2 - Программы обслуживания | M28: Лицензия V-Gate | N28: Внедрение лицензий V-Gate | O28: Да | Q28: =AB28+V28+W28 -> 500 | R28: =SUM(S28+T28+V28+W28) -> 500 | T28: 500 | U28: =IF(ISBLANK(AC28),"",AC28+V28+W28) | X28: июнь | Y28: 2025 | Z28: 120 | AA28: 150 | AB28: =SUM(S28:T28) -> 500 | AD28: =IF(ISBLANK(AC28),"",IF(AB28=0,"Поступлений не планировалось",AC28-AB28)) | AE28: =IF($AB28=0,0,1) -> 1 | AF28: =AC28*100/AB28 -> 0 | AG28: =IF(ISBLANK(AC28),"",AF28-100)
A29: ФГУП "НТЦ "Заря" | C29: Операционный_бюджет | D29: Программное_обеспечение_лицензии | L29: 2.2 - Программы обслуживания | M29: Техническая поддержка АКПШ Континент | N29: Техническая поддержка АКПШ Континент | O29: Нет | Q29: =AB29+V29+W29 -> 350 | R29: =SUM(S29+T29+V29+W29) -> 350 | U29: =IF(ISBLANK(AC29),"",AC29+V29+W29) | V29: 350 | X29: сентябрь | Y29: 2025 | Z29: 370 | AA29: 390 | AB29: =SUM(S29:T29) -> 0 | AD29: =IF(ISBLANK(AC29),"",IF(AB29=0,"Поступлений не планировалось",AC29-AB29)) | AE29: =IF($AB29=0,0,1) -> 0 | AF29: =AC29*100/AB29 -> #DIV/0! | AG29: =IF(ISBLANK(AC29),"",AF29-100)
A30: ФГУП "НТЦ "Заря" | C30: Операционный_бюджет | D30: ИТ_оборудование_и_комплектующие | I30: =Q30 -> 0 | L30: 2. Серверное оборудование, СХД | M30: Источник бесперебойного электропитания для серверов | N30: Закупка источников бесперебойного электропитания для серверов | O30: Да | Q30: =AB30+V30+W30 -> 0 | R30: =SUM(S30+T30+V30+W30) -> 0 | U30: =IF(ISBLANK(AC30),"",AC30+V30+W30) | W30: =200*0 -> 0 | X30: сентябрь | Y30: 2025 | Z30: 200 | AA30: 250 | AB30: =SUM(S30:T30) -> 0 | AD30: =IF(ISBLANK(AC30),"",IF(AB30=0,"Поступлений не планировалось",AC30-AB30)) | AE30: =IF($AB30=0,0,1) -> 0 | AF30: =AC30*100/AB30 -> #DIV/0! | AG30: =IF(ISBLANK(AC30),"",AF30-100)
A31: ФГУП "НТЦ "Заря" | C31: Операционный_бюджет | D31: Программное_обеспечение_лицензии | K31: 11898 | L31: 3.15 - Средства обнаружения угроз и расследования сетевых инцидентов | M31: Закупка подсистемы мониторинга событий информационной безопасности | N31: Поставка неисключительных лицензий на использование подсистема мониторинга событий информационной безопасности MaxPatrol SIEM | O31: Нет | Q31: =AB31+V31+W31 -> 0 | R31: =SUM(S31+T31+V31+W31) -> 0 | U31: =IF(ISBLANK(AC31),"",AC31+V31+W31) | W31: 0 | X31: Каждый квартал | Y31: 2025 | AB31: =SUM(S31:T31) -> 0 | AD31: =IF(ISBLANK(AC31),"",IF(AB31=0,"Поступлений не планировалось",AC31-AB31)) | AE31: =IF($AB31=0,0,1) -> 0 | AF31: =AC31*100/AB31 -> #DIV/0! | AG31: =IF(ISBLANK(AC31),"",AF31-100)
A32: ФГУП "НТЦ "Заря" | C32: Операционный_бюджет | D32: Программное_обеспечение_лицензии | K32: 369 | L32: 1.2 - Встроенные системные программы - операционные системы | M32: Операционная система Astra Linux для серверов | N32: Оказание услуг по предоставлению неисключительных прав (лицензий) на использование отечественной операционной системы Astra Linux 1.7 (серверная) | O32: Да | Q32: =AB32+V32+W32 -> 500 | R32: =SUM(S32+T32+V32+W32) -> 500 | S32: 500 | U32: =IF(ISBLANK(AC32),"",AC32+V32+W32) | X32: июнь | Y32: 2025 | Z32: 300 | AA32: 350 | AB32: =SUM(S32:T32) -> 500 | AD32: =IF(ISBLANK(AC32),"",IF(AB32=0,"Поступлений не планировалось",AC32-AB32)) | AE32: =IF($AB32=0,0,1) -> 1 | AF32: =AC32*100/AB32 -> 0 | AG32: =IF(ISBLANK(AC32),"",AF32-100)
A33: ФГУП "НТЦ "Заря" | C33: Операционный_бюджет | D33: Программное_обеспечение_лицензии | K33: 11953 | L33: 3.17 - Средства автоматизации процессов информационной безопасности | M33: Закупка подсистемы мониторинга событий информационной безопасности | N33: Поставка неисключительных лицензий на использование подсистемы анализа защищенности MaxPatrol VM | O33: Да | Q33: =AB33+V33+W33 -> 4600 | R33: =SUM(S33+T33+V33+W33) -> 4600 | T33: 4600 | U33: =IF(ISBLANK(AC33),"",AC33+V33+W33) | X33: июнь | Y33: 2025 | Z33: 2100 | AA33: 2300 | AB33: =SUM(S33:T33) -> 4600 | AD33: =IF(ISBLANK(AC33),"",IF(AB33=0,"Поступлений не планировалось",AC33-AB33)) | AE33: =IF($AB33=0,0,1) -> 1 | AF33: =AC33*100/AB33 -> 0 | AG33: =IF(ISBLANK(AC33),"",AF33-100)
A34: ФГУП "НТЦ "Заря" | C34: Операционный_бюджет | D34: Программное_обеспечение_лицензии | K34: 4984 | L34: 2.4 - Средства виртуализации | M34: Закупка сертифицированной ФСТЭК России системы виртуализации | N34: Поставка неисключительных лицензий на использование системы виртуализации ZVirt | O34: Да | Q34: =AB34+V34+W34 -> 2200 | R34: =SUM(S34+T34+V34+W34) -> 2200 | T34: 2200 | U34: =IF(ISBLANK(AC34),"",AC34+V34+W34) | X34: июнь | Y34: 2025 | Z34: 700 | AA34: 800 | AB34: =SUM(S34:T34) -> 2200 | AD34: =IF(ISBLANK(AC34),"",IF(AB34=0,"Поступлений не планировалось",AC34-AB34)) | AE34: =IF($AB34=0,0,1) -> 1 | AF34: =AC34*100/AB34 -> 0 | AG34: =IF(ISBLANK(AC34),"",AF34-100)
A35: ФГУП "НТЦ "Заря" | C35: Операционный_бюджет | D35: Программное_обеспечение_лицензии | K35: 369 | L35: 1.2 - Встроенные системные программы - операционные системы | M35: Операционная система Astra Linux для рабочих станций | N35: Оказание услуг по предоставлению неисключительных прав (лицензий) на использование отечественной операционной системы Astra Linux 1.7 (для рабочих станций) | O35: Да | Q35: =AB35+V35+W35 -> 3700 | R35: =SUM(S35+T35+V35+W35) -> 3700 | U35: =IF(ISBLANK(AC35),"",AC35+V35+W35) | V35: 3700 | X35: сентябрь | Y35: 2025 | Z35: 1200 | AA35: 1100 | AB35: =SUM(S35:T35) -> 0 | AD35: =IF(ISBLANK(AC35),"",IF(AB35=0,"Поступлений не планировалось",AC35-AB35)) | AE35: =IF($AB35=0,0,1) -> 0 | AF35: =AC35*100/AB35 -> #DIV/0! | AG35: =IF(ISBLANK(AC35),"",AF35-100)
A36: ФГУП "НТЦ "Заря" | C36: Операционный_бюджет | D36: Программное_обеспечение_лицензии | K36: 6808 | L36: 3.13 - Средства резервного копирования | M36: Средство резервного копирования Кибер Бэкап | N36: Поставка неисключительных прав на использования средства резервного копирования Кибер Бэкап | O36: Да | Q36: =AB36+V36+W36 -> 540 | R36: =SUM(S36+T36+V36+W36) -> 540 | U36: =IF(ISBLANK(AC36),"",AC36+V36+W36) | V36: 540 | X36: сентябрь | Y36: 2025 | Z36: 250 | AA36: 280 | AB36: =SUM(S36:T36) -> 0 | AD36: =IF(ISBLANK(AC36),"",IF(AB36=0,"Поступлений не планировалось",AC36-AB36)) | AE36: =IF($AB36=0,0,1) -> 0 | AF36: =AC36*100/AB36 -> #DIV/0! | AG36: =IF(ISBLANK(AC36),"",AF36-100)
A37: ФГУП "НТЦ "Заря" | C37: Операционный_бюджет | D37: Программное_обеспечение_лицензии | K37: 203 | L37: 3.6 - Средства антивирусной защиты | M37: Kaspersky Security для почтовых сереров | N37: Поставка неисключительных прав на использования средства Kaspersky Security | O37: Да | P37: ООО "РК-ЦИФРА" | Q37: =AB37+V37+W37 -> 560 | R37: =SUM(S37+T37+V37+W37) -> 560 | U37: =IF(ISBLANK(AC37),"",AC37+V37+W37) -> 928 | V37: 560 | X37: сентябрь | Y37: 2025 | Z37: 350 | AA37: 400 | AB37: =SUM(S37:T37) -> 0 | AC37: 368 | AD37: =IF(ISBLANK(AC37),"",IF(AB37=0,"Поступлений не планировалось",AC37-AB37)) -> Поступлений не планировалось | AE37: =IF($AB37=0,0,1) -> 0 | AF37: =AC37*100/AB37 -> #DIV/0! | AG37: =IF(ISBLANK(AC37),"",AF37-100) -> #DIV/0! | AH37: Скидка поставщика
A38: ФГУП "НТЦ "Заря" | C38: Операционный_бюджет | D38: Аренда_оборудования_и_вычислительных_мощностей | L38: 7. Прочее оборудование | M38: Аренда стойко-места под серверное оборудование в ЦОД | N38: Аренда стойко-места под серверное оборудование в ЦОД для развертывания подсистемы мониторинга событий информационной безопасности | O38: Да | Q38: =AB38+V38+W38 -> 1100 | R38: =SUM(S38+T38+V38+W38) -> 1100 | T38: 1100 | U38: =IF(ISBLANK(AC38),"",AC38+V38+W38) | X38: май | Y38: 2025 | Z38: 1300 | AA38: 1500 | AB38: =SUM(S38:T38) -> 1100 | AD38: =IF(ISBLANK(AC38),"",IF(AB38=0,"Поступлений не планировалось",AC38-AB38)) | AE38: =IF($AB38=0,0,1) -> 1 | AF38: =AC38*100/AB38 -> 0 | AG38: =IF(ISBLANK(AC38),"",AF38-100) | AH38: =IF(($AC38=$AB38),"",IF(ISBLANK($AC38),"", "Укажите причину отклонения"))
A39: ФГУП "НТЦ "Заря" | C39: Операционный_бюджет | D39: Ремонт_ИТ_инфраструктуры | L39: 7. Прочее оборудование | M39: Услуга по ремонту | N39: Ремонт сетевого оборудования | O39: Нет | Q39: =AB39+V39+W39 -> 150 | R39: =SUM(S39+T39+V39+W39) -> 150 | U39: =IF(ISBLANK(AC39),"",AC39+V39+W39) | V39: 150 | X39: сентябрь | Y39: 2025 | Z39: 160 | AA39: 160 | AB39: =SUM(S39:T39) -> 0 | AD39: =IF(ISBLANK(AC39),"",IF(AB39=0,"Поступлений не планировалось",AC39-AB39)) | AE39: =IF($AB39=0,0,1) -> 0 | AF39: =AC39*100/AB39 -> #DIV/0! | AG39: =IF(ISBLANK(AC39),"",AF39-100) | AH39: =IF(($AC39=$AB39),"",IF(ISBLANK($AC39),"", "Укажите причину отклонения"))
A40: ФГУП "НТЦ "Заря" | C40: Операционный_бюджет | D40: Ремонт_ИТ_инфраструктуры | L40: 7. Прочее оборудование | M40: Услуга по ремонту | N40: Ремонт каналообразующего оборудования | O40: Нет | Q40: =AB40+V40+W40 -> 200 | R40: =SUM(S40+T40+V40+W40) -> 200 | S40: 50 | T40: 50 | U40: =IF(ISBLANK(AC40),"",AC40+V40+W40) | V40: 50 | W40: 50 | X40: Каждый квартал | Y40: 2025 | Z40: 200 | AA40: 200 | AB40: =SUM(S40:T40) -> 100 | AD40: =IF(ISBLANK(AC40),"",IF(AB40=0,"Поступлений не планировалось",AC40-AB40)) | AE40: =IF($AB40=0,0,1) -> 1 | AF40: =AC40*100/AB40 -> 0 | AG40: =IF(ISBLANK(AC40),"",AF40-100) | AH40: =IF(($AC40=$AB40),"",IF(ISBLANK($AC40),"", "Укажите причину отклонения"))
A41: ФГУП "НТЦ "Заря" | C41: Операционный_бюджет | D41: ИТ_оборудование_и_комплектующие | I41: 3800 | K41: 27104 | L41: Сетевое оборудование | M41: Закупка межсетевого экрана UserGate | N41: Закупка межсетевого экрана для обеспечения защиты периметра предприятия функционирующего UserGate | O41: Да | Q41: =AB41+V41+W41 -> 0 | R41: =SUM(S41+T41+V41+W41) -> 0 | U41: =IF(ISBLANK(AC41),"",AC41+V41+W41) | AB41: =SUM(S41:T41) -> 0 | AD41: =IF(ISBLANK(AC41),"",IF(AB41=0,"Поступлений не планировалось",AC41-AB41)) | AE41: =IF($AB41=0,0,1) -> 0 | AF41: =AC41*100/AB41 -> #DIV/0! | AG41: =IF(ISBLANK(AC41),"",AF41-100) | AH41: =IF(($AC41=$AB41),"",IF(ISBLANK($AC41),"", "Укажите причину отклонения"))
A42: ФГУП "НТЦ "Заря" | C42: Операционный_бюджет | D42: ИТ_оборудование_и_комплектующие | I42: 2000 | L42: Сетевое оборудование | M42: Закупка средств криптографической защиты | N42: Средства криптографической защиты | O42: Да | Q42: =AB42+V42+W42 -> 0 | R42: =SUM(S42+T42+V42+W42) -> 0 | U42: =IF(ISBLANK(AC42),"",AC42+V42+W42) | AB42: =SUM(S42:T42) -> 0 | AD42: =IF(ISBLANK(AC42),"",IF(AB42=0,"Поступлений не планировалось",AC42-AB42)) | AE42: =IF($AB42=0,0,1) -> 0 | AF42: =AC42*100/AB42 -> #DIV/0! | AG42: =IF(ISBLANK(AC42),"",AF42-100) | AH42: =IF(($AC42=$AB42),"",IF(ISBLANK($AC42),"", "Укажите причину отклонения"))
A43: ФГУП "НТЦ "Заря" | C43: Операционный_бюджет | D43: ИТ_оборудование_и_комплектующие | L43: 7. Прочее оборудование | M43: Закупка внешних съёмных носителей | N43: Съёмные носители(флешки) | O43: Да | Q43: =AB43+V43+W43 -> 0 | R43: =SUM(S43+T43+V43+W43) -> 0 | U43: =IF(ISBLANK(AC43),"",AC43+V43+W43) | AB43: =SUM(S43:T43) -> 0 | AD43: =IF(ISBLANK(AC43),"",IF(AB43=0,"Поступлений не планировалось",AC43-AB43)) | AE43: =IF($AB43=0,0,1) -> 0 | AF43: =AC43*100/AB43 -> #DIV/0! | AG43: =IF(ISBLANK(AC43),"",AF43-100) | AH43: =IF(($AC43=$AB43),"",IF(ISBLANK($AC43),"", "Укажите причину отклонения"))
A44: ФГУП "НТЦ "Заря" | C44: Операционный_бюджет | D44: Прочие | M44: Закупка защищенных носителей для электронной подписи | N44: Защищенные носители для электронной подписи | O44: Да | Q44: =AB44+V44+W44 -> 0 | R44: =SUM(S44+T44+V44+W44) -> 0 | U44: =IF(ISBLANK(AC44),"",AC44+V44+W44) | AB44: =SUM(S44:T44) -> 0 | AD44: =IF(ISBLANK(AC44),"",IF(AB44=0,"Поступлений не планировалось",AC44-AB44)) | AE44: =IF($AB44=0,0,1) -> 0 | AF44: =AC44*100/AB44 -> #DIV/0! | AG44: =IF(ISBLANK(AC44),"",AF44-100) | AH44: =IF(($AC44=$AB44),"",IF(ISBLANK($AC44),"", "Укажите причину отклонения"))
A45: ФГУП "НТЦ "Заря" | C45: Операционный_бюджет | D45: Сопровождение_информационных_систем | M45: Продление лицензий систем Битрикс и Аспро | N45: Продление лицензий систем Битрикс и Аспро | O45: Нет | Q45: =AB45+V45+W45 -> 0 | R45: =SUM(S45+T45+V45+W45) -> 0 | U45: =IF(ISBLANK(AC45),"",AC45+V45+W45) | AB45: =SUM(S45:T45) -> 0 | AD45: =IF(ISBLANK(AC45),"",IF(AB45=0,"Поступлений не планировалось",AC45-AB45)) | AE45: =IF($AB45=0,0,1) -> 0 | AF45: =AC45*100/AB45 -> #DIV/0! | AG45: =IF(ISBLANK(AC45),"",AF45-100) | AH45: =IF(($AC45=$AB45),"",IF(ISBLANK($AC45),"", "Укажите причину отклонения"))
A46: ФГУП "НТЦ "Заря" | C46: Операционный_бюджет | D46: ИТ_оборудование_и_комплектующие | L46: 7. Прочее оборудование | M46: Система комплексного анализа защищености | N46: Сканер-ВC | O46: Да | Q46: =AB46+V46+W46 -> 0 | R46: =SUM(S46+T46+V46+W46) -> 0 | U46: =IF(ISBLANK(AC46),"",AC46+V46+W46) | AB46: =SUM(S46:T46) -> 0 | AD46: =IF(ISBLANK(AC46),"",IF(AB46=0,"Поступлений не планировалось",AC46-AB46)) | AE46: =IF($AB46=0,0,1) -> 0 | AF46: =AC46*100/AB46 -> #DIV/0! | AG46: =IF(ISBLANK(AC46),"",AF46-100) | AH46: =IF(($AC46=$AB46),"",IF(ISBLANK($AC46),"", "Укажите причину отклонения"))
A47: ФГУП "НТЦ "Заря" | C47: Операционный_бюджет | D47: ИТ_оборудование_и_комплектующие | L47: 1. Персональные компьютеры, ноутбуки, мониторы, терминалы | M47: Закупка системных блоков для нужд ФГУП "НТЦ "Заря" | N47: Закупка системных блоков | O47: Да | Q47: =AB47+V47+W47 -> 0 | R47: =SUM(S47+T47+V47+W47) -> 0 | U47: =IF(ISBLANK(AC47),"",AC47+V47+W47) | AB47: =SUM(S47:T47) -> 0 | AD47: =IF(ISBLANK(AC47),"",IF(AB47=0,"Поступлений не планировалось",AC47-AB47)) | AE47: =IF($AB47=0,0,1) -> 0 | AF47: =AC47*100/AB47 -> #DIV/0! | AG47: =IF(ISBLANK(AC47),"",AF47-100) | AH47: =IF(($AC47=$AB47),"",IF(ISBLANK($AC47),"", "Укажите причину отклонения"))
A48: ФГУП "НТЦ "Заря" | C48: Операционный_бюджет | D48: ИТ_оборудование_и_комплектующие | L48: 1. Персональные компьютеры, ноутбуки, мониторы, терминалы | M48: Закупка мониторов для нужд ФГУП "НТЦ "Заря" | N48: Закупка мониторов | O48: Да | Q48: =AB48+V48+W48 -> 0 | R48: =SUM(S48+T48+V48+W48) -> 0 | U48: =IF(ISBLANK(AC48),"",AC48+V48+W48) | AB48: =SUM(S48:T48) -> 0 | AD48: =IF(ISBLANK(AC48),"",IF(AB48=0,"Поступлений не планировалось",AC48-AB48)) | AE48: =IF($AB48=0,0,1) -> 0 | AF48: =AC48*100/AB48 -> #DIV/0! | AG48: =IF(ISBLANK(AC48),"",AF48-100) | AH48: =IF(($AC48=$AB48),"",IF(ISBLANK($AC48),"", "Укажите причину отклонения"))
A49: ФГУП "НТЦ "Заря" | C49: Инвестиционный_проект | D49: ИТ_оборудование_и_комплектующие_ИП | E49: 42210100. Приобретение, создание, строительство ОС (ИД) | F49: 42210103. Приобретение оборудования для ИТ-инфраструктуры | G49: 075-00011-НП | I49: =SUM(R49,Z49,AA49) -> 1300 | L49: 7. Прочее оборудование | M49: Закупка МФУ (отечественного производства) | N49: Закупка многофункциональных устройств | O49: Да | Q49: =AB49+V49+W49 -> 1000 | R49: =SUM(S49+T49+V49+W49) -> 1000 | U49: =IF(ISBLANK(AC49),"",AC49+V49+W49) | V49: 1000 | X49: сентябрь | Y49: 2025 | Z49: 300 | AB49: =SUM(S49:T49) -> 0 | AD49: =IF(ISBLANK(AC49),"",IF(AB49=0,"Поступлений не планировалось",AC49-AB49)) | AE49: =IF($AB49=0,0,1) -> 0 | AF49: =AC49*100/AB49 -> #DIV/0! | AG49: =IF(ISBLANK(AC49),"",AF49-100) | AH49: =IF(($AC49=$AB49),"",IF(ISBLANK($AC49),"", "Укажите причину отклонения"))
A50: ФГУП "НТЦ "Заря" | C50: Операционный_бюджет | D50: ИТ_оборудование_и_комплектующие | L50: 7. Прочее оборудование | M50: Закупка HDD для сервера | N50: Закупка запасных HDD для сервера | O50: Нет | Q50: =AB50+V50+W50 -> 110 | R50: =SUM(S50+T50+V50+W50) -> 110 | T50: 50 | U50: =IF(ISBLANK(AC50),"",AC50+V50+W50) | W50: 60 | X50: Каждый квартал | Y50: 2025 | Z50: =110*1.043 -> 114.73 | AA50: =Z50*1.04 -> 119.3192 | AB50: =SUM(S50:T50) -> 50 | AD50: =IF(ISBLANK(AC50),"",IF(AB50=0,"Поступлений не планировалось",AC50-AB50)) | AE50: =IF($AB50=0,0,1) -> 1 | AF50: =AC50*100/AB50 -> 0 | AG50: =IF(ISBLANK(AC50),"",AF50-100) | AH50: =IF(($AC50=$AB50),"",IF(ISBLANK($AC50),"", "Укажите причину отклонения"))
A51: ФГУП "НТЦ "Заря" | C51: Операционный_бюджет | D51: ИТ_оборудование_и_комплектующие | I51: 5000 | L51: 1. Персональные компьютеры, ноутбуки, мониторы, терминалы | M51: Закупка АРМ, серверов, принтеров, Межсетевой экран USERGate D500 | N51: п.1.5 Приложения А Стратегии ЦТ ФГУП "НТЦ "Заря" на период до 2025 года и перспективу до 2030 года | O51: Да | Q51: =AB51+V51+W51 -> 0 | R51: =SUM(S51+T51+V51+W51) -> 0 | U51: =IF(ISBLANK(AC51),"",AC51+V51+W51) | AB51: =SUM(S51:T51) -> 0 | AD51: =IF(ISBLANK(AC51),"",IF(AB51=0,"Поступлений не планировалось",AC51-AB51)) | AE51: =IF($AB51=0,0,1) -> 0 | AF51: =AC51*100/AB51 -> #DIV/0! | AG51: =IF(ISBLANK(AC51),"",AF51-100) | AH51: =IF(($AC51=$AB51),"",IF(ISBLANK($AC51),"", "Укажите причину отклонения"))
A52: ФГУП "НТЦ "Заря" | C52: Инвестиционный_проект | D52: Прочие_ИП | E52: 42210100. Приобретение, создание, строительство ОС (ИД) | F52: 42210103. Приобретение оборудования для ИТ-инфраструктуры | G52: 075-00011-НП | I52: =SUM(R52,Z52,AA52) -> 500 | L52: 7. Прочее оборудование | M52: Закупка сетевого оборудования (отечественного производства) | N52: Закупка сетевого оборудования | Q52: =AB52+V52+W52 -> 500 | R52: =SUM(S52+T52+V52+W52) -> 500 | U52: =IF(ISBLANK(AC52),"",AC52+V52+W52) | V52: 500 | X52: сентябрь | Y52: 2025 | AB52: =SUM(S52:T52) -> 0 | AD52: =IF(ISBLANK(AC52),"",IF(AB52=0,"Поступлений не планировалось",AC52-AB52)) | AE52: =IF($AB52=0,0,1) -> 0 | AF52: =AC52*100/AB52 -> #DIV/0! | AG52: =IF(ISBLANK(AC52),"",AF52-100) | AH52: =IF(($AC52=$AB52),"",IF(ISBLANK($AC52),"", "Укажите причину отклонения"))
A53: ФГУП "НТЦ "Заря" | C53: Операционный_бюджет | D53: Прочие_ИП | E53: 42210100. Приобретение, создание, строительство ОС (ИД) | F53: 42210103. Приобретение оборудования для ИТ-инфраструктуры | I53: =SUM(R53,Z53,AA53) -> 2920 | L53: 7. Прочее оборудование | M53: Создание сети передачи данных с использованием технологии квантового распределения криптографических ключей | N53: Создание сети передачи данных с использованием технологии квантового распределения криптографических ключей | Q53: =AB53+V53+W53 -> 920 | R53: =SUM(S53+T53+V53+W53) -> 920 | U53: =IF(ISBLANK(AC53),"",AC53+V53+W53) | W53: 920 | X53: ноябрь | Y53: 2025 | Z53: 1000 | AA53: 1000 | AB53: =SUM(S53:T53) -> 0 | AD53: =IF(ISBLANK(AC53),"",IF(AB53=0,"Поступлений не планировалось",AC53-AB53)) | AE53: =IF($AB53=0,0,1) -> 0 | AF53: =AC53*100/AB53 -> #DIV/0! | AG53: =IF(ISBLANK(AC53),"",AF53-100) | AH53: =IF(($AC53=$AB53),"",IF(ISBLANK($AC53),"", "Укажите причину отклонения"))
A54: ФГУП "НТЦ "Заря" | C54: Инвестиционный_проект | D54: Прочие_ИП | E54: 42210100. Приобретение, создание, строительство ОС (ИД) | F54: 42210103. Приобретение оборудования для ИТ-инфраструктуры | G54: 075-00011-НП | I54: =SUM(R54,Z54,AA54) -> 1000 | L54: 7. Прочее оборудование | M54: Модули IP-телелефонии | N54: Совершенствование корпоративной телефонной связи | Q54: =AB54+V54+W54 -> 0 | R54: =SUM(S54+T54+V54+W54) -> 0 | U54: =IF(ISBLANK(AC54),"",AC54+V54+W54) | Y54: 2025 | Z54: 1000 | AB54: =SUM(S54:T54) -> 0 | AD54: =IF(ISBLANK(AC54),"",IF(AB54=0,"Поступлений не планировалось",AC54-AB54)) | AE54: =IF($AB54=0,0,1) -> 0 | AF54: =AC54*100/AB54 -> #DIV/0! | AG54: =IF(ISBLANK(AC54),"",AF54-100) | AH54: =IF(($AC54=$AB54),"",IF(ISBLANK($AC54),"", "Укажите причину отклонения"))
A55: ФГУП "НТЦ "Заря" | C55: Инвестиционный_проект | D55: Прочие_ИП | E55: 42210100. Приобретение, создание, строительство ОС (ИД) | F55: 42210103. Приобретение оборудования для ИТ-инфраструктуры | G55: 075-00011-НП | I55: =SUM(R55,Z55,AA55) -> 1100 | L55: 7. Прочее оборудование | M55: Беспроводное сетевое оборудование для офиса | N55: Внедрение Wi-Fi сети предприятия | Q55: =AB55+V55+W55 -> 0 | R55: =SUM(S55+T55+V55+W55) -> 0 | U55: =IF(ISBLANK(AC55),"",AC55+V55+W55) | Y55: 2025 | Z55: 1100 | AB55: =SUM(S55:T55) -> 0 | AD55: =IF(ISBLANK(AC55),"",IF(AB55=0,"Поступлений не планировалось",AC55-AB55)) | AE55: =IF($AB55=0,0,1) -> 0 | AF55: =AC55*100/AB55 -> #DIV/0! | AG55: =IF(ISBLANK(AC55),"",AF55-100) | AH55: =IF(($AC55=$AB55),"",IF(ISBLANK($AC55),"", "Укажите причину отклонения"))
A56: ФГУП "НТЦ "Заря" | C56: Инвестиционный_проект | D56: ИТ_оборудование_и_комплектующие_ИП | E56: 42210100. Приобретение, создание, строительство ОС (ИД) | F56: 42210103. Приобретение оборудования для ИТ-инфраструктуры | G56: 075-00011-НП | I56: =SUM(R56,Z56,AA56) -> 0 | L56: 7. Прочее оборудование | M56: АРМ | N56: Закупка АРМ | O56: Да | Q56: =AB56+V56+W56 -> 0 | U56: =IF(ISBLANK(AC56),"",AC56+V56+W56) | AB56: =SUM(S56:T56) -> 0 | AD56: =IF(ISBLANK(AC56),"",IF(AB56=0,"Поступлений не планировалось",AC56-AB56)) | AE56: =IF($AB56=0,0,1) -> 0 | AF56: =AC56*100/AB56 -> #DIV/0! | AG56: =IF(ISBLANK(AC56),"",AF56-100) | AH56: =IF(($AC56=$AB56),"",IF(ISBLANK($AC56),"", "Укажите причину отклонения"))
A57: ФГУП "НТЦ "Заря" | C57: Инвестиционный_проект | D57: ИТ_оборудование_и_комплектующие_ИП | E57: 42210100. Приобретение, создание, строительство ОС (ИД) | F57: 42210103. Приобретение оборудования для ИТ-инфраструктуры | G57: 075-00011-НП | I57: =SUM(R57,Z57,AA57) -> 0 | L57: 7. Прочее оборудование | M57: ИБП для сервера | N57: Закупка ИБП для сервера | O57: Да | Q57: =AB57+V57+W57 -> 0 | U57: =IF(ISBLANK(AC57),"",AC57+V57+W57) | AB57: =SUM(S57:T57) -> 0 | AD57: =IF(ISBLANK(AC57),"",IF(AB57=0,"Поступлений не планировалось",AC57-AB57)) | AE57: =IF($AB57=0,0,1) -> 0 | AF57: =AC57*100/AB57 -> #DIV/0! | AG57: =IF(ISBLANK(AC57),"",AF57-100) | AH57: =IF(($AC57=$AB57),"",IF(ISBLANK($AC57),"", "Укажите причину отклонения"))
A58: ФГУП "НТЦ "Заря" | C58: Инвестиционный_проект | D58: ИТ_оборудование_и_комплектующие_ИП | E58: 42210100. Приобретение, создание, строительство ОС (ИД) | F58: 42210103. Приобретение оборудования для ИТ-инфраструктуры | G58: 075-00011-НП | I58: =SUM(R58,Z58,AA58) -> 0 | L58: 2. Серверное оборудование, СХД | M58: Серверное оборудование | N58: Закупка серверного оборудования | O58: Да | Q58: =AB58+V58+W58 -> 0 | U58: =IF(ISBLANK(AC58),"",AC58+V58+W58) | AB58: =SUM(S58:T58) -> 0 | AD58: =IF(ISBLANK(AC58),"",IF(AB58=0,"Поступлений не планировалось",AC58-AB58)) | AE58: =IF($AB58=0,0,1) -> 0 | AF58: =AC58*100/AB58 -> #DIV/0! | AG58: =IF(ISBLANK(AC58),"",AF58-100) | AH58: =IF(($AC58=$AB58),"",IF(ISBLANK($AC58),"", "Укажите причину отклонения"))

Sheet План 2026-2028
A1: Наименование организации | B1: Наименование филиала | C1: Источник финансирования | D1: Статья затрат | E1: Код статьи БДДС | F1: Статья БДДС 3 уровень | G1: ID инвестиционного проекта | H1: Отметка о типе проекта | I1: Объем финансирования инвестиционного проекта, всего, тыс. руб. | J1: Пункт мероприятия Программы ЦТ (Стратегии ЦТ) | K1: Номер в реестре отеч ПО | L1: Класс предмета закупки | M1: Предмет закупки | N1: Подробное описание объекта закупки (товара, работы или услуги) | O1: Отметка о закупке у Отраслевого оператора (Да/Нет) | P1: Сумма с НДС, тыс. руб
P2: План 2026 | Q2: 1-й квартал 2026 | R2: 2-й квартал 2026 | S2: 3-й квартал 2026 | T2: 4-й квартал 2026 | U2: Месяц поставки | V2: План 2027 | W2: План 2028 | X2: План 2029
Q3: План | R3: План | S3: План | T3: План | U3: План
A4: 1 | B4: 2 | C4: 3 | D4: 4 | E4: 5 | F4: 6 | G4: 7 | H4: 8 | I4: 9 | J4: 10 | K4: 11 | L4: 12 | M4: 13 | N4: 14 | O4: 15 | P4: 16 | Q4: 17 | R4: 18 | S4: 19 | T4: 20 | U4: 21 | V4: 22 | W4: 23 | X4: 24
A5: ФГУП "НТЦ "Заря" | C5: Инвестиционный_проект | D5: ИТ_оборудование_и_комплектующие_ИП | E5: 42210103 | F5: Приобретение оборудования для ИТ-инфраструктуры | G5: 075-00012-НП | I5: 2100 | L5: 1. Персональные компьютеры, ноутбуки, мониторы, терминалы | M5: Закупка "Обруч 2 " спецпроверенный комплект | N5: Обеспечение защиты гостайны | O5: Нет | P5: =SUM(Q5:T5) -> 1000 | S5: 1000 | U5: сентябрь | V5: 1100
A6: ФГУП "НТЦ"Заря" | C6: Инвестиционный_проект | D6: ИТ_оборудование_и_комплектующие_ИП | E6: 42210103 | F6: Приобретение оборудования для ИТ-инфраструктуры | G6: 075-00012-НП | I6: 7000 | L6: 1. Персональные компьютеры, ноутбуки, мониторы, терминалы | M6: Закупка АРМ в защищенном исполнении (отечественного производства) | N6: Закупка АРМ в защищеном исполнении | O6: Нет | P6: =SUM(Q6:T6) -> 1000 | S6: 1000 | U6: сентябрь | V6: 5400 | W6: 600
A7: ФГУП "НТЦ "Заря" | C7: Инвестиционный_проект | D7: ИТ_оборудование_и_комплектующие_ИП | E7: 42210103 | F7: Приобретение оборудования для ИТ-инфраструктуры | G7: 075-00011-НП | I7: 320 | L7: 7. Прочее оборудование | M7: Закупка консоли для управления серверным оборудованием (отечественного производства) | N7: Закупка консоли для управления серверным оборудованием (отечественного производства) | O7: Да | P7: =SUM(Q7:T7) -> 320 | T7: 320 | U7: октябрь
A8: ФГУП "НТЦ "Заря" | C8: Инвестиционный_проект | D8: ИТ_оборудование_и_комплектующие_ИП | E8: 42210103 | F8: Приобретение оборудования для ИТ-инфраструктуры | G8: 075-00012-НП | I8: 1850 | K8: 27104 | L8: 3. Сетевое и коммуникационное оборудование | M8: Закупка межсетевого экрана (отечественного производства) | N8: Межсетевой экран UserGate | O8: Да | P8: =SUM(Q8:T8) -> 1530 | S8: 1530 | U8: сентябрь
A9: ФГУП "НТЦ"Заря" | C9: Инвестиционный_проект | D9: ИТ_оборудование_и_комплектующие_ИП | E9: 42210103 | F9: Приобретение оборудования для ИТ-инфраструктуры | G9: 075-00011-НП | I9: 2400 | L9: 6. Печатное оборудование и сканеры | M9: Закупка многофункциональных устройств (отечественного производства) | N9: Закупка МФУ для нужд ФГУП "НТЦ "Заря" | O9: Да | P9: =SUM(Q9:T9) -> 2400 | S9: 2400 | U9: сентябрь
A10: ФГУП "НТЦ "Заря" | C10: Инвестиционный_проект | D10: ИТ_оборудование_и_комплектующие_ИП | E10: 42210103 | F10: Приобретение оборудования для ИТ-инфраструктуры | G10: 075-00011-НП | I10: 16300 | L10: 2. Серверное оборудование, СХД | M10: Закупка серверного оборудования (отечественного производства) | N10: Закупка сервера для системы хранения данных, терминального доступа и подсистемы мониторинга событий информационной безопасности | O10: Да | P10: =SUM(Q10:T10) -> 5600 | T10: 5600 | U10: октябрь | V10: 6350 | W10: 8200 | X10: 10250
A11: ФГУП "НТЦ "Заря" | C11: Инвестиционный_проект | D11: ИТ_оборудование_и_комплектующие_ИП | E11: 42210103 | F11: Приобретение оборудования для ИТ-инфраструктуры | G11: 075-00011-НП | I11: 750 | L11: 3. Сетевое и коммуникационное оборудование | M11: Закупка сетевого оборудования (отечественного производства) | N11: Обеспечение бесперебойной работы ФГУП "НТЦ "Заря" | O11: Да | P11: =SUM(Q11:T11) -> 720 | S11: 720 | U11: сентябрь
A12: ФГУП "НТЦ "Заря" | C12: Инвестиционный_проект | D12: Приобретение_ПО | E12: 42210203 | F12: Приобретение ПО | G12: 075-00012-НП | I12: 2700 | K12: 20006 | L12: 3.1 - Средства защиты от несанкционированного доступа к информации | M12: Закупка средств криптографической защиты информации (АПКШ Континент) | N12: Обеспечение безопасности ФГУП "НТЦ "Заря" | O12: Нет | P12: =SUM(Q12:T12) -> 0 | V12: 2700
A13: ФГУП "НТЦ "Заря" | C13: Операционный_бюджет | D13: Аренда_оборудования_и_вычислительных_мощностей | E13: 41210401 | F13: Аренда ИТ-оборудования и вычислительных мощностей | M13: Аренда стойко-места на ММТС-10 | N13: Аренда стойко-места на ММТС-10 для размещения каналообразуюшего оборудования, обеспечение функционирования оборудования, размещение стоек, предоставление производственных ресуросв | O13: Нет | P13: =SUM(Q13:T13) -> 2000 | Q13: 500 | R13: 500 | S13: 500 | T13: 500 | U13: Каждый месяц | V13: 2000 | W13: 2000
A14: ФГУП "НТЦ"Заря" | C14: Операционный_бюджет | D14: Запчасти_и_расходные_материалы_к_ИТ_оборудованию | E14: 41210201 | F14: Оборудование, мебель (малоценное имущество) | M14: Закупка картриджей для принтеров | N14: Закупка картриджей для замены в принтерах в том числе и в НКЦ | O14: Да | P14: =SUM(Q14:T14) -> 2000 | R14: 2000 | U14: апрель | V14: 2400 | W14: 2880 | X14: 3600
A15: ФГУП "НТЦ"Заря" | C15: Операционный_бюджет | D15: Запчасти_и_расходные_материалы_к_ИТ_оборудованию | E15: 41210201 | F15: Оборудование, мебель (малоценное имущество) | M15: Закупка оптических дисков | N15: Закупка оптических дисков для обеспечения информационного обмена | O15: Да | P15: =SUM(Q15:T15) -> 100 | Q15: 100 | U15: февраль | V15: 120 | W15: 140 | X15: 175
A16: ФГУП "НТЦ"Заря" | C16: Операционный_бюджет | D16: Запчасти_и_расходные_материалы_к_ИТ_оборудованию | E16: 41210201 | F16: Оборудование, мебель (малоценное имущество) | M16: Закупка съемых носителей информации | N16: Закупка съемных носителей информации (ЭП, идентификация пользователей и т.д.) | O16: Да | P16: =SUM(Q16:T16) -> 300 | R16: 300 | U16: апрель | V16: 360 | W16: 432 | X16: 540
A17: ФГУП "НТЦ"Заря" | C17: Операционный_бюджет | D17: ИТ_оборудование_и_комплектующие | E17: 41210201 | F17: Оборудование, мебель (малоценное имущество) | L17: 4. Средства связи | M17: Закупка стационарных телефонных аппаратов | N17: Закупка стационарных телефонных аппаратов | O17: Да | P17: =SUM(Q17:T17) -> 300 | R17: 300 | U17: апрель | V17: 350 | W17: 400 | X17: 500
A18: ФГУП "НТЦ "Заря" | C18: Операционный_бюджет | D18: ИТ_оборудование_и_комплектующие | E18: 41210201 | F18: Оборудование, мебель (малоценное имущество) | L18: 7. Прочее оборудование | M18: Закупка АКБ для ИБП | N18: Закупка АКБ для замены выработавших установленный ресурс в ИБП | O18: Нет | P18: =SUM(Q18:T18) -> 200 | Q18: 100 | S18: 100 | U18: сентябрь | V18: 200 | W18: 200 | X18: 250
A19: ФГУП "НТЦ"Заря" | C19: Операционный_бюджет | D19: ИТ_оборудование_и_комплектующие | E19: 41210201 | F19: Оборудование, мебель (малоценное имущество) | L19: 7. Прочее оборудование | M19: Закупка комплектующих для АРМ | N19: Закупка комплектующицих для АРМ и серверов | O19: Да | P19: =SUM(Q19:T19) -> 1500 | S19: 1500 | U19: сентябрь | V19: 1700 | W19: 2000 | X19: 2500
A20: ФГУП "НТЦ"Заря" | C20: Операционный_бюджет | D20: ИТ_оборудование_и_комплектующие | E20: 41210201 | F20: Оборудование, мебель (малоценное имущество) | L20: 1. Персональные компьютеры, ноутбуки, мониторы, терминалы | M20: Закупка мониторов | N20: Закупка мониторов для нужд ФГУП "НТЦ "Заря" | O20: Да | P20: =SUM(Q20:T20) -> 2300 | S20: 2300 | U20: сентябрь | V20: 2700 | W20: 3200 | X20: 4000
A21: ФГУП "НТЦ"Заря" | C21: Операционный_бюджет | D21: ИТ_оборудование_и_комплектующие | E21: 41210201 | F21: Оборудование, мебель (малоценное имущество) | L21: 1. Персональные компьютеры, ноутбуки, мониторы, терминалы | M21: Закупка ноутбуков | N21: Закупка ноутбуков для нужд ФГУП "НТЦ "Заря" | O21: Да | P21: =SUM(Q21:T21) -> 800 | R21: 800 | U21: апрель | V21: 960 | W21: 1150 | X21: 1437.5
A22: ФГУП "НТЦ"Заря" | C22: Операционный_бюджет | D22: ИТ_оборудование_и_комплектующие | E22: 41210201 | F22: Оборудование, мебель (малоценное имущество) | L22: 1. Персональные компьютеры, ноутбуки, мониторы, терминалы | M22: Закупка системных блоков | N22: Закупка системных блоков для нужд "ФГУП НТЦ "Заря" | O22: Да | P22: =SUM(Q22:T22) -> 3400 | S22: 3400 | U22: сентябрь | V22: 4000 | W22: 4800 | X22: 6000
A23: ФГУП "НТЦ"Заря" | C23: Операционный_бюджет | D23: ИТ_оборудование_и_комплектующие | E23: 41210201 | F23: Оборудование, мебель (малоценное имущество) | L23: 4. Средства связи | M23: Совершенствование корпоративной телефонной связи | N23: Закупка модулей IP-телефонии для телефонной станции МиниКом DX-500 | O23: Нет | P23: =SUM(Q23:T23) -> 350 | T23: 350 | U23: октябрь | V23: 600 | W23: 720 | X23: 900
A24: ФГУП "НТЦ "Заря" | C24: Операционный_бюджет | D24: ИТ_оборудование_и_комплектующие | E24: 41210201 | F24: Оборудование, мебель (малоценное имущество) | L24: 3. Сетевое и коммуникационное оборудование | M24: Создание сети передачи данных с использованием технологии квантового распределения криптографических ключей | N24: Создание сети передачи данных с использованием технологии квантового распределения криптографических ключей | O24: Да | P24: =SUM(Q24:T24) -> 1000 | T24: 1000 | U24: октябрь | V24: 1200 | W24: 1500 | X24: 1875
A25: ФГУП "НТЦ"Заря" | C25: Операционный_бюджет | D25: ИТ_оборудование_и_комплектующие | E25: 41210201 | F25: Оборудование, мебель (малоценное имущество) | L25: 7. Прочее оборудование | M25: Закупка комплектующих для оргтехники | N25: Закупка комплектующих для оргтехники | O25: Да | P25: =SUM(Q25:T25) -> 1000 | Q25: 250 | R25: 250 | S25: 250 | T25: 250 | U25: апрель | V25: 1200 | W25: 1400 | X25: 1750
A26: ФГУП "НТЦ"Заря" | C26: Операционный_бюджет | D26: Программное_обеспечение_лицензии | E26: 41210402 | F26: Приобретение прав пользования ПО (лицензии) | K26: 20157 | L26: 9.11 - Средства управления содержимым (CMS), сайты и портальные решения | M26: Доработка и обновление сайта | N26: Закупка средства управления содержимым сайта, SSL-сертификата, доменного имени | O26: Нет | P26: =SUM(Q26:T26) -> 1000 | R26: 1000 | U26: апрель | V26: 1200 | W26: 1440 | X26: 1800
A27: ФГУП "НТЦ"Заря" | C27: Операционный_бюджет | D27: Программное_обеспечение_лицензии | E27: 41210402 | F27: Приобретение прав пользования ПО (лицензии) | K27: 11953 | L27: 3.17 - Средства автоматизации процессов информационной безопасности | M27: Закупка неисключительных прав на использование программного обеспечения анализа защищенности | N27: Закупка MaxPatrol VM | O27: Нет | P27: =SUM(Q27:T27) -> 2000 | T27: 2000 | U27: февраль | V27: 3000 | W27: =V27*0.15+V27 -> 3450 | X27: =W27*1.25 -> 4312.5
A28: ФГУП "НТЦ "Заря" | C28: Операционный_бюджет | D28: Программное_обеспечение_лицензии | E28: 41210402 | F28: Приобретение прав пользования ПО (лицензии) | L28: 1.4 - Программное обеспечение интернета вещей, робототехники и сенсорики | M28: Закупка специализированного программного обеспечения | N28: Специализированное программное обеспечение, содержащие сведения составляющие государственную тайну | O28: Нет | P28: =SUM(Q28:T28) -> 1000 | R28: 1000 | U28: апрель | V28: 1500 | W28: 2000
A29: ФГУП "НТЦ"Заря" | C29: Операционный_бюджет | D29: Программное_обеспечение_лицензии | E29: 41210402 | F29: Приобретение прав пользования ПО (лицензии) | K29: 207 | L29: 3.6 - Средства антивирусной защиты | M29: Закупка средств антивирусной защиты информации | N29: Поставка неисключительных прав на использование антивирусного средства Kaspersky | O29: Нет | P29: =SUM(Q29:T29) -> 600 | S29: 600 | U29: сентябрь | V29: 700 | W29: 800 | X29: 1000
A30: ФГУП "НТЦ"Заря" | C30: Операционный_бюджет | D30: Программное_обеспечение_лицензии | E30: 41210402 | F30: Приобретение прав пользования ПО (лицензии) | K30: 232 | L30: 3.11 - Средства защиты каналов передачи данных, в том числе криптографическими методами | M30: Закупка средств криптографической защиты информации | N30: приобретение неискулючительных прав на использование СКЗИ Континен-АП | O30: Да | P30: =SUM(Q30:T30) -> 150 | R30: 150 | U30: июнь | V30: 150 | W30: 150 | X30: 187.5
A31: ФГУП "НТЦ "Заря" | C31: Операционный_бюджет | D31: Программное_обеспечение_лицензии | E31: 41210402 | F31: Приобретение прав пользования ПО (лицензии) | K31: 8828 | L31: 3.9 - Средства обнаружения и предотвращения утечек информации | M31: Закупка средств обнаружения и предотвращения утечек информации | N31: Программное обеспечение DLP StaffCop | O31: Да | P31: =SUM(Q31:T31) -> 2000 | T31: 2000 | U31: октябрь
A32: ФГУП "НТЦ "Заря" | C32: Операционный_бюджет | D32: Программное_обеспечение_лицензии | E32: 41210402 | F32: Приобретение прав пользования ПО (лицензии) | K32: 369 | L32: 1.2 - Встроенные системные программы - операционные системы | M32: Оказание услуг по предоставлению неисключительных прав (лицензий) на использование отечественной операционной системы Astra Linux (для рабочих станций и серверов) | N32: Оказание услуг по предоставлению неисключительных прав (лицензий) на использование отечественной операционной системы Astra Linux (для рабочих станций и серверов) | O32: Нет | P32: =SUM(Q32:T32) -> 5100 | S32: 5100 | U32: сентябрь | V32: 6080 | W32: 6360 | X32: 7950
A33: ФГУП "НТЦ "Заря" | C33: Операционный_бюджет | D33: Прочие | E33: 41210403 | F33: Услуги связи (связь, интернет) | M33: Услуги связи | N33: Аренда Потока Е 1 | O33: Нет | P33: =SUM(Q33:T33) -> 340 | Q33: 85 | R33: 85 | S33: 85 | T33: 85 | U33: Каждый квартал | V33: 340 | W33: 340
A34: ФГУП "НТЦ "Заря" | C34: Операционный_бюджет | D34: Прочие | E34: 41210403 | F34: Услуги связи (связь, интернет) | M34: Услуги связи | N34: Обеспеспечение функционирования телефона СПТС | O34: Нет | P34: =SUM(Q34:T34) -> 240 | Q34: 60 | R34: 60 | S34: 60 | T34: 60 | U34: Каждый месяц | V34: 240 | W34: 240
A35: ФГУП "НТЦ "Заря" | C35: Операционный_бюджет | D35: Прочие | E35: 41210403 | F35: Услуги связи (связь, интернет) | M35: Услуги связи | N35: Обслуживание в сетях "Атлас", "Исток" | O35: Нет | P35: =SUM(Q35:T35) -> 480 | Q35: 120 | R35: 120 | S35: 120 | T35: 120 | U35: Каждый квартал | V35: 480 | W35: 480
A36: ФГУП "НТЦ "Заря" | C36: Операционный_бюджет | D36: Прочие | E36: 41210403 | F36: Услуги связи (связь, интернет) | M36: Услуги связи | N36: Оказание услуг виртуальных частных сетей на основе сети передачи данных | O36: Нет | P36: =SUM(Q36:T36) -> 100 | Q36: 25 | R36: 25 | S36: 25 | T36: 25 | U36: Каждый квартал | V36: 100 | W36: 100
A37: ФГУП "НТЦ "Заря" | C37: Операционный_бюджет | D37: Прочие | E37: 41210403 | F37: Услуги связи (связь, интернет) | M37: Услуги связи | N37: Оказание услуг виртуальных частных сетей на основе сети передачи данных (VPN L3, Минобороны России) | O37: Нет | P37: =SUM(Q37:T37) -> 100 | Q37: 25 | R37: 25 | S37: 25 | T37: 25 | U37: Каждый квартал | V37: 25 | W37: 25
A38: ФГУП "НТЦ "Заря" | C38: Операционный_бюджет | D38: Прочие | E38: 41210403 | F38: Услуги связи (связь, интернет) | M38: Услуги связи | N38: Предоставление в пользование канала (MPLS L2VPN) | O38: Нет | P38: =SUM(Q38:T38) -> 440 | Q38: 110 | R38: 110 | S38: 110 | T38: 110 | U38: Каждый квартал | V38: 440 | W38: 440
A39: ФГУП "НТЦ "Заря" | C39: Операционный_бюджет | D39: Прочие | E39: 41210403 | F39: Услуги связи (связь, интернет) | M39: Услуги связи | N39: Услуги связи ОАО "КОМКОР" | O39: Нет | P39: =SUM(Q39:T39) -> 260 | Q39: 65 | R39: 65 | S39: 65 | T39: 65 | U39: Каждый квартал | V39: 260 | W39: 260
A40: ФГУП "НТЦ "Заря" | C40: Операционный_бюджет | D40: Прочие | E40: 41210403 | F40: Услуги связи (связь, интернет) | M40: Услуги связи | N40: Услуги связи ПАО "Ростелеком" | O40: Нет | P40: =SUM(Q40:T40) -> 80 | Q40: 20 | R40: 20 | S40: 20 | T40: 20 | U40: Каждый квартал | V40: 80 | W40: 80
A41: ФГУП "НТЦ "Заря" | C41: Операционный_бюджет | D41: Ремонт_ИТ_инфраструктуры | E41: 41210499 | F41: Прочие ИТ-услуги | M41: Ремонт оборудования специальной связи | N41: Ремонт оборудования специальной связи | O41: Нет | P41: =SUM(Q41:T41) -> 400 | R41: 400 | U41: апрель | V41: 480 | W41: 576
A42: ФГУП "НТЦ"Заря" | C42: Операционный_бюджет | D42: Ремонт_ИТ_инфраструктуры | E42: 41210499 | F42: Прочие ИТ-услуги | M42: Услуги по ремонту | N42: Ремонт оборудования оргтехники | O42: Нет | P42: =SUM(Q42:T42) -> 400 | Q42: 100 | R42: 100 | S42: 100 | T42: 100 | U42: Каждый месяц | V42: 400 | W42: 500
A43: ФГУП "НТЦ"Заря" | C43: Операционный_бюджет | D43: Сопровождение_информационных_систем | E43: 41210501 | F43: Консультационные, юридические, аудиторские, информационные услуги | K43: 212 | L43: 5.14 - Справочно-правовые системы | M43: Закупка лицензий Консультант Плюс | N43: Поставка неисключительных прав на использование справочно-правовой системы Консультант Плюс | O43: Нет | P43: =SUM(Q43:T43) -> 1700 | S43: 1700 | U43: сентябрь | V43: 1920 | W43: 2300 | X43: 2875
A44: ФГУП "НТЦ"Заря" | C44: Операционный_бюджет | D44: Услуги_внешней_техподдержки | E44: 41210501 | F44: Консультационные, юридические, аудиторские, информационные услуги | M44: Продление технической поддерки средств защиты информации | N44: Продление тезнической поддкрски средств защиты информации (АПКШ Континент, МЭ UserGate, vGate и т.д.) | O44: Да | P44: =SUM(Q44:T44) -> 1600 | S44: 1600 | U44: сентябрь | V44: 2200 | W44: 2600 | X44: 3250
A45: ФГУП "НТЦ"Заря" | C45: Операционный_бюджет | D45: Услуги_внешней_техподдержки | E45: 41210501 | F45: Консультационные, юридические, аудиторские, информационные услуги | M45: Сопровождение информационных систем для системы управления проектами | N45: Сопровождение информационных систем для системы управления проектами | O45: Нет | P45: =SUM(Q45:T45) -> 1000 | R45: 1000 | U45: апрель | V45: 1100 | W45: 1200
A46: ФГУП "НТЦ"Заря" | C46: Операционный_бюджет | D46: Услуги_внешней_техподдержки | E46: 41210501 | F46: Консультационные, юридические, аудиторские, информационные услуги | M46: Сопровождение информационных систем на базе программных продуктов 1С | N46: Сопровождение информационных систем на базе программных продуктов "1С: Зарплата и Управление персоналом", "1С: Бухгалтерия предприятия", "1С: Документооборот" | O46: Нет | P46: =SUM(Q46:T46) -> 5500 | R46: 5500 | U46: апрель | V46: 6600 | W46: 7920 | X46: 9900
A47: ФГУП "НТЦ"Заря" | C47: Операционный_бюджет | D47: Услуги_внешней_техподдержки | E47: 41210501 | F47: Консультационные, юридические, аудиторские, информационные услуги | K47: 11774 | M47: Сопровождение информационных систем на базе программных продуктов HRLink | N47: Сопровождение информационных систем на базе программных продуктов HRLink | O47: Нет | P47: =SUM(Q47:T47) -> 700 | R47: 700 | U47: апрель | V47: 800 | W47: 900
A48: ФГУП "НТЦ"Заря" | C48: Операционный_бюджет | D48: Услуги_связи | E48: 41210403 | F48: Услуги связи (связь, интернет) | M48: Закупка услуг по доступу к сети Интернет | N48: Закупка услуг по доступу к сети Интернет в инфтесах ФГУП "НТЦ "Заря" | O48: Нет | P48: =SUM(Q48:T48) -> 520 | Q48: 130 | R48: 130 | S48: 130 | T48: 130 | U48: Каждый месяц | V48: 600 | W48: 700 | X48: 875

Sheet Программа ЦТ
B2: Код | C2: Направление программы /мероприятие | K2: Дата начала реализации | M2: Дата окончания реализации | O2: Отметка о проведении работ собственными силами | P2: 2024 | Q2: 2025 | R2: 2026 | S2: 2027
K3: месяц | L3: год | M3: месяц | N3: год
B4: 1 | C4: Цифровая система управления | P4: =SUM(P5:P9) -> 0 | Q4: =SUM(Q5:Q9) -> 0 | R4: =SUM(R5:R9) -> 0 | S4: =SUM(S5:S9) -> 0
B5: 1.1
B6: 1.2
B7: 1.3
B8: 1.4
B9: 1.5
B10: 2 | C10: Цифровизации производства и жизненного цикла изделий | P10: =SUM(P11:P15) -> 0 | Q10: =SUM(Q11:Q15) -> 0 | R10: =SUM(R11:R15) -> 0 | S10: =SUM(S11:S15) -> 0
B11: 2.1
B12: 2.2
B13: 2.3
B14: 2.4
B15: 2.5
B16: 3 | C16: Цифровая система управления данными | P16: =SUM(P17:P23) -> 0 | Q16: =SUM(Q17:Q23) -> 0 | R16: =SUM(R17:R23) -> 0 | S16: =SUM(S17:S23) -> 0
B17: 3.1
B18: 3.2
B19: 3.3
B20: 3.4
B21: 3.5
B22: 3.6
B23: 3.7
B24: 4 | C24: Цифровые компетенции персонала | O24: =IF(COUNTIFS('План Факт 2025'!$J$5:$J$58,'Программа ЦТ'!$D24,'План Факт 2025'!$C$5:$C$58,"ФОТ")>0,"Собственные силы","") | P24: =SUM(P25:P29) -> 0 | Q24: =SUM(Q25:Q29) -> 0 | R24: =SUM(R25:R29) -> 0 | S24: =SUM(S25:S29) -> 0
B25: 4.1
B26: 4.2
B27: 4.3
B28: 4.4
B29: 4.5
B30: 5 | C30: Импортозамещение | O30: =IF(COUNTIFS('План Факт 2025'!$J$5:$J$58,'Программа ЦТ'!$D30,'План Факт 2025'!$C$5:$C$58,"ФОТ")>0,"Собственные силы","") | P30: =SUM(P31:P37) -> 0 | Q30: =SUM(Q31:Q37) -> 0 | R30: =SUM(R31:R37) -> 0 | S30: =SUM(S31:S37) -> 0
B31: 5.1
B32: 5.2
B33: 5.3
B34: 5.4
B35: 5.5
B36: 5.6
B37: 5.7
B38: 6 | C38: Обеспечение безопасности информации (данных) и ИТ-инфраструктуры | O38: =IF(COUNTIFS('План Факт 2025'!$J$5:$J$58,'Программа ЦТ'!$D38,'План Факт 2025'!$C$5:$C$58,"ФОТ")>0,"Собственные силы","") | P38: =SUM(P39:P45) -> 0 | Q38: =SUM(Q39:Q45) -> 0 | R38: =SUM(R39:R45) -> 0 | S38: =SUM(S39:S45) -> 0
B39: 6.1
B40: 6.2
B41: 6.3
B42: 6.4
B43: 6.5
B44: 6.6
B45: 6.7
B46: ИТОГО | D46: ИТОГО | P46: =P38+P30+P24+P16+P10+P4 -> 0 | Q46: =Q38+Q30+Q24+Q16+Q10+Q4 -> 0 | R46: =R38+R30+R24+R16+R10+R4 -> 0 | S46: =S38+S30+S24+S16+S10+S4 -> 0

Sheet Свод ДДС
A1: № п/п | C1: Бюджет ДДС в части ИТ и цифровизации | D1: План 2026 | E1: План 2027 | F1: План 2028 | G1: План 2029
A2: 1 | B2: Операционные затраты | D2: =SUM(D3:D12) -> 40960 | E2: =SUM(E3:E12) -> 46485 | F2: =SUM(F3:F12) -> 53683 | G2: =SUM(G3:G12) -> 55677.5
A3: 1.1 | C3: Программное_обеспечение_лицензии | D3: =SUMIF('План 2026-2028'!$D$5:$D$58,'Свод ДДС'!$C3,'План 2026-2028'!$P$5:$P$58) -> 11850 | E3: =SUMIF('План 2026-2028'!$D$5:$D$58,'Свод ДДС'!$C3,'План 2026-2028'!$V$5:$V$58) -> 12630 | F3: =SUMIF('План 2026-2028'!$D$5:$D$58,'Свод ДДС'!$C3,'План 2026-2028'!$W$5:$W$58) -> 14200 | G3: =SUMIF('План 2026-2028'!$D$5:$D$58,'Свод ДДС'!$C3,'План 2026-2028'!$X$5:$X$58) -> 15250
A4: 1.2 | C4: ИТ_оборудование_и_комплектующие | D4: =SUMIF('План 2026-2028'!$D$5:$D$58,'Свод ДДС'!$C4,'План 2026-2028'!$P$5:$P$58) -> 10850 | E4: =SUMIF('План 2026-2028'!$D$5:$D$58,'Свод ДДС'!$C4,'План 2026-2028'!$V$5:$V$58) -> 12910 | F4: =SUMIF('План 2026-2028'!$D$5:$D$58,'Свод ДДС'!$C4,'План 2026-2028'!$W$5:$W$58) -> 15370 | G4: =SUMIF('План 2026-2028'!$D$5:$D$58,'Свод ДДС'!$C4,'План 2026-2028'!$X$5:$X$58) -> 19212.5
A5: 1.3 | C5: Запчасти_и_расходные_материалы_к_ИТ_оборудованию | D5: =SUMIF('План 2026-2028'!$D$5:$D$58,'Свод ДДС'!$C5,'План 2026-2028'!$P$5:$P$58) -> 2400 | E5: =SUMIF('План 2026-2028'!$D$5:$D$58,'Свод ДДС'!$C5,'План 2026-2028'!$V$5:$V$58) -> 2880 | F5: =SUMIF('План 2026-2028'!$D$5:$D$58,'Свод ДДС'!$C5,'План 2026-2028'!$W$5:$W$58) -> 3452 | G5: =SUMIF('План 2026-2028'!$D$5:$D$58,'Свод ДДС'!$C5,'План 2026-2028'!$X$5:$X$58) -> 4315
A6: 1.4 | C6: Услуги_внешней_техподдержки | D6: =SUMIF('План 2026-2028'!$D$5:$D$58,'Свод ДДС'!$C6,'План 2026-2028'!$P$5:$P$58) -> 8800 | E6: =SUMIF('План 2026-2028'!$D$5:$D$58,'Свод ДДС'!$C6,'План 2026-2028'!$V$5:$V$58) -> 10700 | F6: =SUMIF('План 2026-2028'!$D$5:$D$58,'Свод ДДС'!$C6,'План 2026-2028'!$W$5:$W$58) -> 12620 | G6: =SUMIF('План 2026-2028'!$D$5:$D$58,'Свод ДДС'!$C6,'План 2026-2028'!$X$5:$X$58) -> 13150
A7: 1.5 | C7: Ремонт_ИТ_инфраструктуры | D7: =SUMIF('План 2026-2028'!$D$5:$D$58,'Свод ДДС'!$C7,'План 2026-2028'!$P$5:$P$58) -> 800 | E7: =SUMIF('План 2026-2028'!$D$5:$D$58,'Свод ДДС'!$C7,'План 2026-2028'!$V$5:$V$58) -> 880 | F7: =SUMIF('План 2026-2028'!$D$5:$D$58,'Свод ДДС'!$C7,'План 2026-2028'!$W$5:$W$58) -> 1076 | G7: =SUMIF('План 2026-2028'!$D$5:$D$58,'Свод ДДС'!$C7,'План 2026-2028'!$X$5:$X$58) -> 0
A8: 1.6 | C8: Аренда_оборудования_и_вычислительных_мощностей | D8: =SUMIF('План 2026-2028'!$D$5:$D$58,'Свод ДДС'!$C8,'План 2026-2028'!$P$5:$P$58) -> 2000 | E8: =SUMIF('План 2026-2028'!$D$5:$D$58,'Свод ДДС'!$C8,'План 2026-2028'!$V$5:$V$58) -> 2000 | F8: =SUMIF('План 2026-2028'!$D$5:$D$58,'Свод ДДС'!$C8,'План 2026-2028'!$W$5:$W$58) -> 2000 | G8: =SUMIF('План 2026-2028'!$D$5:$D$58,'Свод ДДС'!$C8,'План 2026-2028'!$X$5:$X$58) -> 0
A9: 1.7 | C9: Услуги_связи | D9: =SUMIF('План 2026-2028'!$D$5:$D$58,'Свод ДДС'!$C9,'План 2026-2028'!$P$5:$P$58) -> 520 | E9: =SUMIF('План 2026-2028'!$D$5:$D$58,'Свод ДДС'!$C9,'План 2026-2028'!$V$5:$V$58) -> 600 | F9: =SUMIF('План 2026-2028'!$D$5:$D$58,'Свод ДДС'!$C9,'План 2026-2028'!$W$5:$W$58) -> 700 | G9: =SUMIF('План 2026-2028'!$D$5:$D$58,'Свод ДДС'!$C9,'План 2026-2028'!$X$5:$X$58) -> 875
A10: 1.8 | C10: Услуги_по_внедрению_информационных_систем_(непроектные) | D10: =SUMIF('План 2026-2028'!$D$5:$D$58,'Свод ДДС'!$C10,'План 2026-2028'!$P$5:$P$58) -> 0 | E10: =SUMIF('План 2026-2028'!$D$5:$D$58,'Свод ДДС'!$C10,'План 2026-2028'!$V$5:$V$58) -> 0 | F10: =SUMIF('План 2026-2028'!$D$5:$D$58,'Свод ДДС'!$C10,'План 2026-2028'!$W$5:$W$58) -> 0 | G10: =SUMIF('План 2026-2028'!$D$5:$D$58,'Свод ДДС'!$C10,'План 2026-2028'!$X$5:$X$58) -> 0
A11: 1.9 | C11: Сопровождение_информационных_систем | D11: =SUMIF('План 2026-2028'!$D$5:$D$58,'Свод ДДС'!$C11,'План 2026-2028'!$P$5:$P$58) -> 1700 | E11: =SUMIF('План 2026-2028'!$D$5:$D$58,'Свод ДДС'!$C11,'План 2026-2028'!$V$5:$V$58) -> 1920 | F11: =SUMIF('План 2026-2028'!$D$5:$D$58,'Свод ДДС'!$C11,'План 2026-2028'!$W$5:$W$58) -> 2300 | G11: =SUMIF('План 2026-2028'!$D$5:$D$58,'Свод ДДС'!$C11,'План 2026-2028'!$X$5:$X$58) -> 2875
A12: 1.10 | C12: Прочие | D12: =SUMIF('План 2026-2028'!$D$5:$D$58,'Свод ДДС'!$C12,'План 2026-2028'!$P$5:$P$58) -> 2040 | E12: =SUMIF('План 2026-2028'!$D$5:$D$58,'Свод ДДС'!$C12,'План 2026-2028'!$V$5:$V$58) -> 1965 | F12: =SUMIF('План 2026-2028'!$D$5:$D$58,'Свод ДДС'!$C12,'План 2026-2028'!$W$5:$W$58) -> 1965 | G12: =SUMIF('План 2026-2028'!$D$5:$D$58,'Свод ДДС'!$C12,'План 2026-2028'!$X$5:$X$58) -> 0
A13: 2 | B13: Инвестиционные проекты | D13: =SUM(D14:D17) -> 12570 | E13: =SUM(E14:E17) -> 15550 | F13: =SUM(F14:F17) -> 8800 | G13: =SUM(G14:G17) -> 10250
A14: 2.1 | C14: Приобретение_ПО | D14: =SUMIF('План 2026-2028'!$D$5:$D$58,'Свод ДДС'!$C14,'План 2026-2028'!$P$5:$P$58) -> 0 | E14: =SUMIF('План 2026-2028'!$D$5:$D$58,'Свод ДДС'!$C14,'План 2026-2028'!$V$5:$V$58) -> 2700 | F14: =SUMIF('План 2026-2028'!$D$5:$D$58,'Свод ДДС'!$C14,'План 2026-2028'!$W$5:$W$58) -> 0 | G14: =SUMIF('План 2026-2028'!$D$5:$D$58,'Свод ДДС'!$C14,'План 2026-2028'!$X$5:$X$58) -> 0
A15: 2.2 | C15: ИТ_оборудование_и_комплектующие_ИП | D15: =SUMIF('План 2026-2028'!$D$5:$D$58,'Свод ДДС'!$C15,'План 2026-2028'!$P$5:$P$58) -> 12570 | E15: =SUMIF('План 2026-2028'!$D$5:$D$58,'Свод ДДС'!$C15,'План 2026-2028'!$V$5:$V$58) -> 12850 | F15: =SUMIF('План 2026-2028'!$D$5:$D$58,'Свод ДДС'!$C15,'План 2026-2028'!$W$5:$W$58) -> 8800 | G15: =SUMIF('План 2026-2028'!$D$5:$D$58,'Свод ДДС'!$C15,'План 2026-2028'!$X$5:$X$58) -> 10250
A16: 2.3 | C16: Услуги_сторонних_организаций | D16: =SUMIF('План 2026-2028'!$D$5:$D$58,'Свод ДДС'!$C16,'План 2026-2028'!$P$5:$P$58) -> 0 | E16: =SUMIF('План 2026-2028'!$D$5:$D$58,'Свод ДДС'!$C16,'План 2026-2028'!$V$5:$V$58) -> 0 | F16: =SUMIF('План 2026-2028'!$D$5:$D$58,'Свод ДДС'!$C16,'План 2026-2028'!$W$5:$W$58) -> 0 | G16: =SUMIF('План 2026-2028'!$D$5:$D$58,'Свод ДДС'!$C16,'План 2026-2028'!$X$5:$X$58) -> 0
A17: 2.4 | C17: Прочие_ИП | D17: =SUMIF('План 2026-2028'!$D$5:$D$58,'Свод ДДС'!$C17,'План 2026-2028'!$P$5:$P$58) -> 0 | E17: =SUMIF('План 2026-2028'!$D$5:$D$58,'Свод ДДС'!$C17,'План 2026-2028'!$V$5:$V$58) -> 0 | F17: =SUMIF('План 2026-2028'!$D$5:$D$58,'Свод ДДС'!$C17,'План 2026-2028'!$W$5:$W$58) -> 0 | G17: =SUMIF('План 2026-2028'!$D$5:$D$58,'Свод ДДС'!$C17,'План 2026-2028'!$X$5:$X$58) -> 0
A18: ИТОГО | D18: =D2+D13 -> 53530 | E18: =E2+E13 -> 62035 | F18: =F2+F13 -> 62483 | G18: =G2+G13 -> 65927.5
A19: в т.ч. закупки у Отраслевого оператора | D19: =SUMIF('План Факт 2025'!$O$5:$O$58,"да",'План Факт 2025'!$Q$5:$Q$58) -> 38200 | E19: =SUMIF('План 2026-2028'!$O$5:$O$58,"да",'План 2026-2028'!$V$5:$V$58) -> 23690 | F19: =SUMIF('План 2026-2028'!$O$5:$O$58,"да",'План 2026-2028'!$W$5:$W$58) -> 28852 | G19: =SUMIF('План 2026-2028'!$O$5:$O$58,"да",'План 2026-2028'!$X$5:$X$58) -> 36065
D20: =IFERROR(D19/D18,"") -> 0.71361853 | E20: =IFERROR(E19/E18,"") -> 0.3818812 | F20: =IFERROR(F19/F18,"") -> 0.4617576 | G20: =IFERROR(G19/G18,"") -> 0.54704031
A21: в т.ч. Инвестиционные проекты | D21: =SUM(D22:D32) -> 10850 | E21: =SUM(E22:E32) -> 15550 | F21: =SUM(F22:F32) -> 8800 | G21: =SUM(G22:G32) -> 10250
C22: {=IFERROR(INDEX('План Факт 2025'!$G$5:$G$30, MATCH(0,COUNTIF($C$21:C21,'План Факт 2025'!$G$5:$G$30&"") + IF('План Факт 2025'!$G$5:$G$30="",1,0), 0)), "")} -> 075-00011-НП | D22: =IF(C22<>"",SUMIF('План Факт 2025'!$G$5:$G$58,'Свод ДДС'!$C22,'План Факт 2025'!$Q$5:$Q$58),"") -> 10850 | E22: =IF(C22<>"",SUMIF('План 2026-2028'!$G$5:$G$14,'Свод ДДС'!$C22,'План 2026-2028'!$V$5:$V$58),"") -> 6350 | F22: =IF(C22<>"",SUMIF('План 2026-2028'!$G$5:$G$14,'Свод ДДС'!$C22,'План 2026-2028'!$W$5:$W$58),"") -> 8200 | G22: =IF(C22<>"",SUMIF('План 2026-2028'!$G$5:$G$14,'Свод ДДС'!$C22,'План 2026-2028'!$X$5:$X$58),"") -> 10250
C23: 075-00012-НП | D23: =IF(C23<>"",SUMIF('План Факт 2025'!$G$5:$G$58,'Свод ДДС'!$C23,'План Факт 2025'!$Q$5:$Q$58),"") -> 0 | E23: =IF(C23<>"",SUMIF('План 2026-2028'!$G$5:$G$14,'Свод ДДС'!$C23,'План 2026-2028'!$V$5:$V$58),"") -> 9200 | F23: =IF(C23<>"",SUMIF('План 2026-2028'!$G$5:$G$14,'Свод ДДС'!$C23,'План 2026-2028'!$W$5:$W$58),"") -> 600 | G23: =IF(C23<>"",SUMIF('План 2026-2028'!$G$5:$G$14,'Свод ДДС'!$C23,'План 2026-2028'!$X$5:$X$58),"") -> 0
C24: {=IFERROR(INDEX('План Факт 2025'!$G$5:$G$30, MATCH(0,COUNTIF($C$21:C23,'План Факт 2025'!$G$5:$G$30&"") + IF('План Факт 2025'!$G$5:$G$30="",1,0), 0)), "")} | D24: =IF(C24<>"",SUMIF('План Факт 2025'!$G$5:$G$58,'Свод ДДС'!$C24,'План Факт 2025'!$Q$5:$Q$58),"") | E24: =IF(C24<>"",SUMIF('План 2026-2028'!$G$5:$G$14,'Свод ДДС'!$C24,'План 2026-2028'!$V$5:$V$58),"") | F24: =IF(C24<>"",SUMIF('План 2026-2028'!$G$5:$G$14,'Свод ДДС'!$C24,'План 2026-2028'!$W$5:$W$58),"") | G24: =IF(C24<>"",SUMIF('План 2026-2028'!$G$5:$G$14,'Свод ДДС'!$C24,'План 2026-2028'!$X$5:$X$58),"")
C25: {=IFERROR(INDEX('План Факт 2025'!$G$5:$G$30, MATCH(0,COUNTIF($C$21:C24,'План Факт 2025'!$G$5:$G$30&"") + IF('План Факт 2025'!$G$5:$G$30="",1,0), 0)), "")} | D25: =IF(C25<>"",SUMIF('План Факт 2025'!$G$5:$G$58,'Свод ДДС'!$C25,'План Факт 2025'!$Q$5:$Q$58),"") | E25: =IF(C25<>"",SUMIF('План 2026-2028'!$G$5:$G$14,'Свод ДДС'!$C25,'План 2026-2028'!$V$5:$V$58),"") | F25: =IF(C25<>"",SUMIF('План 2026-2028'!$G$5:$G$14,'Свод ДДС'!$C25,'План 2026-2028'!$W$5:$W$58),"") | G25: =IF(C25<>"",SUMIF('План 2026-2028'!$G$5:$G$14,'Свод ДДС'!$C25,'План 2026-2028'!$X$5:$X$58),"")
C26: {=IFERROR(INDEX('План Факт 2025'!$G$5:$G$30, MATCH(0,COUNTIF($C$21:C25,'План Факт 2025'!$G$5:$G$30&"") + IF('План Факт 2025'!$G$5:$G$30="",1,0), 0)), "")} | D26: =IF(C26<>"",SUMIF('План Факт 2025'!$G$5:$G$58,'Свод ДДС'!$C26,'План Факт 2025'!$Q$5:$Q$58),"") | E26: =IF(C26<>"",SUMIF('План 2026-2028'!$G$5:$G$14,'Свод ДДС'!$C26,'План 2026-2028'!$V$5:$V$58),"") | F26: =IF(C26<>"",SUMIF('План 2026-2028'!$G$5:$G$14,'Свод ДДС'!$C26,'План 2026-2028'!$W$5:$W$58),"") | G26: =IF(C26<>"",SUMIF('План 2026-2028'!$G$5:$G$14,'Свод ДДС'!$C26,'План 2026-2028'!$X$5:$X$58),"")
C27: {=IFERROR(INDEX('План Факт 2025'!$G$5:$G$30, MATCH(0,COUNTIF($C$21:C26,'План Факт 2025'!$G$5:$G$30&"") + IF('План Факт 2025'!$G$5:$G$30="",1,0), 0)), "")} | D27: =IF(C27<>"",SUMIF('План Факт 2025'!$G$5:$G$58,'Свод ДДС'!$C27,'План Факт 2025'!$Q$5:$Q$58),"") | E27: =IF(C27<>"",SUMIF('План 2026-2028'!$G$5:$G$14,'Свод ДДС'!$C27,'План 2026-2028'!$V$5:$V$58),"") | F27: =IF(C27<>"",SUMIF('План 2026-2028'!$G$5:$G$14,'Свод ДДС'!$C27,'План 2026-2028'!$W$5:$W$58),"") | G27: =IF(C27<>"",SUMIF('План 2026-2028'!$G$5:$G$14,'Свод ДДС'!$C27,'План 2026-2028'!$X$5:$X$58),"")
C28: {=IFERROR(INDEX('План Факт 2025'!$G$5:$G$30, MATCH(0,COUNTIF($C$21:C27,'План Факт 2025'!$G$5:$G$30&"") + IF('План Факт 2025'!$G$5:$G$30="",1,0), 0)), "")} | D28: =IF(C28<>"",SUMIF('План Факт 2025'!$G$5:$G$58,'Свод ДДС'!$C28,'План Факт 2025'!$Q$5:$Q$58),"") | E28: =IF(C28<>"",SUMIF('План 2026-2028'!$G$5:$G$14,'Свод ДДС'!$C28,'План 2026-2028'!$V$5:$V$58),"") | F28: =IF(C28<>"",SUMIF('План 2026-2028'!$G$5:$G$14,'Свод ДДС'!$C28,'План 2026-2028'!$W$5:$W$58),"") | G28: =IF(C28<>"",SUMIF('План 2026-2028'!$G$5:$G$14,'Свод ДДС'!$C28,'План 2026-2028'!$X$5:$X$58),"")
C29: {=IFERROR(INDEX('План Факт 2025'!$G$5:$G$30, MATCH(0,COUNTIF($C$21:C28,'План Факт 2025'!$G$5:$G$30&"") + IF('План Факт 2025'!$G$5:$G$30="",1,0), 0)), "")} | D29: =IF(C29<>"",SUMIF('План Факт 2025'!$G$5:$G$58,'Свод ДДС'!$C29,'План Факт 2025'!$Q$5:$Q$58),"") | E29: =IF(C29<>"",SUMIF('План 2026-2028'!$G$5:$G$14,'Свод ДДС'!$C29,'План 2026-2028'!$V$5:$V$58),"") | F29: =IF(C29<>"",SUMIF('План 2026-2028'!$G$5:$G$14,'Свод ДДС'!$C29,'План 2026-2028'!$W$5:$W$58),"") | G29: =IF(C29<>"",SUMIF('План 2026-2028'!$G$5:$G$14,'Свод ДДС'!$C29,'План 2026-2028'!$X$5:$X$58),"")
C30: {=IFERROR(INDEX('План Факт 2025'!$G$5:$G$30, MATCH(0,COUNTIF($C$21:C29,'План Факт 2025'!$G$5:$G$30&"") + IF('План Факт 2025'!$G$5:$G$30="",1,0), 0)), "")} | D30: =IF(C30<>"",SUMIF('План Факт 2025'!$G$5:$G$58,'Свод ДДС'!$C30,'План Факт 2025'!$Q$5:$Q$58),"") | E30: =IF(C30<>"",SUMIF('План 2026-2028'!$G$5:$G$14,'Свод ДДС'!$C30,'План 2026-2028'!$V$5:$V$58),"") | F30: =IF(C30<>"",SUMIF('План 2026-2028'!$G$5:$G$14,'Свод ДДС'!$C30,'План 2026-2028'!$W$5:$W$58),"") | G30: =IF(C30<>"",SUMIF('План 2026-2028'!$G$5:$G$14,'Свод ДДС'!$C30,'План 2026-2028'!$X$5:$X$58),"")
C31: {=IFERROR(INDEX('План Факт 2025'!$G$5:$G$30, MATCH(0,COUNTIF($C$21:C30,'План Факт 2025'!$G$5:$G$30&"") + IF('План Факт 2025'!$G$5:$G$30="",1,0), 0)), "")} | D31: =IF(C31<>"",SUMIF('План Факт 2025'!$G$5:$G$58,'Свод ДДС'!$C31,'План Факт 2025'!$Q$5:$Q$58),"") | E31: =IF(C31<>"",SUMIF('План 2026-2028'!$G$5:$G$14,'Свод ДДС'!$C31,'План 2026-2028'!$V$5:$V$58),"") | F31: =IF(C31<>"",SUMIF('План 2026-2028'!$G$5:$G$14,'Свод ДДС'!$C31,'План 2026-2028'!$W$5:$W$58),"") | G31: =IF(C31<>"",SUMIF('План 2026-2028'!$G$5:$G$14,'Свод ДДС'!$C31,'План 2026-2028'!$X$5:$X$58),"")
C32: {=IFERROR(INDEX('План Факт 2025'!$G$5:$G$30, MATCH(0,COUNTIF($C$21:C31,'План Факт 2025'!$G$5:$G$30&"") + IF('План Факт 2025'!$G$5:$G$30="",1,0), 0)), "")} | D32: =IF(C32<>"",SUMIF('План Факт 2025'!$G$5:$G$58,'Свод ДДС'!$C32,'План Факт 2025'!$Q$5:$Q$58),"") | E32: =IF(C32<>"",SUMIF('План 2026-2028'!$G$5:$G$14,'Свод ДДС'!$C32,'План 2026-2028'!$V$5:$V$58),"") | F32: =IF(C32<>"",SUMIF('План 2026-2028'!$G$5:$G$14,'Свод ДДС'!$C32,'План 2026-2028'!$W$5:$W$58),"") | G32: =IF(C32<>"",SUMIF('План 2026-2028'!$G$5:$G$14,'Свод ДДС'!$C32,'План 2026-2028'!$X$5:$X$58),"")
A33: Закупки ИТ оборудования, ПО, услуг в рамках Гособоронзаказа (ГОЗ) | D33: =SUMIF('План Факт 2025'!$C$5:$C$58,"ГОЗ",'План Факт 2025'!$R$5:$R$58) -> 0 | E33: =SUMIF('План Факт 2025'!$C$5:$C$58,"ГОЗ",'План Факт 2025'!$Z$5:$Z$58) -> 0 | F33: =SUMIF('План Факт 2025'!$C$5:$C$58,"ГОЗ",'План Факт 2025'!$AA$5:$AA$58) -> 0
A34: Закупки ИТ оборудования, ПО, услуг в рамках НИОКР | D34: =SUMIF('План Факт 2025'!$C$5:$C$58,"НИОКР",'План Факт 2025'!$R$5:$R$58) -> 0 | E34: =SUMIF('План Факт 2025'!$C$5:$C$58,"НИОКР",'План Факт 2025'!$Z$5:$Z$58) -> 0 | F34: =SUMIF('План Факт 2025'!$C$5:$C$58,"НИОКР",'План Факт 2025'!$AA$5:$AA$58) -> 0
A36: СПРАВОЧНО
A37: № п/п | C37: Затраты на лицензии ПО, внедрение и сопровождение ИС | D37: План 2026 | E37: План 2027 | F37: План 2028
A38: 1 | C38: ПО включенное в реестр | D38: =SUMIFS('План 2026-2028'!$P$5:$P$58,'План 2026-2028'!$D$5:$D$58,"Программное_обеспечение_лицензии",'План 2026-2028'!$K$5:$K$58,">0")+SUMIFS('План 2026-2028'!$P$5:$P$58,'План 2026-2028'!$D$5:$D$58,"Приобретение_ПО",'План 2026-2028'!$K$5:$K$58,">0")+SUMIFS('План 2026-2028'!$P$5:$P$58,'План 2026-2028'!$D$5:$D$58,"Услуги_по_внедрению_информационных_систем_(непроектные)",'План 2026-2028'!$K$5:$K$58,">0")+SUMIFS('План 2026-2028'!$P$5:$P$58,'План 2026-2028'!$D$5:$D$58,"Сопровождение_информационных_систем",'План 2026-2028'!$K$5:$K$58,">0")+SUMIFS('План 2026-2028'!$P$5:$P$58,'План 2026-2028'!$D$5:$D$58,"Услуги_внешней_техподдержки",'План 2026-2028'!$K$5:$K$58,">0") -> 13250 | E38: =SUMIFS('План 2026-2028'!$V$5:$V$58,'План 2026-2028'!$D$5:$D$58,"Программное_обеспечение_лицензии",'План 2026-2028'!$K$5:$K$58,">0")+SUMIFS('План 2026-2028'!$V$5:$V$58,'План 2026-2028'!$D$5:$D$58,"Приобретение_ПО",'План 2026-2028'!$K$5:$K$58,">0")+SUMIFS('План 2026-2028'!$V$5:$V$58,'План 2026-2028'!$D$5:$D$58,"Услуги_по_внедрению_информационных_систем_(непроектные)",'План 2026-2028'!$K$5:$K$58,">0")+SUMIFS('План 2026-2028'!$V$5:$V$58,'План 2026-2028'!$D$5:$D$58,"Сопровождение_информационных_систем",'План 2026-2028'!$K$5:$K$58,">0")+SUMIFS('План 2026-2028'!$P$5:$P$58,'План 2026-2028'!$D$5:$D$58,"Услуги_внешней_техподдержки",'План 2026-2028'!$K$5:$K$58,">0") -> 16450 | F38: =SUMIFS('План 2026-2028'!$W$5:$W$58,'План 2026-2028'!$D$5:$D$58,"Программное_обеспечение_лицензии",'План 2026-2028'!$K$5:$K$58,">0")+SUMIFS('План 2026-2028'!$W$5:$W$58,'План 2026-2028'!$D$5:$D$58,"Приобретение_ПО",'План 2026-2028'!$K$5:$K$58,">0")+SUMIFS('План 2026-2028'!$W$5:$W$58,'План 2026-2028'!$D$5:$D$58,"Услуги_по_внедрению_информационных_систем_(непроектные)",'План 2026-2028'!$K$5:$K$58,">0")+SUMIFS('План 2026-2028'!$W$5:$W$58,'План 2026-2028'!$D$5:$D$58,"Сопровождение_информационных_систем",'План 2026-2028'!$K$5:$K$58,">0")+SUMIFS('План 2026-2028'!$P$5:$P$58,'План 2026-2028'!$D$5:$D$58,"Услуги_внешней_техподдержки",'План 2026-2028'!$K$5:$K$58,">0") -> 15200
A39: 2 | C39: ПО вне реестра | D39: =SUMIFS('План 2026-2028'!$P$5:$P$58,'План 2026-2028'!$D$5:$D$58,"Программное_обеспечение_лицензии",'План 2026-2028'!$K$5:$K$58,"")+SUMIFS('План 2026-2028'!$P$5:$P$58,'План 2026-2028'!$D$5:$D$58,"Приобретение_ПО",'План 2026-2028'!$K$5:$K$58,"")+SUMIFS('План 2026-2028'!$P$5:$P$58,'План 2026-2028'!$D$5:$D$58,"Услуги_по_внедрению_информационных_систем_(непроектные)",'План 2026-2028'!$K$5:$K$58,"")+SUMIFS('План 2026-2028'!$P$5:$P$58,'План 2026-2028'!$D$5:$D$58,"Сопровождение_информационных_систем",'План 2026-2028'!$K$5:$K$58,"") -> 1000 | E39: =SUMIFS('План 2026-2028'!$V$5:$V$58,'План 2026-2028'!$D$5:$D$58,"Программное_обеспечение_лицензии",'План 2026-2028'!$K$5:$K$58,"")+SUMIFS('План 2026-2028'!$V$5:$V$58,'План 2026-2028'!$D$5:$D$58,"Приобретение_ПО",'План 2026-2028'!$K$5:$K$58,"")+SUMIFS('План 2026-2028'!$V$5:$V$58,'План 2026-2028'!$D$5:$D$58,"Услуги_по_внедрению_информационных_систем_(непроектные)",'План 2026-2028'!$K$5:$K$58,"")+SUMIFS('План 2026-2028'!$V$5:$V$58,'План 2026-2028'!$D$5:$D$58,"Сопровождение_информационных_систем",'План 2026-2028'!$K$5:$K$58,"") -> 1500 | F39: =SUMIFS('План 2026-2028'!$W$5:$W$58,'План 2026-2028'!$D$5:$D$58,"Программное_обеспечение_лицензии",'План 2026-2028'!$K$5:$K$58,"")+SUMIFS('План 2026-2028'!$W$5:$W$58,'План 2026-2028'!$D$5:$D$58,"Приобретение_ПО",'План 2026-2028'!$K$5:$K$58,"")+SUMIFS('План 2026-2028'!$W$5:$W$58,'План 2026-2028'!$D$5:$D$58,"Услуги_по_внедрению_информационных_систем_(непроектные)",'План 2026-2028'!$K$5:$K$58,"")+SUMIFS('План 2026-2028'!$W$5:$W$58,'План 2026-2028'!$D$5:$D$58,"Сопровождение_информационных_систем",'План 2026-2028'!$K$5:$K$58,"") -> 2000
A40: ИТОГО | D40: =SUM(E38:E39) -> 17950 | E40: =SUM(F38:F39) -> 17200 | F40: =SUM(G38:G39) -> 0
C43: Заместитель директора по информационной безопасности | E43: В. Н. Афонин
C46: Главный эксперт группы экономики и планирования | E46: Е. А. Миронова

Sheet Реестр отеч ПО
A1: Регистрационный номер | B1: Наименование ПО | C1: Альтернативные названия ПО | D1: Класс ПО | E1: Код продукции
A2: 17372 | B2: BPMSoft | D2: 09.01 - Средства управления бизнес-процессами (BPM) | E2: 62 Продукты программные и услуги по разработке программного обеспечения; консультационные и аналогичные услуги в области информационных технологий
A3: 17371 | B3: Средство криптографической защиты информации ВМШ-ТР-1U | D3: 03.11 - Средства защиты каналов передачи данных, в том числе криптографическими методами; 01.03 - Встроенные прикладные программы | E3: 62 Продукты программные и услуги по разработке программного обеспечения; консультационные и аналогичные услуги в области информационных технологий; 63.11.19 Услуги прочие по размещению и предоставлению инфраструктуры информационных технологий
A4: 17370 | B4: BI.ZONE Bug Bounty | C4: Платформа BI.ZONE Bug Bounty; Программа BI.ZONE Bug Bounty; Багбаунти | D4: 03.17 - Средства автоматизации процессов информационной безопасности | E4: 62 Продукты программные и услуги по разработке программного обеспечения; консультационные и аналогичные услуги в области информационных технологий; 63.11.19 Услуги прочие по размещению и предоставлению инфраструктуры информационных технологий
A5: 17369 | B5: Программное обеспечение «ФОТОКАССА» | D5: 11.06 - Инструменты обработки, анализа и распознавания изображений; 05.15 - Информационные системы для решения специфических отраслевых задач; 09.02 - Средства управления производственными процессами (MES) | E5: 58.29.29 Обеспечение программное прикладное прочее на электронном носителе; 62 Продукты программные и услуги по разработке программного обеспечения; консультационные и аналогичные услуги в области информационных технологий; 63.11.19 Услуги прочие по размещению и предоставлению инфраструктуры информационных технологий
A6: 17368 | B6: Платформа Like | D6: 09.11 - Средства управления содержимым (CMS), сайты и портальные решения | E6: 62 Продукты программные и услуги по разработке программного обеспечения; консультационные и аналогичные услуги в области информационных технологий
A7: 17367 | B7: СЭО «ДругЗаДругом» | C7: Система для управления потоками клиентов; Система управления электронной очередью; Система электронной очереди | D7: 05.15 - Информационные системы для решения специфических отраслевых задач | E7: 58.29.29 Обеспечение программное прикладное прочее на электронном носителе; 62 Продукты программные и услуги по разработке программного обеспечения; консультационные и аналогичные услуги в области информационных технологий
A8: 17366 | B8: ПЛАТФОРМА РАБОЧИЕ РУКИ - ОБЛАЧНЫЙ B2B СЕРВИС ДЛЯ ПОИСКА, НАЙМА И УПРАВЛЕНИЯ ВРЕМЕННЫМИ ИЛИ ПРОЕКТНЫМИ ИСПОЛНИТЕЛЯМИ, А ТАКЖЕ ПРОИЗВОДСТВА МАССОВЫХ ВЫПЛАТ | C8: Платформа РАБОЧИЕ РУКИ; Программа РАБОЧИЕ РУКИ; Система РАБОЧИЕ РУКИ; Маркетплейс РАБОЧИЕ РУКИ | D8: 09.07 - Средства финансового менеджмента, управления активами и трудовыми ресурсами (ERP); 09.01 - Средства управления бизнес-процессами (BPM) | E8: 62 Продукты программные и услуги по разработке программного обеспечения; консультационные и аналогичные услуги в области информационных технологий
A9: 17365 | B9: Система записи разговоров «Record» на базе ATC ASTERISK | D9: 09.01 - Средства управления бизнес-процессами (BPM) | E9: 62 Продукты программные и услуги по разработке программного обеспечения; консультационные и аналогичные услуги в области информационных технологий
A10: 17364 | B10: Программа управления наружным освещением «СПЕКТР» | C10: АСУНО «СПЕКТР» | D10: 02.08 - Средства мониторинга и управления; 09.14 - Средства централизованного управления конечными устройствами | E10: 58.29.12 Обеспечение программное сетевое на электронном носителе; 62 Продукты программные и услуги по разработке программного обеспечения; консультационные и аналогичные услуги в области информационных технологий; 63.11.12 Услуги по размещению в информационно-коммуникационной сети Интернет
A11: 17363 | B11: BD-soft Analytics | D11: 02.08 - Средства мониторинга и управления | E11: 58.29.12 Обеспечение программное сетевое на электронном носителе; 62 Продукты программные и услуги по разработке программного обеспечения; консультационные и аналогичные услуги в области информационных технологий; 63.11.12 Услуги по размещению в информационно-коммуникационной сети Интернет
A12: 17362 | B12: Автоматизированная система организации процесса контроля качества диалогов "АУДИТОРиЯ" | D12: 05.08 - Средства управления контактными центрами | E12: 58.29.29 Обеспечение программное прикладное прочее на электронном носителе; 62 Продукты программные и услуги по разработке программного обеспечения; консультационные и аналогичные услуги в области информационных технологий
A13: 17361 | B13: ОСМ Аналитика | C13: OCM Analytics, ОСМ АНАЛИТИКА, OCM ANALYTICS | D13: 05.13 - Средства интеллектуальной обработки информации и интеллектуального анализа бизнес-процессов; 05.11 - Интеллектуальные средства управления экспертной деятельностью; 11.05 - Средства поддержки принятия решений (DSS) | E13: 58.29.21 Приложения общие для повышения эффективности бизнеса и приложения для домашнего пользования, отдельно реализуемые; 58.29.29 Обеспечение программное прикладное прочее на электронном носителе; 62 Продукты программные и услуги по разработке программного обеспечения; консультационные и аналогичные услуги в области информационных технологий; 63.11.19 Услуги прочие по размещению и предоставлению инфраструктуры информационных технологий
A14: 17360 | B14: РЕПАБ | D14: 05.10 - Базы знаний | E14: 58.29.21 Приложения общие для повышения эффективности бизнеса и приложения для домашнего пользования, отдельно реализуемые; 58.29.29 Обеспечение программное прикладное прочее на электронном носителе; 62 Продукты программные и услуги по разработке программного обеспечения; консультационные и аналогичные услуги в области информационных технологий
A15: 17359 | B15: ПН-Контроль | C15: нет | D15: 01.03 - Встроенные прикладные программы; 05.15 - Информационные системы для решения специфических отраслевых задач | E15: 58.29.29 Обеспечение программное прикладное прочее на электронном носителе; 62 Продукты программные и услуги по разработке программного обеспечения; консультационные и аналогичные услуги в области информационных технологий
A16: 17358 | B16: Конструктор бизнес-приложений SciOffice | D16: 04.08 - Интегрированные платформы для создания приложений; 09.01 - Средства управления бизнес-процессами (BPM) | E16: 58.29.14 Средства разработки инструментальные и программное обеспечение языков программирования на электронном носителе; 62 Продукты программные и услуги по разработке программного обеспечения; консультационные и аналогичные услуги в области информационных технологий
A17: 17357 | B17: Hello, Doc! | C17: Hello, Doc! для работы; Hello, Doc! для пациента; Hello, Doc! WORK | D17: 05.15 - Информационные системы для решения специфических отраслевых задач; 09.01 - Средства управления бизнес-процессами (BPM) | E17: 58.29.29 Обеспечение программное прикладное прочее на электронном носителе; 62 Продукты программные и услуги по разработке программного обеспечения; консультационные и аналогичные услуги в области информационных технологий
A18: 17356 | B18: Автоматизированная информационная система «Единый реестр неработающих пенсионеров» (АИС «ЕРНП») | D18: 11.02 - Предметно-ориентированные информационные базы данных (EDW); 05.15 - Информационные системы для решения специфических отраслевых задач | E18: 58.29.29 Обеспечение программное прикладное прочее на электронном носителе; 62 Продукты программные и услуги по разработке программного обеспечения; консультационные и аналогичные услуги в области информационных технологий; 63.11.19 Услуги прочие по размещению и предоставлению инфраструктуры информационных технологий
A19: 17355 | B19: Мои Задания | D19: 05.15 - Информационные системы для решения специфических отраслевых задач; 09.01 - Средства управления бизнес-процессами (BPM) | E19: 58.29.29 Обеспечение программное прикладное прочее на электронном носителе; 62 Продукты программные и услуги по разработке программного обеспечения; консультационные и аналогичные услуги в области информационных технологий
A20: 17354 | B20: Программа сервера системы управления движением судов | C20: ПО Сервера СУДС | D20: 05.15 - Информационные системы для решения специфических отраслевых задач; 09.01 - Средства управления бизнес-процессами (BPM) | E20: 58.29.29 Обеспечение программное прикладное прочее на электронном носителе; 62 Продукты программные и услуги по разработке программного обеспечения; консультационные и аналогичные услуги в области информационных технологий
A21: 17353 | B21: Система контроля и управления обслуживанием "Консенсус" | C21: СКУО "Консенсус"; СКУО Consensus | D21: 09.01 - Средства управления бизнес-процессами (BPM); 05.15 - Информационные системы для решения специфических отраслевых задач; 09.14 - Средства централизованного управления конечными устройствами | E21: 58.29.29 Обеспечение программное прикладное прочее на электронном носителе; 62 Продукты программные и услуги по разработке программного обеспечения; консультационные и аналогичные услуги в области информационных технологий
A22: 17352 | B22: Автоматизированная система открытия расчетного счета "АС ОРС" | C22: Автоматизированная система процесса открытия расчетного счета для клиентов — юридических лиц, индивидуальных предпринимателей и физических лиц, занимающихся в установленном законодательством Российской Федерации порядке частной практикой; Автоматизированная система открытия расчетного счета; АС ОРС | D22: 05.15 - Информационные системы для решения специфических отраслевых задач; 09.01 - Средства управления бизнес-процессами (BPM) | E22: 58.29.29 Обеспечение программное прикладное прочее на электронном носителе; 62 Продукты программные и услуги по разработке программного обеспечения; консультационные и аналогичные услуги в области информационных технологий
A23: 17351 | B23: Социальная сеть QR’ME – основной модуль | C23: QR’ME | D23: 05.03 - Игры и развлечения; 06.02 - Коммуникационное программное обеспечение | E23: 58.29.21 Приложения общие для повышения эффективности бизнеса и приложения для домашнего пользования, отдельно реализуемые; 58.29.29 Обеспечение программное прикладное прочее на электронном носителе; 62 Продукты программные и услуги по разработке программного обеспечения; консультационные и аналогичные услуги в области информационных технологий
A24: 17350 | B24: Инструментальное средство системы обеспечения исполнения функциональных алгоритмов (ИС СОИФА) | D24: 04.01 - Средства подготовки исполнимого кода | E24: 58.29.14 Средства разработки инструментальные и программное обеспечение языков программирования на электронном носителе
A25: 17349 | B25: Платформа IN.TOP | C25: - | D25: 09.01 - Средства управления бизнес-процессами (BPM); 05.05 - Средства управления проектами | E25: 58.29.21 Приложения общие для повышения эффективности бизнеса и приложения для домашнего пользования, отдельно реализуемые; 62 Продукты программные и услуги по разработке программного обеспечения; консультационные и аналогичные услуги в области информационных технологий
A26: 17348 | B26: Мобильное приложение Знакомства@Mail.ru для устройств с операционной системой Android | D26: 05.03 - Игры и развлечения; 06.02 - Коммуникационное программное обеспечение | E26: 58.29.21 Приложения общие для повышения эффективности бизнеса и приложения для домашнего пользования, отдельно реализуемые; 58.29.29 Обеспечение программное прикладное прочее на электронном носителе
A27: 17347 | B27: Мобильное приложение Знакомства@Mail.ru для устройств с операционной системой iOS | D27: 06.02 - Коммуникационное программное обеспечение; 05.03 - Игры и развлечения | E27: 58.29.21 Приложения общие для повышения эффективности бизнеса и приложения для домашнего пользования, отдельно реализуемые; 58.29.29 Обеспечение программное прикладное прочее на электронном носителе; 62 Продукты программные и услуги по разработке программного обеспечения; консультационные и аналогичные услуги в области информационных технологий
A28: 17346 | B28: Модуль переноса данных из 1С:Управление торговлей, ред.11 в 1С:Комплексная автоматизация, ред. 1.1 | C28: Перенос данных из УТ 11 в КА 1; Перенос данных из 1С:УТ 11 в 1С:КА 1; Перенос данных из "1С:Управление торговлей, ред.11" в "1С:Комплексная автоматизация, ред. 1.1" | D28: 05.15 - Информационные системы для решения специфических отраслевых задач | E28: 62 Продукты программные и услуги по разработке программного обеспечения; консультационные и аналогичные услуги в области информационных технологий
A29: 17345 | B29: Программа индивидуализированной вторичной профилактики (интерактивная программа «Санрайс») | D29: 05.15 - Информационные системы для решения специфических отраслевых задач | E29: 58.29.29 Обеспечение программное прикладное прочее на электронном носителе; 62 Продукты программные и услуги по разработке программного обеспечения; консультационные и аналогичные услуги в области информационных технологий
A30: 17344 | B30: Автоматические акты сверки с контрагентами для 1С:Предприятие | D30: 09.01 - Средства управления бизнес-процессами (BPM) | E30: 62 Продукты программные и услуги по разработке программного обеспечения; консультационные и аналогичные услуги в области информационных технологий
A31: 17343 | B31: Программный комплекс «GanNet-SCADA» | D31: 09.04 - Средства управления технологическими процессами (АСУ ТП, SCADA) | E31: 62 Продукты программные и услуги по разработке программного обеспечения; консультационные и аналогичные услуги в области информационных технологий
A32: 17342 | B32: Модуль переноса данных из 1С:ERP Управление предприятием, ред. 2.5 в 1С:Управление торговлей, ред.10.3 | C32: Перенос данных из ЕРП 2 в УТ 10; Перенос данных из 1С:ЕРП в 1С:УТ 10; Перенос данных из "1С:ERP Управление предприятием, ред. 2.5" в "1С:Управление торговлей, ред.10.3" | D32: 05.15 - Информационные системы для решения специфических отраслевых задач | E32: 62 Продукты программные и услуги по разработке программного обеспечения; консультационные и аналогичные услуги в области информационных технологий
A33: 17341 | B33: Модуль переноса данных из 1С:ERP Управление предприятием, ред. 2.5 в 1С:Комплексная автоматизация, ред. 1.1 | C33: Перенос данных из ЕРП 2 в КА 1; Перенос данных из 1С:ЕРП в 1С:КА 1; Перенос данных из "1С:ERP Управление предприятием, ред. 2.5" в "1С:Комплексная автоматизация, ред. 1.1" | D33: 05.15 - Информационные системы для решения специфических отраслевых задач | E33: 62 Продукты программные и услуги по разработке программного обеспечения; консультационные и аналогичные услуги в области информационных технологий
A34: 17340 | B34: Базовая система ввода-вывода iRU BIOS 012 для системной платы ЛПГР.469559.012 | C34: Доверенный iRU BIOS RU.ЛПГР.469559.012; Доверенная базовая система ввода-вывода iRU BIOS RU.ЛПГР.469559.012; Доверенная БСВВ iRU RU.ЛПГР.469559.012; Программное обеспечение для системной платы ЛПГР.469559.012 | D34: 01.01 - Встроенные системные программы: BIOS, UEFI и иные встроенные системные программы; 03.02 - Средства управления событиями информационной безопасности | E34: 62 Продукты программные и услуги по разработке программного обеспечения; консультационные и аналогичные услуги в области информационных технологий
A35: 17339 | B35: Модуль переноса данных из 1С:Комплексная автоматизация, ред. 2.5 в 1С:Управление производственным предприятием, ред.1.3 | C35: Перенос данных из КА 2 в УПП; Перенос данных из 1С:КА 2 в 1С:УПП; Перенос данных из "1С:Комплексная автоматизация, ред. 2.5" в "1С:Управление производственным предприятием, ред.1.3" | D35: 05.15 - Информационные системы для решения специфических отраслевых задач | E35: 62 Продукты программные и услуги по разработке программного обеспечения; консультационные и аналогичные услуги в области информационных технологий
A36: 17338 | B36: Модуль переноса данных из 1С:ERP Управление предприятием, ред. 2.5 в 1С:Управление производственным предприятием, ред.1.3 | C36: Перенос данных из ЕРП 2 в УПП; Перенос данных из 1С:ЕРП в 1С:УПП; Перенос данных из "1С:ERP Управление предприятием, ред. 2.5" в "1С:Управление производственным предприятием, ред.1.3" | D36: 05.15 - Информационные системы для решения специфических отраслевых задач | E36: 62 Продукты программные и услуги по разработке программного обеспечения; консультационные и аналогичные услуги в области информационных технологий
A37: 17337 | B37: Модуль переноса данных из 1С:Комплексная автоматизация, ред. 2.5 в 1С:Комплексная автоматизация, ред. 1.1 | C37: Перенос данных из КА 2 в КА 1; Перенос данных из 1С:КА 2 в 1С:КА 1; Перенос данных из "1С:Комплексная автоматизация, ред. 2.5" в "1С:Комплексная автоматизация, ред. 1.1" | D37: 05.15 - Информационные системы для решения специфических отраслевых задач | E37: 62 Продукты программные и услуги по разработке программного обеспечения; консультационные и аналогичные услуги в области информационных технологий
A38: 17336 | B38: Модуль переноса данных из 1С:Управление торговлей, ред.11 в 1С:Управление торговлей, ред.10.3 | C38: Перенос данных из УТ 11 в УТ 10; Перенос данных из 1С: УТ 11 в 1С: УТ 10; Перенос данных из "1С:Управление торговлей, ред.11" в "1С:Управление торговлей, ред.10.3" | D38: 05.15 - Информационные системы для решения специфических отраслевых задач | E38: 62 Продукты программные и услуги по разработке программного обеспечения; консультационные и аналогичные услуги в области информационных технологий
A39: 17335 | B39: Система контроля поручений и документооборота (СКП Документооборот) | D39: 06.12 - Системы электронного документооборота | E39: 58.29.21 Приложения общие для повышения эффективности бизнеса и приложения для домашнего пользования, отдельно реализуемые
A40: 17334 | B40: Модуль переноса данных из 1С:Бухгалтерия предприятия, ред. 3.0 в 1С:Управление нашей фирмой, ред.3.0 | C40: Перенос данных из "1С:Бухгалтерия предприятия, ред. 3.0" в "1С:Управление нашей фирмой, ред.3.0" | D40: 05.15 - Информационные системы для решения специфических отраслевых задач | E40: 62 Продукты программные и услуги по разработке программного обеспечения; консультационные и аналогичные услуги в области информационных технологий
A41: 17333 | B41: Модуль переноса данных из 1С:Бухгалтерия предприятия, ред. 3.0 в 1С:ERP Управление предприятием, ред. 2.5 | C41: Перенос данных из "1С:Бухгалтерия предприятия, ред. 3" в "1С:ERP Управление предприятием, ред. 2.5"; Перенос данных из 1С:БП3 в 1С:ERP; Перенос данных из БП3 в ERP | D41: 05.15 - Информационные системы для решения специфических отраслевых задач | E41: 62 Продукты программные и услуги по разработке программного обеспечения; консультационные и аналогичные услуги в области информационных технологий
A42: 17332 | B42: Модуль переноса данных из 1С:Управление торговлей, ред.11 в 1С:Бухгалтерия предприятия, ред. 3.0 | C42: Перенос данных из УТ 11 в БП 3; Перенос данных из 1С:УТ 11 в 1С:БП 3; Перенос данных из "1С:Управление торговлей, ред.11" в "1С:Бухгалтерия предприятия, ред. 3.0" | D42: 05.15 - Информационные системы для решения специфических отраслевых задач | E42: 62 Продукты программные и услуги по разработке программного обеспечения; консультационные и аналогичные услуги в области информационных технологий
A43: 17331 | B43: Модуль переноса данных из 1С:Комплексная автоматизация, ред. 2.5 в 1С:Бухгалтерия предприятия, ред. 3.0 | C43: Перенос данных из КА 2 в БП 3; Перенос данных из 1С:КА 2 в 1СБП 3; Перенос данных из "1С:Комплексная автоматизация, ред. 2.5" в "1С:Бухгалтерия предприятия, ред. 3.0" | D43: 05.15 - Информационные системы для решения специфических отраслевых задач | E43: 62 Продукты программные и услуги по разработке программного обеспечения; консультационные и аналогичные услуги в области информационных технологий
A44: 17330 | B44: Программа оперативного контроля и управления системой оповещения региональной системы оповещения | D44: 05.15 - Информационные системы для решения специфических отраслевых задач; 02.08 - Средства мониторинга и управления | E44: 58.29.12 Обеспечение программное сетевое на электронном носителе; 58.29.29 Обеспечение программное прикладное прочее на электронном носителе; 62 Продукты программные и услуги по разработке программного обеспечения; консультационные и аналогичные услуги в области информационных технологий
A45: 17329 | B45: Программный комплекс Гибридная система видеоаналитики, детекции и идентификации объектов лесных массивов и сельскохозяйственных угодий в сложной окружающей среде на основе использования нейросетей (ПК «ВАДИ») | C45: ПК «ВАДИ» | D45: 05.15 - Информационные системы для решения специфических отраслевых задач | E45: 58.29.29 Обеспечение программное прикладное прочее на электронном носителе
A46: 17328 | B46: Специальное программное обеспечение "ПВ-Про" | C46: СПО "ПВ-Про" | D46: 05.15 - Информационные системы для решения специфических отраслевых задач | E46: 58.29.29 Обеспечение программное прикладное прочее на электронном носителе
A47: 17327 | B47: Программный комплекс Accent TMBrowser | D47: 05.15 - Информационные системы для решения специфических отраслевых задач | E47: 58.29.29 Обеспечение программное прикладное прочее на электронном носителе
A48: 17326 | B48: САПФИР_95&RC_ХОЯТ | D48: 05.15 - Информационные системы для решения специфических отраслевых задач; 10.03 - Средства математического и имитационного моделирования | E48: 62 Продукты программные и услуги по разработке программного обеспечения; консультационные и аналогичные услуги в области информационных технологий
A49: 17325 | B49: CRC15 | D49: 05.15 - Информационные системы для решения специфических отраслевых задач; 10.03 - Средства математического и имитационного моделирования | E49: 62 Продукты программные и услуги по разработке программного обеспечения; консультационные и аналогичные услуги в области информационных технологий
A50: 17324 | B50: Vision | C50: Программное обеспечение Vision для просмотра, помощи в исследовании и обработки цифровых микроскопических изображений с принадлежностями; Ключ лицензионный для активации программного обеспечения Vision; Ключ лицензионный для активации 1000 тестов; Ключ лицензионный для активации 5000 тестов; Ключ лицензионный для активации 10000 тестов; Ключ лицензионный для активации удаленного рабочего места | D50: 05.15 - Информационные системы для решения специфических отраслевых задач; 05.13 - Средства интеллектуальной обработки информации и интеллектуального анализа бизнес-процессов | E50: 58.29.29 Обеспечение программное прикладное прочее на электронном носителе
A51: 17323 | B51: Программа контроля и управления крановой площадкой магистрального газопровода в системе телемеханики СТН-3000-Р | D51: 09.04 - Средства управления технологическими процессами (АСУ ТП, SCADA); 05.15 - Информационные системы для решения специфических отраслевых задач | E51: 58.29.29 Обеспечение программное прикладное прочее на электронном носителе
A52: 17322 | B52: Программа контроля, управления и регулирования системы автоматического управления газоизмерительной станцией СТН-3000-Р | D52: 09.04 - Средства управления технологическими процессами (АСУ ТП, SCADA); 05.15 - Информационные системы для решения специфических отраслевых задач | E52: 58.29.29 Обеспечение программное прикладное прочее на электронном носителе
A53: 17321 | B53: Q.Health, Мониторинг здоровья | D53: 02.08 - Средства мониторинга и управления | E53: 58.29.12 Обеспечение программное сетевое на электронном носителе; 62 Продукты программные и услуги по разработке программного обеспечения; консультационные и аналогичные услуги в области информационных технологий; 63.11.12 Услуги по размещению в информационно-коммуникационной сети Интернет
A54: 17320 | B54: Программа для ЭВМ «Пособие для оценки, мониторинга и скрининга психофизического развития ребенка «Инфант» (интерактивная программа)» | D54: 05.15 - Информационные системы для решения специфических отраслевых задач | E54: 58.29.29 Обеспечение программное прикладное прочее на электронном носителе
A55: 17319 | B55: Сервис обновления ПО | C55: Сервис обновления программного обеспечения | D55: 05.15 - Информационные системы для решения специфических отраслевых задач | E55: 58.29.29 Обеспечение программное прикладное прочее на электронном носителе
A56: 17318 | B56: Workforce Management | D56: 05.15 - Информационные системы для решения специфических отраслевых задач | E56: 58.29.29 Обеспечение программное прикладное прочее на электронном носителе
A57: 17317 | B57: Автоматизированная система управления наружным освещением (АСУНО) AWADA | D57: 02.08 - Средства мониторинга и управления | E57: 58.29.12 Обеспечение программное сетевое на электронном носителе
A58: 17316 | B58: «ГИС «Регистрация захоронений» КОРП» | D58: 05.06 - Геоинформационные и навигационные средства (GIS); 05.15 - Информационные системы для решения специфических отраслевых задач | E58: 58.29.29 Обеспечение программное прикладное прочее на электронном носителе; 62 Продукты программные и услуги по разработке программного обеспечения; консультационные и аналогичные услуги в области информационных технологий
A59: 17315 | B59: Система управления производственным процессом | C59: СУПП | D59: 09.02 - Средства управления производственными процессами (MES) | E59: 62 Продукты программные и услуги по разработке программного обеспечения; консультационные и аналогичные услуги в области информационных технологий
A60: 17314 | B60: I-PS – ПОС. КОМПЛЕКТ | D60: 05.02 - Дополнительные программные модули (плагины); 05.15 - Информационные системы для решения специфических отраслевых задач; 08.09 - Средства информационного моделирования зданий и сооружений, архитектурно-строительного проектирования (BIM, AEC CAD) | E60: 58.29.21 Приложения общие для повышения эффективности бизнеса и приложения для домашнего пользования, отдельно реализуемые; 58.29.29 Обеспечение программное прикладное прочее на электронном носителе; 62 Продукты программные и услуги по разработке программного обеспечения; консультационные и аналогичные услуги в области информационных технологий
A61: 17313 | B61: Физтех.Ресурс.Ядро | C61: Программное обеспечение универсального ядра веб-ресурса "Физтех.Ресурс.Ядро" | D61: 05.10 - Базы знаний | E61: 62 Продукты программные и услуги по разработке программного обеспечения; консультационные и аналогичные услуги в области информационных технологий
A62: 17312 | B62: РЕЛАН-61850 | D62: 02.08 - Средства мониторинга и управления; 05.15 - Информационные системы для решения специфических отраслевых задач | E62: 58.29.12 Обеспечение программное сетевое на электронном носителе
A63: 17311 | B63: SMDocs Lite | D63: 06.01 - Файловые менеджеры | E63: 58.29.21 Приложения общие для повышения эффективности бизнеса и приложения для домашнего пользования, отдельно реализуемые; 62 Продукты программные и услуги по разработке программного обеспечения; консультационные и аналогичные услуги в области информационных технологий
A64: 17310 | B64: 152DOC | D64: 05.15 - Информационные системы для решения специфических отраслевых задач | E64: 58.29.29 Обеспечение программное прикладное прочее на электронном носителе; 62 Продукты программные и услуги по разработке программного обеспечения; консультационные и аналогичные услуги в области информационных технологий
A65: 17309 | B65: Mind tracker BCI | D65: 04.06 - Средства разработки программного обеспечения на основе нейротехнологий и искусственного интеллекта | E65: 62 Продукты программные и услуги по разработке программного обеспечения; консультационные и аналогичные услуги в области информационных технологий
A66: 17308 | B66: Программа ведения бизнеса online "БИЗ-ОН" | D66: 05.15 - Информационные системы для решения специфических отраслевых задач; 06.12 - Системы электронного документооборота | E66: 62 Продукты программные и услуги по разработке программного обеспечения; консультационные и аналогичные услуги в области информационных технологий
A67: 17307 | B67: FamedServer v.2.0 | C67: FamedServer | D67: 11.01 - Инструменты извлечения и трансформации данных (ETL); 09.01 - Средства управления бизнес-процессами (BPM); 09.03 - Средства управления лабораторными потоками работ и документов (LIMS) | E67: 62 Продукты программные и услуги по разработке программного обеспечения; консультационные и аналогичные услуги в области информационных технологий
A68: 17306 | B68: АСУ- ЗиС | D68: 05.15 - Информационные системы для решения специфических отраслевых задач | E68: 62 Продукты программные и услуги по разработке программного обеспечения; консультационные и аналогичные услуги в области информационных технологий
A69: 17305 | B69: Программное обеспечение АСУ ТП управления турбокомпрессорными и нагнетательными агрегатами Ю-Скат ВЕТРОЛ (ВЕТРОЛ, VETROL) | C69: ПО АСУ ТП Ветрол; ПО Ветрол | D69: 09.04 - Средства управления технологическими процессами (АСУ ТП, SCADA); 05.15 - Информационные системы для решения специфических отраслевых задач; 08.11 - Средства автоматизированного управления техникой; 09.14 - Средства централизованного управления конечными устройствами | E69: 58.29.29 Обеспечение программное прикладное прочее на электронном носителе; 62 Продукты программные и услуги по разработке программного обеспечения; консультационные и аналогичные услуги в области информационных технологий
A70: 17304 | B70: Tamelent | C70: Платформа взаимодействия с клиентами | D70: 09.09 - Средства управления отношениями с клиентами (CRM) | E70: 62 Продукты программные и услуги по разработке программного обеспечения; консультационные и аналогичные услуги в области информационных технологий
A71: 17303 | B71: Диаграмма | D71: 02.08 - Средства мониторинга и управления; 02.02 - Программы обслуживания; 05.15 - Информационные системы для решения специфических отраслевых задач | E71: 58.29.12 Обеспечение программное сетевое на электронном носителе; 62 Продукты программные и услуги по разработке программного обеспечения; консультационные и аналогичные услуги в области информационных технологий; 63.11.12 Услуги по размещению в информационно-коммуникационной сети Интернет
A72: 17302 | B72: СМС-Органайзер | D72: 06.02 - Коммуникационное программное обеспечение | E72: 62 Продукты программные и услуги по разработке программного обеспечения; консультационные и аналогичные услуги в области информационных технологий
A73: 17301 | B73: Тетрадь для лабораторных работ «Физика», раздел «Молекулярная физика и термодинамика» | D73: 05.01 - Мультимедийное программное обеспечение; 05.15 - Информационные системы для решения специфических отраслевых задач | E73: 58.29.29 Обеспечение программное прикладное прочее на электронном носителе
A74: 17300 | B74: Цифровой двойник города на основе 3D | D74: 05.06 - Геоинформационные и навигационные средства (GIS); 10.02 - Средства обработки и анализа геологических и геофизических данных | E74: 62 Продукты программные и услуги по разработке программного обеспечения; консультационные и аналогичные услуги в области информационных технологий
A75: 17299 | B75: Программное обеспечение дефибриллятора-монитора ДКИ-Н-10 "АКСИОН" | D75: 01.03 - Встроенные прикладные программы | E75: 62 Продукты программные и услуги по разработке программного обеспечения; консультационные и аналогичные услуги в области информационных технологий
A76: 17298 | B76: Шлюз оплаты электронными сертификатами НСПК | D76: 09.12 - Средства электронной коммерции (ecommerce platform); 05.15 - Информационные системы для решения специфических отраслевых задач | E76: 62 Продукты программные и услуги по разработке программного обеспечения; консультационные и аналогичные услуги в области информационных технологий
A77: 17297 | B77: SVGView | D77: 04.03 - Библиотеки подпрограмм (SDK) | E77: 62 Продукты программные и услуги по разработке программного обеспечения; консультационные и аналогичные услуги в области информационных технологий
A78: 17296 | B78: TalkBank Platform | D78: 05.09 - Средства управления диалоговыми роботами (чат-боты и голосовые роботы) | E78: 58.29.21 Приложения общие для повышения эффективности бизнеса и приложения для домашнего пользования, отдельно реализуемые; 62 Продукты программные и услуги по разработке программного обеспечения; консультационные и аналогичные услуги в области информационных технологий
A79: 17295 | B79: Система управления данными Polyflow | D79: 11.01 - Инструменты извлечения и трансформации данных (ETL); 05.15 - Информационные системы для решения специфических отраслевых задач | E79: 58.29.29 Обеспечение программное прикладное прочее на электронном носителе; 63.11.19 Услуги прочие по размещению и предоставлению инфраструктуры информационных технологий
A80: 17294 | B80: Автоматизированная информационная система Цифровой учет биологических ресурсов "Феникс" (АИС ЦУБР "Феникс") | D80: 05.15 - Информационные системы для решения специфических отраслевых задач | E80: 58.29.29 Обеспечение программное прикладное прочее на электронном носителе
A81: 17293 | B81: Б1 Discoverit | D81: 05.15 - Информационные системы для решения специфических отраслевых задач | E81: 58.29.29 Обеспечение программное прикладное прочее на электронном носителе; 62 Продукты программные и услуги по разработке программного обеспечения; консультационные и аналогичные услуги в области информационных технологий
A82: 17292 | B82: owl.Guard | D82: 11.06 - Инструменты обработки, анализа и распознавания изображений; 02.06 - Серверное и связующее программное обеспечение | E82: 62 Продукты программные и услуги по разработке программного обеспечения; консультационные и аналогичные услуги в области информационных технологий
... A84: 17290 | B84: ОТОР (Охрана Труда Оптимизация Рисков) | D84: 05.15 - Информационные системы для решения специфических отраслевых задач; 09.05 - Средства управления эффективностью предприятия (CPM/EPM); 09.07 - Средства финансового менеджмента, управления активами и трудовыми ресурсами (ERP) | E84: 58.29.29 Обеспечение программное прикладное прочее на электронном носителе; 62 Продукты программные и услуги по разработке программного обеспечения; консультационные и аналогичные услуги в области информационных технологий
A85: 17289 | B85: Онлайн сервис Center.Travel | C85: Платформа Center.Travel | D85: 05.15 - Информационные системы для решения специфических отраслевых задач; 09.01 - Средства управления бизнес-процессами (BPM) | E85: 58.29.29 Обеспечение программное прикладное прочее на электронном носителе; 62 Продукты программные и услуги по разработке программного обеспечения; консультационные и аналогичные услуги в области информационных технологий
A86: 17288 | B86: DataCheckEngine v.2 | C86: DataCheckEngine | D86: 10.01 - Средства обработки Больших Данных (BigData); 11.04 - Средства интеллектуального анализа данных (Data Mining) | E86: 62 Продукты программные и услуги по разработке программного обеспечения; консультационные и аналогичные услуги в области информационных технологий
A87: 17287 | B87: Программное обеспечение системы скрытого субтитрирования и телетекста телевизионных программ VS Subtitles | D87: 05.15 - Информационные системы для решения специфических отраслевых задач; 05.01 - Мультимедийное программное обеспечение | E87: 58.29.29 Обеспечение программное прикладное прочее на электронном носителе
A88: 17286 | B88: Программное обеспечение для прогнозирования качества геометрии выпускаемой продукции и выявления причин дефектов IASolutions QForecast | D88: 05.15 - Информационные системы для решения специфических отраслевых задач; 05.13 - Средства интеллектуальной обработки информации и интеллектуального анализа бизнес-процессов | E88: 58.29.29 Обеспечение программное прикладное прочее на электронном носителе
A89: 17285 | B89: Агрегатор нагрузки "ФОТЕЛ АН-01" | D89: 02.06 - Серверное и связующее программное обеспечение; 02.08 - Средства мониторинга и управления | E89: 61.90.10 Услуги телекоммуникационные прочие
A90: 17284 | B90: UPT.Medic | D90: 05.15 - Информационные системы для решения специфических отраслевых задач | E90: 62 Продукты программные и услуги по разработке программного обеспечения; консультационные и аналогичные услуги в области информационных технологий
A91: 17283 | B91: Программа автоматизированного рабочего места оператора системы управления движением судов | C91: программа АРМ оператора СУДС | D91: 05.15 - Информационные системы для решения специфических отраслевых задач; 05.06 - Геоинформационные и навигационные средства (GIS) | E91: 58.29.29 Обеспечение программное прикладное прочее на электронном носителе
A92: 17282 | B92: MaxPatrol O2 | D92: 03.02 - Средства управления событиями информационной безопасности; 03.07 - Средства выявления целевых атак; 03.15 - Средства обнаружения угроз и расследования сетевых инцидентов; 03.17 - Средства автоматизации процессов информационной безопасности | E92: 62 Продукты программные и услуги по разработке программного обеспечения; консультационные и аналогичные услуги в области информационных технологий; 63.11.19 Услуги прочие по размещению и предоставлению инфраструктуры информационных технологий
A93: 17281 | B93: Компонент обработки индексных данных «Модуль ОБХД» | D93: 05.07 - Специализированное ПО органов исполнительной власти Российской Федерации, государственных корпораций, компаний и юридических лиц с преимущественным участием Российской Федерации для внутреннего использования | E93: 58.29.21 Приложения общие для повышения эффективности бизнеса и приложения для домашнего пользования, отдельно реализуемые; 58.29.29 Обеспечение программное прикладное прочее на электронном носителе; 62 Продукты программные и услуги по разработке программного обеспечения; консультационные и аналогичные услуги в области информационных технологий
A94: 17280 | B94: ТЕРАПЛАН-АВИА | D94: 05.15 - Информационные системы для решения специфических отраслевых задач; 05.13 - Средства интеллектуальной обработки информации и интеллектуального анализа бизнес-процессов | E94: 58.29.29 Обеспечение программное прикладное прочее на электронном носителе
A95: 17279 | B95: Платформа АС МК-АЗК 7 | D95: 02.09 - Операционные системы общего назначения | E95: 58.29.11 Системы операционные на электронном носителе
A96: 17278 | B96: Прикладное программное обеспечение автоматизированного рабочего места дежурного по станции (АРМ ДСП) микропроцессорных систем управления железнодорожной автоматики и телемеханики (МПСУ ЖАТ) | D96: 09.14 - Средства централизованного управления конечными устройствами; 05.15 - Информационные системы для решения специфических отраслевых задач | E96: 58.29.29 Обеспечение программное прикладное прочее на электронном носителе; 62 Продукты программные и услуги по разработке программного обеспечения; консультационные и аналогичные услуги в области информационных технологий
A97: 17277 | B97: Открытый цифровой университет: Поступление онлайн | D97: 05.15 - Информационные системы для решения специфических отраслевых задач | E97: 58.29.29 Обеспечение программное прикладное прочее на электронном носителе; 62 Продукты программные и услуги по разработке программного обеспечения; консультационные и аналогичные услуги в области информационных технологий
A98: 17276 | B98: Кадровая программа «Персонал» | D98: 09.01 - Средства управления бизнес-процессами (BPM) | E98: 62 Продукты программные и услуги по разработке программного обеспечения; консультационные и аналогичные услуги в области информационных технологий
A99: 17275 | B99: Flocktory 2.0 | D99: 09.01 - Средства управления бизнес-процессами (BPM) | E99: 62 Продукты программные и услуги по разработке программного обеспечения; консультационные и аналогичные услуги в области информационных технологий
A100: 17274 | B100: Plicante 1.0 | D100: 09.01 - Средства управления бизнес-процессами (BPM) | E100: 62 Продукты программные и услуги по разработке программного обеспечения; консультационные и аналогичные услуги в области информационных технологий
A101: 17273 | B101: Коммуникационный сервер «Космотроника» | C101: Коммуникационный сервер программно-технического комплекса «Космотроника» | D101: 05.15 - Информационные системы для решения специфических отраслевых задач; 02.06 - Серверное и связующее программное обеспечение | E101: 58.29.29 Обеспечение программное прикладное прочее на электронном носителе; 61.90.10 Услуги телекоммуникационные прочие; 62 Продукты программные и услуги по разработке программного обеспечения; консультационные и аналогичные услуги в области информационных технологий; 63.11 Услуги по обработке данных, размещению и взаимосвязанные услуги
...

Sheet Выдержка из реестра
A1: 2948 | B1: ПАРУС-Предприятие 8
A2: 72 | B2: 1С: ERP Управление предприятием 8
A3: 4492 | B3: Система Галактика ERP.ОПК
A4: 169 | B4: 1С:Зарплата и Управление Персоналом 8
A6: 212 | B6: Справочная правовая система (СПС) КонсультантПлюс
A7: 6 | B7: Электронный периодический справочник "Система ГАРАНТ"
A8: 12387 | B8: СПАРК – поисковая система
A9: 523 | B9: Контур.Экстерн
A10: 508 | B10: Контур-Фокус
A11: 119 | B11: Информационно-справочная система "Техэксперт"
A12: 1622 | B12: NormaCS
A13: 8559 | B13: Casebook
... A59: 1704 | B59: Docsvision Делопроизводство

Sheet Справочники
R1: Операционный_бюджет | S1: Инвестиционный_проект | T1: ГОЗ | U1: НИОКР | V1: ФОТ | W1: Прочее | AG1: Код статьи | AH1: Статьи БДДС | AI1: Уровень
A2: 2020 | B2: Каждый месяц | E2: Операционный_бюджет | J2: Классификатор | L2: Описание класса программ для электронных вычислительных машин и баз данных | M2: Код (числовое обозначение) раздела или класса программ для электронных вычислительных машин и баз данных | O2: 1. Персональные компьютеры, ноутбуки, мониторы, терминалы | R2: Программное_обеспечение_лицензии | S2: Приобретение_ПО | AA2: =$R$1&R2 -> Операционный_бюджетПрограммное_обеспечение_лицензии | AH2: Денежные потоки
A3: 2021 | B3: Каждый квартал | E3: Инвестиционный_проект | J3: Раздел | K3: Класс | O3: 2. Серверное оборудование, СХД | R3: ИТ_оборудование_и_комплектующие | S3: ИТ_оборудование_и_комплектующие_ИП | AA3: =$R$1&R3 -> Операционный_бюджетИТ_оборудование_и_комплектующие | AG3: 40000001 | AH3: Перевод между счетами организации | AI3: 3
A4: 2022 | B4: январь | E4: ГОЗ | J4: Встроенное | M4: 1 | O4: 3. Сетевое и коммуникационное оборудование | R4: Запчасти_и_расходные_материалы_к_ИТ_оборудованию | S4: Услуги_сторонних_организаций | AA4: =$R$1&R4 -> Операционный_бюджетЗапчасти_и_расходные_материалы_к_ИТ_оборудованию | AG4: 40000002 | AH4: Курсовая разница | AI4: 3
A5: 2023 | B5: февраль | E5: НИОКР | J5: программное | O5: 4. Средства связи | R5: Услуги_внешней_техподдержки | S5: Прочие_ИП | AA5: =$R$1&R5 -> Операционный_бюджетУслуги_внешней_техподдержки | AG5: 4100 | AH5: Денежные потоки от текущих операций
A6: 2024 | B6: март | E6: Прочее | J6: обеспечение | O6: 5. Видеонаблюдение | R6: Ремонт_ИТ_инфраструктуры | AA6: =$R$1&R6 -> Операционный_бюджетРемонт_ИТ_инфраструктуры | AG6: 4110 | AH6: Поступления
A7: 2025 | B7: апрель | E7: ФОТ | K7: Встроенные системные программы: BIOS, UEFI и иные встроенные системные программы | L7: Программное обеспечение, которое должно храниться в постоянной памяти и должно обеспечивать работоспособность и управление техническими (аппаратными) компонентами устройств (средств вычислительной техники, телекоммуникационных устройств, устройств интернета вещей, сенсорах и роботах) | M7: 44927 | N7: 1.1 | O7: 6. Печатное оборудование и сканеры | R7: Аренда_оборудования_и_вычислительных_мощностей | AA7: =$R$1&R7 -> Операционный_бюджетАренда_оборудования_и_вычислительных_мощностей | AG7: 4111 | AH7: от продажи продукции, товаров, работ и услуг | AI7: 1
A8: 2026 | B8: май | K8: Встроенные системные программы - операционные системы | L8: Встроенные системные управляющие программы, которые должны храниться в постоянной памяти и обеспечивать управление вычислительными ресурсами устройств (блоков управления устройствами), включая смарт-карты, и их взаимодействие с внешней средой | M8: 44958 | N8: 1.2 | O8: 7. Прочее оборудование | R8: Услуги_связи | AA8: =$R$1&R8 -> Операционный_бюджетУслуги_связи | AG8: 41110100 | AH8: Поступления от продажи продукции, товаров, работ, услуг | AI8: 2
A9: 2027 | B9: июнь | K9: Встроенные прикладные программы | L9: Встроенные программы, которые должны храниться в постоянной памяти и обеспечивать выполнение устройством предопределенных задач | M9: 44986 | N9: 1.3 | R9: Услуги_по_внедрению_информационных_систем_(непроектные) | AA9: =$R$1&R9 -> Операционный_бюджетУслуги_по_внедрению_информационных_систем_(непроектные) | AG9: 41110101 | AH9: Поступления от выполнения НИОКР | AI9: 3
A10: 2028 | B10: июль | K10: Программное обеспечение интернета вещей, робототехники и сенсорики | L10: Программы, которые должны использоваться в устройствах интернета вещей, сенсорах и роботах | M10: 45017 | N10: 1.4 | O10: =N7&" - "&K7 -> 1.1 - Встроенные системные программы: BIOS, UEFI и иные встроенные системные программы | R10: Сопровождение_информационных_систем | AA10: =$R$1&R10 -> Операционный_бюджетСопровождение_информационных_систем | AG10: 41110102 | AH10: Поступления от продажи продукции, работ, услуг в рамках серийных поставок | AI10: 3
A11: 2029 | B11: август | J11: Системное | M11: 2 | O11: =N8&" - "&K8 -> 1.2 - Встроенные системные программы - операционные системы | R11: Прочие | AA11: =$R$1&R11 -> Операционный_бюджетПрочие | AG11: 41110103 | AH11: Поступления от оказания пусковых услуг | AI11: 3
A12: 2030 | B12: сентябрь | J12: программное | O12: =N9&" - "&K9 -> 1.3 - Встроенные прикладные программы | AA12: =$S$1&S2 -> Инвестиционный_проектПриобретение_ПО | AG12: 41110104 | AH12: Поступления по оказанию услуг по управлению ДЗО | AI12: 3
B13: октябрь | J13: обеспечение | O13: =N10&" - "&K10 -> 1.4 - Программное обеспечение интернета вещей, робототехники и сенсорики | AA13: =$S$1&S3 -> Инвестиционный_проектИТ_оборудование_и_комплектующие_ИП | AG13: 41110105 | AH13: Поступления по сервисным услугам | AI13: 3
B14: ноябрь | K14: Драйверы | L14: Программы, которые должны использоваться для организации доступа к техническим (аппаратным) компонентам средств вычислительной техники | M14: 44928 | N14: 2.1 | O14: =N14&" - "&K14 -> 2.1 - Драйверы | AA14: =$S$1&S4 -> Инвестиционный_проектУслуги_сторонних_организаций | AG14: 41110199 | AH14: Поступления от прочей основной и иной деятельности | AI14: 3
B15: декабрь | K15: Программы обслуживания | L15: Программы, которые должны решать вспомогательные задачи или оказывать услуги общего характера пользователям | M15: 44959 | N15: 2.2 | O15: =N15&" - "&K15 -> 2.2 - Программы обслуживания | AA15: =$S$1&S5 -> Инвестиционный_проектПрочие_ИП | AG15: 4114 | AH15: cубсидии на финансирование текущих расходов | AI15: 1
K16: Средства обеспечения облачных и распределенных вычислений | L16: Программы, которые должны обеспечивать сетевой (внешний) доступ к общему пулу распределенных конфигурируемых вычислительных ресурсов | M16: 44987 | N16: 2.3 | O16: =N16&" - "&K16 -> 2.3 - Средства обеспечения облачных и распределенных вычислений | AA16: =$T$1&T2 -> ГОЗ | AG16: 41140100 | AH16: Субсидии на финансирование текущих расходов | AI16: 2
K17: Средства виртуализации | L17: Программы, которые должны обеспечивать доступ к общему пулу конфигурируемых вычислительных ресурсов или их логического объединения, абстрагированному от аппаратной реализации | M17: 45018 | N17: 2.4 | O17: =N17&" - "&K17 -> 2.4 - Средства виртуализации | AA17: =$U$1&U2 -> НИОКР | AG17: 41140101 | AH17: Поступление субсидии на финансирование текущих расходов | AI17: 3
K18: Средства хранения данных | L18: Программы, которые должны обеспечивать хранение и внешний (как правило) сетевой доступ к общему хранилищу данных | M18: 45048 | N18: 2.5 | O18: =N18&" - "&K18 -> 2.5 - Средства хранения данных | AA18: =$V$1&V2 -> ФОТ | AG18: 4115 | AH18: возврат НДС | AI18: 1
K19: Серверное и связующее программное обеспечение | L19: Программное обеспечение, которое должно выполнять сервисные (обслуживающие) функции по запросу клиента, предоставляя ему доступ к определенным ресурсам или услугам и обеспечивать взаимодействие между различными приложениями, системами, компонентами, в том числе программные интерфейсы (API) для интеграции систем. Также должно включать в себя программное обеспечение для передачи видео по сетям IP | M19: 45079 | N19: 2.6 | O19: =N19&" - "&K19 -> 2.6 - Серверное и связующее программное обеспечение | AA19: =$W$1&W2 -> Прочее | AG19: 41150100 | AH19: Возврат НДС | AI19: 2
K20: Средства управления базами данных | L20: Программы, которые должны предоставлять возможность организации и ведения баз данных, в том числе с использованием технологии распределенного реестра | M20: 45109 | N20: 2.7 | O20: =N20&" - "&K20 -> 2.7 - Средства управления базами данных | AG20: 41150101 | AH20: Поступления от возврата НДС | AI20: 3
K21: Средства мониторинга и управления | L21: Программы, которые должны предоставлять возможность измерения, сбора, хранения и анализа рабочих характеристик объектов управления для оценки их состояния, выявления неполадок, оповещения, управления настройками и состоянием | M21: 45140 | N21: 2.8 | O21: =N21&" - "&K21 -> 2.8 - Средства мониторинга и управления | AG21: 4119 | AH21: прочие поступления | AI21: 1
K22: Операционные системы общего назначения | L22: Операционные системы, которые должны быть обеспечивать функционирование на средствах вычислительной техники общего назначения (рабочие станции, сервера) | M22: 45171 | N22: 2.9 | O22: =N22&" - "&K22 -> 2.9 - Операционные системы общего назначения | AG22: 41190100 | AH22: Поступления от арендных платежей | AI22: 2
K23: Операционные системы реального времени | L23: Операционные системы, которое должны обеспечивать предсказуемое время обработки непредсказуемо возникающих внешних событий | M23: 45201 | N23: 2.10 | O23: =N23&" - "&K23 -> 2.10 - Операционные системы реального времени | AG23: 41190101 | AH23: Поступления от предоставления имущества в аренду (кроме финансовой аренды, лизинга) | AI23: 3
K24: Мобильная операционная система | L24: Операционные системы, которые должны быть предназначены для смартфонов, планшетов или других мобильных устройств | M24: 45232 | N24: 2.11 | O24: =N24&" - "&K24 -> 2.11 - Мобильная операционная система | AG24: 41190102 | AH24: Поступления по финансовой аренде (лизингу) | AI24: 3
K25: Системы контейнеризации и контейнеры | L25: Системы, в которых ядро операционной системы должно поддерживать несколько изолированных экземпляров пространства пользователя | M25: 45262 | N25: 2.12 | O25: =N25&" - "&K25 -> 2.12 - Системы контейнеризации и контейнеры | AG25: 41190200 | AH25: Прочие поступления по текущей деятельности | AI25: 2
J26: Средства обеспечения | M26: 3 | O26: =N29&" - "&K29 -> 3.1 - Средства защиты от несанкционированного доступа к информации | AG26: 41190201 | AH26: Поступления лицензионных платежей, роялти | AI26: 3
J27: информационной | O27: =N30&" - "&K30 -> 3.2 - Средства управления событиями информационной безопасности | AG27: 41190202 | AH27: Поступления по агентским и иным аналогичным договорам | AI27: 3
J28: безопасности | O28: =N31&" - "&K31 -> 3.3 - Межсетевые экраны | AG28: 41190203 | AH28: Поступления в виде возврата налогов и сборов (кроме НДС) | AI28: 3
K29: Средства защиты от несанкционированного доступа к информации | L29: Программы, которые должны предотвращать несанкционированный доступ к информации некриптографическими методами и обеспечивать: идентификацию и аутентификацию, управление доступом, целостность, аудит (регистрацию и учет). Включает программы управления средствами (устройствами) защиты от несанкционированного доступа к информации | M29: 44929 | N29: 3.1 | O29: =N32&" - "&K32 -> 3.4 - Средства фильтрации негативного контента | AG29: 41190204 | AH29: Поступления в виде процентов по остаткам на банковских счетах (НСО) и депозитам, признаваемым денежными эквивалентами | AI29: 3
K30: Средства управления событиями информационной безопасности | L30: Программы, которые должны обеспечивать выявление и предотвращение кибератак за счет анализа в режиме реального времени событий (данных) с целью определения потенциальных угроз безопасности | M30: 44960 | N30: 3.2 | O30: =N33&" - "&K33 -> 3.5 - Средства защиты сервисов онлайн-платежей и дистанционного банковского обслуживания | AG30: 41190205 | AH30: Поступления в виде процентов по займам выданным (признаваемым денежными эквивалентами) | AI30: 3
K31: Межсетевые экраны | L31: Программы, которые должны осуществлять контроль и фильтрацию проходящих через него сетевых пакетов в соответствии с заданными правилами | M31: 44988 | N31: 3.3 | O31: =N34&" - "&K34 -> 3.6 - Средства антивирусной защиты | AG31: 41190206 | AH31: Поступления от продажи неиспользуемых запасов | AI31: 3
K32: Средства фильтрации негативного контента | L32: Программное обеспечение, которое должно позволять управлять доступом к различным категориям веб-сайтов, для ограничения определенного нежелательного контента, средства защиты от спама и нежелательной корреспонденции | M32: 45019 | N32: 3.4 | O32: =N35&" - "&K35 -> 3.7 - Средства выявления целевых атак | AG32: 41190207 | AH32: Поступления в счет возмещения ущерба, в виде санкций за нарушение договорных обязательств | AI32: 3
K33: Средства защиты сервисов онлайн-платежей и дистанционного банковского обслуживания | L33: Программное обеспечение, которое должно позволять выявлять, анализировать и предотвращать мошенничество | M33: 45049 | N33: 3.5 | O33: =N36&" - "&K36 -> 3.8 - Средства гарантированного уничтожения данных | AG33: 41190208 | AH33: Ошибочные платежи, невыясненные суммы | AI33: 3
K34: Средства антивирусной защиты | L34: Программное обеспечение, которое должно позволять обнаруживать, перехватывать и обезвреживать вредоносное программное обеспечение как в памяти устройства, так и во входящем/исходящем трафике | M34: 45080 | N34: 3.6 | O34: =N37&" - "&K37 -> 3.9 - Средства обнаружения и предотвращения утечек информации | AG34: 41190209 | AH34: Обеспечение исполнения договора полученное | AI34: 3
K35: Средства выявления целевых атак | L35: Программное обеспечение, которое должно обнаруживать атаки (в том числе DDoS атаки) на конкретную организацию, страну или индустрию с целью кражи данных, получения контроля над ресурсами или блокирования их работы; должно противодействовать таким атакам | M35: 45110 | N35: 3.7 | O35: =N38&" - "&K38 -> 3.10 - Средства криптографической защиты информации и электронной подписи | AG35: Код статьи | AH35: Статьи БДДС | AI35: Уровень
K36: Средства гарантированного уничтожения данных | L36: Программное обеспечение, которое должно использовать специальные методики многократной перезаписи определенными паттернами, для минимизации вероятности восстановления информации с носителей на базе жестких магнитных дисков (HDD). Должно быть ограниченно применимо к твердотельным накопителям (SSD) | M36: 45141 | N36: 3.8 | O36: =N39&" - "&K39 -> 3.11 - Средства защиты каналов передачи данных, в том числе криптографическими методами | AG36: 41190210 | AH36: Купля-продажа иностранной валюты | AI36: 3
K37: Средства обнаружения и предотвращения утечек информации | L37: Программы, которые должны обнаруживать утечки и предотвращать распространения охраняемой законом компьютерной информации | M37: 45172 | N37: 3.9 | O37: =N40&" - "&K40 -> 3.12 - Средства управления доступом к | AG37: 41190299 | AH37: Прочие поступления по текущей деятельности | AI37: 3
K38: Средства криптографической защиты информации и электронной подписи | L38: Программы, которые должны предотвращать несанкционированный доступ к информации криптографическими методами, а также управлять ключевой информацией, включая ключи электронной подписи, ключи проверки электронной подписи и ключи шифрования информации; программное обеспечение, которое предназначено для изготовления сертификатов открытых ключей и управления ими (аннулирование, приостановление, возобновление), включая служебные функции (управление списками сертификатов, подтверждение статусов сертификатов открытых ключей, сервисы доверенного времени) | M38: 45202 | N38: 3.10 | O38: =N41&" - "&K41 -> 3.13 - Средства резервного копирования | AG38: 4120 | AH38: Платежи
K39: Средства защиты каналов передачи данных, в том числе криптографическими методами | L39: Программы, которые должны обеспечивать конфиденциальность информации, передаваемой через общедоступные каналы связи | M39: 45233 | N39: 3.11 | O39: =N42&" - "&K42 -> 3.14 - Средства обнаружения и/или предотвращения вторжений (атак) | AG39: 4121 | AH39: поставщикам (подрядчикам) за СиМ, работы, услуги | AI39: 1
K40: Средства управления доступом к | L40: Совокупность программных или программно-аппаратных технических средств безопасности, которые должны ограничивать и регистрировать доступ к ресурсам информационной системы | M40: 45263 | N40: 3.12 | O40: =N43&" - "&K43 -> 3.15 - Средства обнаружения угроз и расследования сетевых инцидентов | AG40: 41210100 | AH40: Сырье и материалы (ТД) | AI40: 2(1)
K41: Средства резервного копирования | L41: Программное обеспечение, которое должно обеспечивать создание копии данных на носителе (жестком диске, твердотельных накопителях и иных носителях) и которое должно обеспечивать их восстановление в оригинальном или новом месте в случае их повреждения или утраты | M41: 41334 | N41: 3.13 | O41: =N44&" - "&K44 -> 3.16 - Средства администрирования и управления жизненным циклом ключевых носителей | AG41: 41210101 | AH41: Сырье и материалы | AI41: 3
K42: Средства обнаружения и/или предотвращения вторжений (атак) | L42: Системы, которые должны позволять обнаруживать вторжения уровня сети, уровня узла | M42: 41699 | N42: 3.14 | O42: =N45&" - "&K45 -> 3.17 - Средства автоматизации процессов информационной безопасности | AG42: 41210102 | AH42: Полуфабрикаты и комплектующие | AI42: 3
K43: Средства обнаружения угроз и расследования сетевых инцидентов | L43: Программное обеспечение, которое должно выявлять вредоносную активность, присутствие злоумышленников, нецелевое использование ресурсов, халатность администраторов и должно позволять расследовать сетевые инциденты информационной безопасности | M43: 42064 | N43: 3.15 | O43: =N47&" - "&K47 -> 4.1 - Средства подготовки исполнимого кода | AG43: 41210103 | AH43: Материалы для технологических нужд | AI43: 3
K44: Средства администрирования и управления жизненным циклом ключевых носителей | L44: Программное обеспечение, которое должно обеспечивать связь между учетными записями пользователей, средствами аутентификации, приложениями и регламентами информационной безопасности | M44: 42430 | N44: 3.16 | O44: =N48&" - "&K48 -> 4.2 - Средства версионного контроля исходного кода | AG44: 41210104 | AH44: Энергия | AI44: 3
K45: Средства автоматизации процессов информационной безопасности | L45: Средства, которые должны автоматизировать процессы управления и обеспечения информационной безопасности, включая менеджмент инцидентов информационной безопасности, учет и контроль безопасности ИТ-активов, контроль соблюдения требований по безопасности, моделирование угроз и управление рисками информационной безопасности, получение и анализ данных об актуальных угрозах с целью прогнозирования вероятных кибератак и их предотвращения | M45: 42795 | N45: 3.17 | O45: =N49&" - "&K49 -> 4.3 - Библиотеки подпрограмм (SDK) | AG45: 41210105 | AH45: Топливо | AI45: 3
J46: Средства разработки | M46: 4 | O46: =N50&" - "&K50 -> 4.4 - Среды разработки, тестирования и отладки | AG46: 41210106 | AH46: Специальная оснастка | AI46: 3
K47: Средства подготовки исполнимого кода | L47: Программное обеспечение, которое должно переводить текст программы на высокоуровневом языке программирования в набор инструкций на машинном языке (ассемблеры, трансляторы, компиляторы, интерпретаторы, редакторы связей) | M47: 44930 | N47: 4.1 | O47: =N51&" - "&K51 -> 4.5 - Средства анализа исходного кода на закладки и уязвимости | AG47: 41210107 | AH47: Спецодежда и средства индивидуальной защиты | AI47: 3
K48: Средства версионного контроля исходного кода | L48: Программное обеспечение, которое должно позволять хранить несколько версий одного и того же документа и при необходимости возвращать к более ранним версиям и определять кем и когда были сделаны те или иные изменения | M48: 44961 | N48: 4.2 | O48: =N52&" - "&K52 -> 4.6 - Средства разработки программного обеспечения на основе нейротехнологий и искусственного интеллекта | AG48: 41210108 | AH48: Товары для перепродажи | AI48: 3
K49: Библиотеки подпрограмм (SDK) | L49: Комплект средств разработки, который должен позволять разработчику программного обеспечения создавать приложения для определенного пакета программ или платформы, или операционных систем | M49: 44989 | N49: 4.3 | O49: =N53&" - "&K53 -> 4.7 - Средства разработки программного обеспечения на основе квантовых технологий | AG49: 41210199 | AH49: Прочие платежи за сырье и материалы (ТД) | AI49: 3
K50: Среды разработки, тестирования и отладки | L50: Интегрированные программы, которые должны быть необходимыми для разработки программного обеспечения, включающие специализированное программное обеспечение, процедуры и документы | M50: 45020 | N50: 4.4 | O50: =N54&" - "&K54 -> 4.8 - Интегрированные платформы для создания приложений | AG50: 41210200 | AH50: Оборудование | AI50: 2(1)
K51: Средства анализа исходного кода на закладки и уязвимости | L51: Средства, которые должны позволять проводить аудит безопасности исходного кода с использованием автоматизированных средств и ручной обработки данных | M51: 45050 | N51: 4.5 | O51: =N55&" - "&K55 -> 4.9 - Системы предотвращения анализа и восстановления исполняемого кода программ | AG51: 41210201 | AH51: Оборудование, мебель (малоценное имущество) | AI51: 3
K52: Средства разработки программного обеспечения на основе нейротехнологий и искусственного интеллекта | L52: Программное обеспечение, которое должно позволять разрабатывать продукты на основе технологий компьютерного зрения, обработки естественного языка, распознавания и синтеза речи, а также модули рекомендательных средств и средств поддержки принятия решений | M52: 45081 | N52: 4.6 | O52: =N59&" - "&K59 -> 5.1 - Мультимедийное программное обеспечение | AG52: 41210300 | AH52: Аренда | AI52: 2(2)
K53: Средства разработки программного обеспечения на основе квантовых технологий | L53: Программное обеспечение, которое должно позволять разрабатывать продукты на основе принципов квантовой механики и квантовых коммуникаций | M53: 45111 | N53: 4.7 | O53: =N60&" - "&K60 -> 5.2 - Дополнительные программные модули (плагины) | AG53: 41210301 | AH53: Операционная аренда помещений, зданий и сооружений | AI53: 3
K54: Интегрированные платформы для создания приложений | L54: Программные платформы (конструкторы), которые должны позволять разрабатывать и запускать приложения | M54: 45142 | N54: 4.8 | O54: =N61&" - "&K61 -> 5.3 - Игры и развлечения | AG54: 41210302 | AH54: Операционная аренда транспортных средств | AI54: 3
K55: Системы предотвращения анализа и восстановления исполняемого кода программ | L55: Программное обеспечение, которое должно позволять защищать готовые исполняемые коды программ или исходные тексты программ от их анализа и восстановления | M55: 45173 | N55: 4.9 | O55: =N62&" - "&K62 -> 5.4 - Поисковые средства | AG55: 41210303 | AH55: Операционная аренда машин и оборудования (кроме ИТ-оборудования) | AI55: 3
J56: Прикладное | M56: 5 | O56: =N63&" - "&K63 -> 5.5 - Средства управления проектами | AG56: 41210304 | AH56: Операционная аренда земельных участков | AI56: 3
J57: программное | O57: =N64&" - "&K64 -> 5.6 - Геоинформационные и навигационные средства (GIS) | AG57: 41210399 | AH57: Прочая операционная аренда (за исключением лизинга) | AI57: 3
J58: обеспечение | O58: =N65&" - "&K65 -> 5.7 - Специализированное ПО органов исполнительной власти Российской Федерации, государственных корпораций, компаний и юридических лиц с преимущественным участием Российской Федерации для внутреннего использования | AG58: 41210400 | AH58: Информационные технологии | AI58: 2(2)
K59: Мультимедийное программное обеспечение | L59: Программы, которые должны обеспечивать представление информации в виде звука, анимированной компьютерной графики, видеоряда | M59: 44931 | N59: 5.1 | O59: =N66&" - "&K66 -> 5.8 - Средства управления контактными центрами | AG59: 41210401 | AH59: Аренда ИТ-оборудования и вычислительных мощностей | AI59: 3
K60: Дополнительные программные модули (плагины) | L60: Независимо компилируемые программные модули, которые должны быть динамически подключаемыми к основной программе и предназначенными для расширения ее возможностей | M60: 44962 | N60: 5.2 | O60: =N67&" - "&K67 -> 5.9 - Средства управления диалоговыми роботами (чат-боты и голосовые роботы) | AG60: 41210402 | AH60: Приобретение прав пользования ПО (лицензии) | AI60: 3
K61: Игры и развлечения | L61: Программы, которые должны организовывать игровой процесс, связь с партнерами по игре или которые могут сами выступать в качестве партнера | M61: 44990 | N61: 5.3 | O61: =N68&" - "&K68 -> 5.10 - Базы знаний | AG61: 41210403 | AH61: Услуги связи (связь, интернет) | AI61: 3
K62: Поисковые средства | L62: Программное обеспечение, которое должно быть предназначено для поиска текстовой, графической и другой информации в локальных и корпоративных хранилищах (в том числе консультационно-информационные средства поиска и просмотра информации в специализированных многоотраслевых базах данных) | M62: 45021 | N62: 5.4 | O62: =N69&" - "&K69 -> 5.11 - Интеллектуальные средства управления экспертной деятельностью | AG62: 41210499 | AH62: Прочие ИТ-услуги | AI62: 3
K63: Средства управления проектами | L63: Программное обеспечение, которое должно позволять управлять проектами, портфелями и программами проектов, которое реализует функции планирования и анализа эффективности проектов, управления ресурсами и финансами проектов, контроля реализации проектов, управления рисками и изменениями в проектах, управления коммуникациями, автоматизации построения консолидированной отчетности | M63: 45051 | N63: 5.5 | O63: =N70&" - "&K70 -> 5.12 - Интеллектуальные средства разработки и управления стандартами и нормативами | AG63: 41210500 | AH63: Консалтинг | AI63: 2(2)
K64: Геоинформационные и навигационные средства (GIS) | L64: Программное обеспечение, которое должно позволять собирать, хранить, анализировать и графически визуализировать пространственные (географические) данные и связанные с ними информацию о необходимых объектах, в том числе средства позиционирования в режиме реального времени | M64: 45082 | N64: 5.6 | O64: =N71&" - "&K71 -> 5.13 - Средства интеллектуальной обработки информации и интеллектуального анализа бизнес-процессов | AG64: 41210501 | AH64: Консультационные, юридические, аудиторские, информационные услуги | AI64: 3
K65: Специализированное ПО органов исполнительной власти Российской Федерации, государственных корпораций, компаний и юридических лиц с преимущественным участием Российской Федерации для внутреннего использования | L65: Программное обеспечение, разработанное органами исполнительной власти Российской Федерации, | M65: 45112 | N65: 5.7 | O65: =N72&" - "&K72 -> 5.14 - Справочно-правовые системы | AG65: 41210600 | AH65: Ремонт | AI65: 2(2)
K66: Средства управления контактными центрами | L66: Программное обеспечение, которое должно позволять организацию корпоративного или аутсорсингового контакт-центра | M66: 45143 | N66: 5.8 | O66: =N73&" - "&K73 -> 5.15 - Информационные системы для решения специфических отраслевых задач | AG66: 41210601 | AH66: Ремонт и содержание ОС | AI66: 3
K67: Средства управления диалоговыми роботами (чат-боты и голосовые роботы) | L67: Программное обеспечение, которое должно быть предназначено для создания голосовых роботов и чат-ботов для обслуживания клиентов, внедрения их в контакт-центры, управления работой искусственного интеллекта сотрудников | M67: 45174 | N67: 5.9 | O67: =N74&" - "&K74 -> 5.16 - Автоматизированные информационные системы оформления воздушных перевозок | AG67: 41210700 | AH67: Прочие расходы на персонал (ТД) | AI67: 2(2)
K68: Базы знаний | L68: Программное обеспечение, которое должно быть предназначено для автоматизации процесса управления знаниями | M68: 45204 | N68: 5.10 | O68: =N76&" - "&K76 -> 6.1 - Файловые менеджеры | AG68: 41210701 | AH68: Питание сотрудников | AI68: 3
K69: Интеллектуальные средства управления экспертной деятельностью | L69: Прикладное программное обеспечение, которое должно быть предназначено для автоматизации процесса проведения экспертизы с применением искусственного интеллекта | M69: 45235 | N69: 5.11 | O69: =N77&" - "&K77 -> 6.2 - Коммуникационное программное обеспечение | AG69: 41210702 | AH69: Обучение сотрудников | AI69: 3
K70: Интеллектуальные средства разработки и управления стандартами и нормативами | L70: Программное обеспечение, которое должно быть предназначено для разработки и управления стандартами нормативами с использованием искусственного интеллекта | M70: 45265 | N70: 5.12 | O70: =N78&" - "&K78 -> 6.3 - Офисные пакеты | AG70: 41210799 | AH70: Прочие расходы на персонал | AI70: 3
K71: Средства интеллектуальной обработки информации и интеллектуального анализа бизнес-процессов | L71: Программное обеспечение, которое должно быть предназначено для решения задач, возникающих на различных этапах управления данными в организации, в том числе преобразования, поиска и анализа информации | M71: 41395 | N71: 5.13 | O71: =N79&" - "&K79 -> 6.4 - Почтовые приложения | AG71: 41210800 | AH71: Платежи сторонним организациям за НИОКР по основной деятельности | AI71: 2(2)
K72: Справочно-правовые системы | L72: Программы, которые должны обеспечивать информационное сопровождение работы: содержат нормативные правовые акты, судебную практику, постатейные комментарии, профессиональные юридические журналы и прочую профессиональную юридическую литературу и обеспечивают некоторый уровень связности этих элементов через механизмы перекрестных ссылок, истории версий и поиска | M72: 41760 | N72: 5.14 | O72: =N80&" - "&K80 -> 6.5 - Органайзеры | AG72: 41210801 | AH72: Платежи сторонним организациям за НИОКР по основной деятельности | AI72: 3
K73: Информационные системы для решения специфических отраслевых задач | L73: Программные системы, которые должны быть предназначены для специализированного информационного обеспечения государственного управления, жилищно-коммунального хозяйства, социальной защиты и обеспечения норм труда, здравоохранения,обеспечения безопасности, видеонаблюдения и контроля доступа, оборонно-промышленного комплекса, образования, производства и машиностроения, радиочастотной идентификации, промышленности, страхования, строительства, телекоммуникаций и средств массовой информации, торговли, транспорта и перевозок, финансов и банковского сектора, энергетики и нефтегазовой отрасли, юриспруденции, фармацевтики, рекламы, гостиничного и туристического бизнеса, таможенного оформления и информационной поддержки внешнеэкономической деятельности предприятий, железнодорожной логистики | M73: 42125 | N73: 5.15 | O73: =N81&" - "&K81 -> 6.6 - Средства просмотра | AG73: 41210900 | AH73: Платежи за прочие работы, услуги | AI73: 2(2)
K74: Автоматизированные информационные системы оформления воздушных перевозок | L74: Комплексные автоматизированные информационные системы, реализующие производственные процессы по обслуживанию потребителей услуг авиационных пассажирских перевозок (авиапассажиры и багаж) на всех этапах и организующие необходимую информационную структуру для осуществления авиакомпанией ее производственной деятельности | M74: 42491 | N74: 5.16 | O74: =N82&" - "&K82 -> 6.7 - Браузеры | AG74: 41210901 | AH74: Командировочные расходы (проезд, проживание) | AI74: 3
J75: Офисные приложения | M75: 6 | O75: =N83&" - "&K83 -> 6.8 - Редакторы мультимедиа | AG75: 41210902 | AH75: Сертификация, аккредитация, контроль качества продукции | AI75: 3
K76: Файловые менеджеры | L76: Программное обеспечение, которое должно позволять создавать, удалять, копировать и перемещать файлы в доступных пользователю хранилищах файлов | M76: 44932 | N76: 6.1 | O76: =N84&" - "&K84 -> 6.9 - Редакторы презентаций | AG76: 41210903 | AH76: Прочие услуги производственного характера | AI76: 3
K77: Коммуникационное программное обеспечение | L77: Программное обеспечение, которое должно позволять организовать коммуникации пользователей, в том числе в виде голосовых и видеозвонков, обмениваться текстовыми сообщениями, файлами, электронными письмами | M77: 44963 | N77: 6.2 | O77: =N85&" - "&K85 -> 6.10 - Табличные редакторы | AG77: 41210904 | AH77: Платежи в связи с участием в выставках, симпозиумах, семинарах, конференциях, форумах | AI77: 3
K78: Офисные пакеты | L78: Программное обеспечение, которое должно позволять создавать, просматривать и редактировать электронные документы | M78: 44991 | N78: 6.3 | O78: =N86&" - "&K86 -> 6.11 - Текстовые редакторы | AG78: Код статьи | AH78: Статьи БДДС | AI78: Уровень
K79: Почтовые приложения | L79: Программное обеспечение, которое должно предоставлять доступ пользователя к его электронному почтовому ящику с учетом разграничения прав, позволять получать, создавать, просматривать, редактировать, отправлять и хранить сообщения электронной почты | M79: 45022 | N79: 6.4 | O79: =N87&" - "&K87 -> 6.12 - Системы электронного документооборота | AG79: 41210905 | AH79: Коммунальные услуги (электроэнергия, водоснабжение, тепло, газ и др.) | AI79: 3
K80: Органайзеры | L80: Программное обеспечение, которое должно позволять организовывать информацию о личных контактах, задачах и событиях пользователя | M80: 45052 | N80: 6.5 | O80: =N91&" - "&K91 -> 7.1 - Парсеры и семантические анализаторы | AG80: 41210906 | AH80: Содержание объектов непромышленной и социальной сферы | AI80: 3
K81: Средства просмотра | L81: Программное обеспечение, которое должно быть предназначено исключительно для просмотра файлов (электронных документов) | M81: 45083 | N81: 6.6 | O81: =N92&" - "&K92 -> 7.2 - Средства речевого перевода | AG81: 41210907 | AH81: Охрана объектов | AI81: 3
K82: Браузеры | L82: Программное обеспечение, которое должно предоставлять возможность для взаимодействия пользователя с удаленными (или локальными) ресурсами информационной сети Интернет | M82: 45113 | N82: 6.7 | O82: =N93&" - "&K93 -> 7.3 - Средства распознавания символов | AG82: 41210908 | AH82: ГО и предупреждение ЧС | AI82: 3
K83: Редакторы мультимедиа | L83: Программное обеспечение, которое должно обеспечивать создание, просмотр и редактирование информации в виде графики, звука, анимированной компьютерной графики, видеоряда | M83: 45144 | N83: 6.8 | O83: =N94&" - "&K94 -> 7.4 - Средства распознавания и синтеза речи | AG83: 41210909 | AH83: Охрана труда и техника безопасности, обеспечение пожарной, экологической и промышленной безопасности | AI83: 3
K84: Редакторы презентаций | L84: Программное обеспечение, которое должно обеспечивать создание, просмотр, редактирование и демонстрацию | M84: 45175 | N84: 6.9 | O84: =N95&" - "&K95 -> 7.5 - Средства автоматизированного перевода | AG84: 41210910 | AH84: Прочие хозяйственные расходы | AI84: 3
K85: Табличные редакторы | L85: Программное обеспечение, которое должно обеспечивать создание, просмотр и редактирование электронных таблиц | M85: 45205 | N85: 6.10 | O85: =N96&" - "&K96 -> 7.6 - Электронные словари | AG85: 41210999 | AH85: Платежи поставщикам за прочие СиМ, работы, услуги | AI85: 3
K86: Текстовые редакторы | L86: Программное обеспечение, которое должно обеспечивать создание, просмотр и редактирование текстовых файлов | M86: 45236 | N86: 6.11 | O86: =N97&" - "&K97 -> 7.7 - Средства проверки правописания | AG86: 41211000 | AH86: Страхование | AI86: 2
K87: Системы электронного документооборота | L87: Программное обеспечение, которое должно предоставлять возможность управления различными видами электронных документов, обеспечивать создание, изменение, хранение, передачу, обмен, согласование, в том числе между различными субъектами, поиск документов на протяжении всего их жизненного цикла | M87: 45266 | N87: 6.12 | O87: =N101&" - "&K101 -> 8.1 - Средства управления жизненным циклом изделия (PLM) | AG87: 41211001 | AH87: Страхование пусков и космических объектов | AI87: 3
J88: Лингвистическое | M88: 7 | O88: =N102&" - "&K102 -> 8.2 - Универсальные машиностроительные средства автоматизированного проектирования (MCAD) | AG88: 41211002 | AH88: Страхование имущества | AI88: 3
J89: программное | O89: =N103&" - "&K103 -> 8.3 - Средства автоматизированного проектирования (CAD) | AG89: 41211003 | AH89: Страхование груза | AI89: 3
J90: обеспечение | O90: =N104&" - "&K104 -> 8.4 - Средства автоматизированного проектирования для радиоэлектроники и электротехники (ECAD, EDA) | AG90: 41211004 | AH90: Страхование персонала | AI90: 3
K91: Парсеры и семантические анализаторы | L91: Программы, которые должны позволять анализировать тексты на естественных языках с выделением синтаксических структур в предложениях или выделением семантических отношений между элементами текста и общего смысла текстов | M91: 44933 | N91: 7.1 | O91: =N105&" - "&K105 -> 8.5 - Средства инженерного анализа (CAE) | AG91: 41211005 | AH91: Страхование ответственности | AI91: 3
K92: Средства речевого перевода | L92: Средства, которые должны предоставлять возможность проведения анализа, синтеза и голосового перевода | M92: 44964 | N92: 7.2 | O92: =N106&" - "&K106 -> 8.6 - Средства управления оборудованием с числовым программным управлением (САМ) | AG92: 41211006 | AH92: Страхование транспорта | AI92: 3
K93: Средства распознавания символов | L93: Программы, которые должны позволять переводить изображения документов (фотографий, результатов сканирования, PDF-файлов) в электронные редактируемые форматы | M93: 44992 | N93: 7.3 | O93: =N107&" - "&K107 -> 8.7 - Средства технологической подготовки производства (САРР) | AG93: 41211099 | AH93: Прочее страхование | AI93: 3
K94: Средства распознавания и синтеза речи | L94: Программы, которые должны предоставлять возможность преобразования речевого сигнала в электронные редактируемые форматы и синтез речевого сигнала на основе данных электронного редактируемого формата | M94: 45023 | N94: 7.4 | O94: =N108&" - "&K108 -> 8.8 - Средства управления инженерными данными об изделии (PDM) | AG94: 4122 | AH94: оплата труда работников | AI94: 1
K95: Средства автоматизированного перевода | L95: Средства, которые должны предоставлять возможность автоматизированного перевода текстов и документов разных форматов | M95: 45053 | N95: 7.5 | O95: =N109&" - "&K109 -> 8.9 - Средства информационного моделирования зданий и сооружений, архитектурно-строительного проектирования (BIM, АЕС CAD) | AG95: 41220100 | AH95: Оплата труда | AI95: 2
K96: Электронные словари | L96: Словарь в электронной форме, который должен предоставлять возможность поиска значения или перевода слов и словосочетаний | M96: 45084 | N96: 7.6 | O96: =N110&" - "&K110 -> 8.10 - Средства усовершенствованного управления технологическими процессами (АРС, RTO) | AG96: 41220101 | AH96: Оплата труда | AI96: 3
K97: Средства проверки правописания | L97: Средства, которые должны предоставлять возможность поиска орфографических ошибок в электронных текстах | M97: 45114 | N97: 7.7 | O97: =N111&" - "&K111 -> 8.11 - Средства автоматизированного управления техникой | AG97: 4123 | AH97: обязательных взносов на соц. страхование | AI97: 1
J98: Промышленное | M98: 8 | O98: =N115&" - "&K115 -> 9.1 - Средства управления бизнес-процессами (ВРМ) | AG98: 41230100 | AH98: Страховые взносы | AI98: 2
J99: программное | O99: =N116&" - "&K116 -> 9.2 - Средства управления производственными процессами (MES) | AG99: 41230101 | AH99: Страховые взносы | AI99: 3
J100: обеспечение | O100: =N117&" - "&K117 -> 9.3 - Средства управления лабораторными потоками работ и документов (LIMS) | AG100: 4124 | AH100: налога на прибыль организаций | AI100: 1
...

Sheet Проверочный лист
A1: Наименование организации | B1: Наименование филиала | C1: Источник финансирования | D1: Статья затрат | E1: ID инвестиционного проекта | F1: Отметка о типе проекта | G1: Объем финансирования инвестиционного проекта, всего, тыс. руб. | H1: Пункт мероприятия Программы ЦТ (Стратегии ЦТ) | I1: Номер в реестре отеч ПО | J1: Класс предмета закупки | K1: Предмет закупки | L1: Подробное описание объекта закупки (товара, работы или услуги) | M1: Отметка о закупке у Отраслевого оператора | N1: Сумма с НДС, тыс. руб
N2: Факт (текущий год) | O2: План (след. Год) | P2: 1-е квартал след года | Q2: 2-е квартал след года | R2: 3-е квартал след года | S2: 4-е квартал след года | T2: Месяц поставки | U2: Год поставки | V2: План (след. Год+1) | W2: План (след. Год+2)
P3: План | Q3: План | R3: План | S3: План | T3: План | U3: План
A4: 1 | B4: 2 | C4: 3 | D4: 4 | E4: 5 | F4: 6 | G4: 7 | H4: 8 | I4: 9 | J4: 10 | K4: 11 | L4: 12 | M4: 13 | N4: 14 | O4: 15 | P4: 16 | Q4: 17 | R4: 18 | S4: 19 | T4: 20 | U4: 21 | V4: 22 | W4: 23
A5: =IF(AND('План Факт 2025'!B5<>"",'План Факт 2025'!A5=""),"Требует заполнения","ОК") -> ОК | C5: =IF(AND('План Факт 2025'!C5="",SUM('План Факт 2025'!Q5,'План Факт 2025'!R5,'План Факт 2025'!Z5,'План Факт 2025'!AA5)>0),"Требует заполнения","ОК") -> ОК | D5: =IF(OR(AND('План Факт 2025'!D5="",'План Факт 2025'!C5="Инвестиционный_проект"),AND('План Факт 2025'!D5="",'План Факт 2025'!C5="Операционный_бюджет")),"Требует заполнения", IF('План Факт 2025'!D5="","ОК",IFERROR(VLOOKUP('План Факт 2025'!C5&'План Факт 2025'!D5,статьи,1,FALSE()),"Требует исправления"))) -> Инвестиционный_проектИТ_оборудование_и_комплектующие_ИП | E5: =IF(AND('План Факт 2025'!C5="Инвестиционный_проект",'План Факт 2025'!G5=""),"Требует заполнения",IF(AND('План Факт 2025'!C5<>"Инвестиционный_проект",'План Факт 2025'!G5<>""),"Требует изменения","ОК")) -> ОК | G5: =IF(AND('План Факт 2025'!C5="Инвестиционный_проект",'План Факт 2025'!I5=""),"Требует заполнения","ОК") -> ОК | H5: =IF(AND('План Факт 2025'!C5="ФОТ",'План Факт 2025'!J5=""),"Требует заполнения","ОК") -> ОК | J5: =IF(OR(AND('План Факт 2025'!D5="Программное_обеспечение_лицензии",'План Факт 2025'!L5=""),AND('План Факт 2025'!D5="Приобретение_ПО",'План Факт 2025'!L5=""),AND('План Факт 2025'!D5="ИТ_оборудование_и_комплектующие_ИП",'План Факт 2025'!L5=""),AND('План Факт 2025'!D5="ИТ_оборудование_и_комплектующие",'План Факт 2025'!L5="")),"Требует заполнения","ОК") -> ОК | K5: =IF(OR(AND('План Факт 2025'!C5="Операционный_бюджет",'План Факт 2025'!D5="Программное_обеспечение_лицензии",'План Факт 2025'!M5=""),AND('План Факт 2025'!C5="Инвестиционный_проект",'План Факт 2025'!D5="Приобретение_ПО",'План Факт 2025'!M5=""),AND('План Факт 2025'!D5="ИТ_оборудование_и_комплектующие_ИП",'План Факт 2025'!M5=""),AND('План Факт 2025'!D5="ИТ_оборудование_и_комплектующие",'План Факт 2025'!M5="")),"Требует заполнения","ОК") -> ОК | L5: =IF(OR(AND('План Факт 2025'!D5="Программное_обеспечение_лицензии",'План Факт 2025'!N5="",'План Факт 2025'!M5=""),AND('План Факт 2025'!D5="Приобретение_ПО",'План Факт 2025'!M5="",'План Факт 2025'!N5="",'План Факт 2025'!M5=""),AND('План Факт 2025'!C5<>"",'План Факт 2025'!N5="",'План Факт 2025'!M5="")),"Требует заполнения","ОК") -> ОК | N5: =IF(OR('План Факт 2025'!C5="ФОТ",SUM('План Факт 2025'!Q5,'План Факт 2025'!R5,'План Факт 2025'!Z5,'План Факт 2025'!AA5)>0),"ОК",IF('План Факт 2025'!C5="","ОК","Требует заполнения")) -> ОК | T5: =IF(AND('План Факт 2025'!R5>0,'План Факт 2025'!X5=""),"Требует заполнения","ОК") -> ОК | U5: =IF(AND('План Факт 2025'!R5>0,'План Факт 2025'!Y5=""),"Требует заполнения","ОК") -> ОК
A6: =IF(AND('План Факт 2025'!B6<>"",'План Факт 2025'!A6=""),"Требует заполнения","ОК") -> ОК | C6: =IF(AND('План Факт 2025'!C6="",SUM('План Факт 2025'!Q6,'План Факт 2025'!R6,'План Факт 2025'!Z6,'План Факт 2025'!AA6)>0),"Требует заполнения","ОК") -> ОК | D6: =IF(OR(AND('План Факт 2025'!D6="",'План Факт 2025'!C6="Инвестиционный_проект"),AND('План Факт 2025'!D6="",'План Факт 2025'!C6="Операционный_бюджет")),"Требует заполнения", IF('План Факт 2025'!D6="","ОК",IFERROR(VLOOKUP('План Факт 2025'!C6&'План Факт 2025'!D6,статьи,1,FALSE()),"Требует исправления"))) -> Инвестиционный_проектИТ_оборудование_и_комплектующие_ИП | E6: =IF(AND('План Факт 2025'!C6="Инвестиционный_проект",'План Факт 2025'!G6=""),"Требует заполнения",IF(AND('План Факт 2025'!C6<>"Инвестиционный_проект",'План Факт 2025'!G6<>""),"Требует изменения","ОК")) -> ОК | G6: =IF(AND('План Факт 2025'!C6="Инвестиционный_проект",'План Факт 2025'!I6=""),"Требует заполнения","ОК") -> ОК | H6: =IF(AND('План Факт 2025'!C6="ФОТ",'План Факт 2025'!J6=""),"Требует заполнения","ОК") -> ОК | J6: =IF(OR(AND('План Факт 2025'!D6="Программное_обеспечение_лицензии",'План Факт 2025'!L6=""),AND('План Факт 2025'!D6="Приобретение_ПО",'План Факт 2025'!L6=""),AND('План Факт 2025'!D6="ИТ_оборудование_и_комплектующие_ИП",'План Факт 2025'!L6=""),AND('План Факт 2025'!D6="ИТ_оборудование_и_комплектующие",'План Факт 2025'!L6="")),"Требует заполнения","ОК") -> ОК | K6: =IF(OR(AND('План Факт 2025'!C6="Операционный_бюджет",'План Факт 2025'!D6="Программное_обеспечение_лицензии",'План Факт 2025'!M6=""),AND('План Факт 2025'!C6="Инвестиционный_проект",'План Факт 2025'!D6="Приобретение_ПО",'План Факт 2025'!M6=""),AND('План Факт 2025'!D6="ИТ_оборудование_и_комплектующие_ИП",'План Факт 2025'!M6=""),AND('План Факт 2025'!D6="ИТ_оборудование_и_комплектующие",'План Факт 2025'!M6="")),"Требует заполнения","ОК") -> ОК | L6: =IF(OR(AND('План Факт 2025'!D6="Программное_обеспечение_лицензии",'План Факт 2025'!N6="",'План Факт 2025'!M6=""),AND('План Факт 2025'!D6="Приобретение_ПО",'План Факт 2025'!M6="",'План Факт 2025'!N6="",'План Факт 2025'!M6=""),AND('План Факт 2025'!C6<>"",'План Факт 2025'!N6="",'План Факт 2025'!M6="")),"Требует заполнения","ОК") -> ОК | N6: =IF(OR('План Факт 2025'!C6="ФОТ",SUM('План Факт 2025'!Q6,'План Факт 2025'!R6,'План Факт 2025'!Z6,'План Факт 2025'!AA6)>0),"ОК",IF('План Факт 2025'!C6="","ОК","Требует заполнения")) -> ОК | T6: =IF(AND('План Факт 2025'!R6>0,'План Факт 2025'!X6=""),"Требует заполнения","ОК") -> ОК | U6: =IF(AND('План Факт 2025'!R6>0,'План Факт 2025'!Y6=""),"Требует заполнения","ОК") -> ОК
A7: =IF(AND('План Факт 2025'!B7<>"",'План Факт 2025'!A7=""),"Требует заполнения","ОК") -> ОК | C7: =IF(AND('План Факт 2025'!C7="",SUM('План Факт 2025'!Q7,'План Факт 2025'!R7,'План Факт 2025'!Z7,'План Факт 2025'!AA7)>0),"Требует заполнения","ОК") -> ОК | D7: =IF(OR(AND('План Факт 2025'!D7="",'План Факт 2025'!C7="Инвестиционный_проект"),AND('План Факт 2025'!D7="",'План Факт 2025'!C7="Операционный_бюджет")),"Требует заполнения", IF('План Факт 2025'!D7="","ОК",IFERROR(VLOOKUP('План Факт 2025'!C7&'План Факт 2025'!D7,статьи,1,FALSE()),"Требует исправления"))) -> Инвестиционный_проектИТ_оборудование_и_комплектующие_ИП | E7: =IF(AND('План Факт 2025'!C7="Инвестиционный_проект",'План Факт 2025'!G7=""),"Требует заполнения",IF(AND('План Факт 2025'!C7<>"Инвестиционный_проект",'План Факт 2025'!G7<>""),"Требует изменения","ОК")) -> ОК | G7: =IF(AND('План Факт 2025'!C7="Инвестиционный_проект",'План Факт 2025'!I7=""),"Требует заполнения","ОК") -> ОК | H7: =IF(AND('План Факт 2025'!C7="ФОТ",'План Факт 2025'!J7=""),"Требует заполнения","ОК") -> ОК | J7: =IF(OR(AND('План Факт 2025'!D7="Программное_обеспечение_лицензии",'План Факт 2025'!L7=""),AND('План Факт 2025'!D7="Приобретение_ПО",'План Факт 2025'!L7=""),AND('План Факт 2025'!D7="ИТ_оборудование_и_комплектующие_ИП",'План Факт 2025'!L7=""),AND('План Факт 2025'!D7="ИТ_оборудование_и_комплектующие",'План Факт 2025'!L7="")),"Требует заполнения","ОК") -> ОК | K7: =IF(OR(AND('План Факт 2025'!C7="Операционный_бюджет",'План Факт 2025'!D7="Программное_обеспечение_лицензии",'План Факт 2025'!M7=""),AND('План Факт 2025'!C7="Инвестиционный_проект",'План Факт 2025'!D7="Приобретение_ПО",'План Факт 2025'!M7=""),AND('План Факт 2025'!D7="ИТ_оборудование_и_комплектующие_ИП",'План Факт 2025'!M7=""),AND('План Факт 2025'!D7="ИТ_оборудование_и_комплектующие",'План Факт 2025'!M7="")),"Требует заполнения","ОК") -> ОК | L7: =IF(OR(AND('План Факт 2025'!D7="Программное_обеспечение_лицензии",'План Факт 2025'!N7="",'План Факт 2025'!M7=""),AND('План Факт 2025'!D7="Приобретение_ПО",'План Факт 2025'!M7="",'План Факт 2025'!N7="",'План Факт 2025'!M7=""),AND('План Факт 2025'!C7<>"",'План Факт 2025'!N7="",'План Факт 2025'!M7="")),"Требует заполнения","ОК") -> ОК | N7: =IF(OR('План Факт 2025'!C7="ФОТ",SUM('План Факт 2025'!Q7,'План Факт 2025'!R7,'План Факт 2025'!Z7,'План Факт 2025'!AA7)>0),"ОК",IF('План Факт 2025'!C7="","ОК","Требует заполнения")) -> ОК | T7: =IF(AND('План Факт 2025'!R7>0,'План Факт 2025'!X7=""),"Требует заполнения","ОК") -> ОК | U7: =IF(AND('План Факт 2025'!R7>0,'План Факт 2025'!Y7=""),"Требует заполнения","ОК") -> ОК
A8: =IF(AND('План Факт 2025'!B8<>"",'План Факт 2025'!A8=""),"Требует заполнения","ОК") -> ОК | C8: =IF(AND('План Факт 2025'!C8="",SUM('План Факт 2025'!Q8,'План Факт 2025'!R8,'План Факт 2025'!Z8,'План Факт 2025'!AA8)>0),"Требует заполнения","ОК") -> ОК | D8: =IF(OR(AND('План Факт 2025'!D8="",'План Факт 2025'!C8="Инвестиционный_проект"),AND('План Факт 2025'!D8="",'План Факт 2025'!C8="Операционный_бюджет")),"Требует заполнения", IF('План Факт 2025'!D8="","ОК",IFERROR(VLOOKUP('План Факт 2025'!C8&'План Факт 2025'!D8,статьи,1,FALSE()),"Требует исправления"))) -> Операционный_бюджетИТ_оборудование_и_комплектующие | E8: =IF(AND('План Факт 2025'!C8="Инвестиционный_проект",'План Факт 2025'!G8=""),"Требует заполнения",IF(AND('План Факт 2025'!C8<>"Инвестиционный_проект",'План Факт 2025'!G8<>""),"Требует изменения","ОК")) -> ОК | G8: =IF(AND('План Факт 2025'!C8="Инвестиционный_проект",'План Факт 2025'!I8=""),"Требует заполнения","ОК") -> ОК | H8: =IF(AND('План Факт 2025'!C8="ФОТ",'План Факт 2025'!J8=""),"Требует заполнения","ОК") -> ОК | J8: =IF(OR(AND('План Факт 2025'!D8="Программное_обеспечение_лицензии",'План Факт 2025'!L8=""),AND('План Факт 2025'!D8="Приобретение_ПО",'План Факт 2025'!L8=""),AND('План Факт 2025'!D8="ИТ_оборудование_и_комплектующие_ИП",'План Факт 2025'!L8=""),AND('План Факт 2025'!D8="ИТ_оборудование_и_комплектующие",'План Факт 2025'!L8="")),"Требует заполнения","ОК") -> ОК | K8: =IF(OR(AND('План Факт 2025'!C8="Операционный_бюджет",'План Факт 2025'!D8="Программное_обеспечение_лицензии",'План Факт 2025'!M8=""),AND('План Факт 2025'!C8="Инвестиционный_проект",'План Факт 2025'!D8="Приобретение_ПО",'План Факт 2025'!M8=""),AND('План Факт 2025'!D8="ИТ_оборудование_и_комплектующие_ИП",'План Факт 2025'!M8=""),AND('План Факт 2025'!D8="ИТ_оборудование_и_комплектующие",'План Факт 2025'!M8="")),"Требует заполнения","ОК") -> ОК | L8: =IF(OR(AND('План Факт 2025'!D8="Программное_обеспечение_лицензии",'План Факт 2025'!N8="",'План Факт 2025'!M8=""),AND('План Факт 2025'!D8="Приобретение_ПО",'План Факт 2025'!M8="",'План Факт 2025'!N8="",'План Факт 2025'!M8=""),AND('План Факт 2025'!C8<>"",'План Факт 2025'!N8="",'План Факт 2025'!M8="")),"Требует заполнения","ОК") -> ОК | N8: =IF(OR('План Факт 2025'!C8="ФОТ",SUM('План Факт 2025'!Q8,'План Факт 2025'!R8,'План Факт 2025'!Z8,'План Факт 2025'!AA8)>0),"ОК",IF('План Факт 2025'!C8="","ОК","Требует заполнения")) -> ОК | T8: =IF(AND('План Факт 2025'!R8>0,'План Факт 2025'!X8=""),"Требует заполнения","ОК") -> ОК | U8: =IF(AND('План Факт 2025'!R8>0,'План Факт 2025'!Y8=""),"Требует заполнения","ОК") -> ОК
A9: =IF(AND('План Факт 2025'!B9<>"",'План Факт 2025'!A9=""),"Требует заполнения","ОК") -> ОК | C9: =IF(AND('План Факт 2025'!C9="",SUM('План Факт 2025'!Q9,'План Факт 2025'!R9,'План Факт 2025'!Z9,'План Факт 2025'!AA9)>0),"Требует заполнения","ОК") -> ОК | D9: =IF(OR(AND('План Факт 2025'!D9="",'План Факт 2025'!C9="Инвестиционный_проект"),AND('План Факт 2025'!D9="",'План Факт 2025'!C9="Операционный_бюджет")),"Требует заполнения", IF('План Факт 2025'!D9="","ОК",IFERROR(VLOOKUP('План Факт 2025'!C9&'План Факт 2025'!D9,статьи,1,FALSE()),"Требует исправления"))) -> Операционный_бюджетЗапчасти_и_расходные_материалы_к_ИТ_оборудованию | E9: =IF(AND('План Факт 2025'!C9="Инвестиционный_проект",'План Факт 2025'!G9=""),"Требует заполнения",IF(AND('План Факт 2025'!C9<>"Инвестиционный_проект",'План Факт 2025'!G9<>""),"Требует изменения","ОК")) -> ОК | G9: =IF(AND('План Факт 2025'!C9="Инвестиционный_проект",'План Факт 2025'!I9=""),"Требует заполнения","ОК") -> ОК | H9: =IF(AND('План Факт 2025'!C9="ФОТ",'План Факт 2025'!J9=""),"Требует заполнения","ОК") -> ОК | J9: =IF(OR(AND('План Факт 2025'!D9="Программное_обеспечение_лицензии",'План Факт 2025'!L9=""),AND('План Факт 2025'!D9="Приобретение_ПО",'План Факт 2025'!L9=""),AND('План Факт 2025'!D9="ИТ_оборудование_и_комплектующие_ИП",'План Факт 2025'!L9=""),AND('План Факт 2025'!D9="ИТ_оборудование_и_комплектующие",'План Факт 2025'!L9="")),"Требует заполнения","ОК") -> ОК | K9: =IF(OR(AND('План Факт 2025'!C9="Операционный_бюджет",'План Факт 2025'!D9="Программное_обеспечение_лицензии",'План Факт 2025'!M9=""),AND('План Факт 2025'!C9="Инвестиционный_проект",'План Факт 2025'!D9="Приобретение_ПО",'План Факт 2025'!M9=""),AND('План Факт 2025'!D9="ИТ_оборудование_и_комплектующие_ИП",'План Факт 2025'!M9=""),AND('План Факт 2025'!D9="ИТ_оборудование_и_комплектующие",'План Факт 2025'!M9="")),"Требует заполнения","ОК") -> ОК | L9: =IF(OR(AND('План Факт 2025'!D9="Программное_обеспечение_лицензии",'План Факт 2025'!N9="",'План Факт 2025'!M9=""),AND('План Факт 2025'!D9="Приобретение_ПО",'План Факт 2025'!M9="",'План Факт 2025'!N9="",'План Факт 2025'!M9=""),AND('План Факт 2025'!C9<>"",'План Факт 2025'!N9="",'План Факт 2025'!M9="")),"Требует заполнения","ОК") -> ОК | N9: =IF(OR('План Факт 2025'!C9="ФОТ",SUM('План Факт 2025'!Q9,'План Факт 2025'!R9,'План Факт 2025'!Z9,'План Факт 2025'!AA9)>0),"ОК",IF('План Факт 2025'!C9="","ОК","Требует заполнения")) -> ОК | T9: =IF(AND('План Факт 2025'!R9>0,'План Факт 2025'!X9=""),"Требует заполнения","ОК") -> ОК | U9: =IF(AND('План Факт 2025'!R9>0,'План Факт 2025'!Y9=""),"Требует заполнения","ОК") -> ОК
A10: =IF(AND('План Факт 2025'!B10<>"",'План Факт 2025'!A10=""),"Требует заполнения","ОК") -> ОК | C10: =IF(AND('План Факт 2025'!C10="",SUM('План Факт 2025'!Q10,'План Факт 2025'!R10,'План Факт 2025'!Z10,'План Факт 2025'!AA10)>0),"Требует заполнения","ОК") -> ОК | D10: =IF(OR(AND('План Факт 2025'!D10="",'План Факт 2025'!C10="Инвестиционный_проект"),AND('План Факт 2025'!D10="",'План Факт 2025'!C10="Операционный_бюджет")),"Требует заполнения", IF('План Факт 2025'!D10="","ОК",IFERROR(VLOOKUP('План Факт 2025'!C10&'План Факт 2025'!D10,статьи,1,FALSE()),"Требует исправления"))) -> Операционный_бюджетИТ_оборудование_и_комплектующие | E10: =IF(AND('План Факт 2025'!C10="Инвестиционный_проект",'План Факт 2025'!G10=""),"Требует заполнения",IF(AND('План Факт 2025'!C10<>"Инвестиционный_проект",'План Факт 2025'!G10<>""),"Требует изменения","ОК")) -> ОК | G10: =IF(AND('План Факт 2025'!C10="Инвестиционный_проект",'План Факт 2025'!I10=""),"Требует заполнения","ОК") -> ОК | H10: =IF(AND('План Факт 2025'!C10="ФОТ",'План Факт 2025'!J10=""),"Требует заполнения","ОК") -> ОК | J10: =IF(OR(AND('План Факт 2025'!D10="Программное_обеспечение_лицензии",'План Факт 2025'!L10=""),AND('План Факт 2025'!D10="Приобретение_ПО",'План Факт 2025'!L10=""),AND('План Факт 2025'!D10="ИТ_оборудование_и_комплектующие_ИП",'План Факт 2025'!L10=""),AND('План Факт 2025'!D10="ИТ_оборудование_и_комплектующие",'План Факт 2025'!L10="")),"Требует заполнения","ОК") -> ОК | K10: =IF(OR(AND('План Факт 2025'!C10="Операционный_бюджет",'План Факт 2025'!D10="Программное_обеспечение_лицензии",'План Факт 2025'!M10=""),AND('План Факт 2025'!C10="Инвестиционный_проект",'План Факт 2025'!D10="Приобретение_ПО",'План Факт 2025'!M10=""),AND('План Факт 2025'!D10="ИТ_оборудование_и_комплектующие_ИП",'План Факт 2025'!M10=""),AND('План Факт 2025'!D10="ИТ_оборудование_и_комплектующие",'План Факт 2025'!M10="")),"Требует заполнения","ОК") -> ОК | L10: =IF(OR(AND('План Факт 2025'!D10="Программное_обеспечение_лицензии",'План Факт 2025'!N10="",'План Факт 2025'!M10=""),AND('План Факт 2025'!D10="Приобретение_ПО",'План Факт 2025'!M10="",'План Факт 2025'!N10="",'План Факт 2025'!M10=""),AND('План Факт 2025'!C10<>"",'План Факт 2025'!N10="",'План Факт 2025'!M10="")),"Требует заполнения","ОК") -> ОК | N10: =IF(OR('План Факт 2025'!C10="ФОТ",SUM('План Факт 2025'!Q10,'План Факт 2025'!R10,'План Факт 2025'!Z10,'План Факт 2025'!AA10)>0),"ОК",IF('План Факт 2025'!C10="","ОК","Требует заполнения")) -> ОК | T10: =IF(AND('План Факт 2025'!R10>0,'План Факт 2025'!X10=""),"Требует заполнения","ОК") -> ОК | U10: =IF(AND('План Факт 2025'!R10>0,'План Факт 2025'!Y10=""),"Требует заполнения","ОК") -> ОК
A11: =IF(AND('План Факт 2025'!B11<>"",'План Факт 2025'!A11=""),"Требует заполнения","ОК") -> ОК | C11: =IF(AND('План Факт 2025'!C11="",SUM('План Факт 2025'!Q11,'План Факт 2025'!R11,'План Факт 2025'!Z11,'План Факт 2025'!AA11)>0),"Требует заполнения","ОК") -> ОК | D11: =IF(OR(AND('План Факт 2025'!D11="",'План Факт 2025'!C11="Инвестиционный_проект"),AND('План Факт 2025'!D11="",'План Факт 2025'!C11="Операционный_бюджет")),"Требует заполнения", IF('План Факт 2025'!D11="","ОК",IFERROR(VLOOKUP('План Факт 2025'!C11&'План Факт 2025'!D11,статьи,1,FALSE()),"Требует исправления"))) -> Операционный_бюджетПрограммное_обеспечение_лицензии | E11: =IF(AND('План Факт 2025'!C11="Инвестиционный_проект",'План Факт 2025'!G11=""),"Требует заполнения",IF(AND('План Факт 2025'!C11<>"Инвестиционный_проект",'План Факт 2025'!G11<>""),"Требует изменения","ОК")) -> ОК | G11: =IF(AND('План Факт 2025'!C11="Инвестиционный_проект",'План Факт 2025'!I11=""),"Требует заполнения","ОК") -> ОК | H11: =IF(AND('План Факт 2025'!C11="ФОТ",'План Факт 2025'!J11=""),"Требует заполнения","ОК") -> ОК | J11: =IF(OR(AND('План Факт 2025'!D11="Программное_обеспечение_лицензии",'План Факт 2025'!L11=""),AND('План Факт 2025'!D11="Приобретение_ПО",'План Факт 2025'!L11=""),AND('План Факт 2025'!D11="ИТ_оборудование_и_комплектующие_ИП",'План Факт 2025'!L11=""),AND('План Факт 2025'!D11="ИТ_оборудование_и_комплектующие",'План Факт 2025'!L11="")),"Требует заполнения","ОК") -> ОК | K11: =IF(OR(AND('План Факт 2025'!C11="Операционный_бюджет",'План Факт 2025'!D11="Программное_обеспечение_лицензии",'План Факт 2025'!M11=""),AND('План Факт 2025'!C11="Инвестиционный_проект",'План Факт 2025'!D11="Приобретение_ПО",'План Факт 2025'!M11=""),AND('План Факт 2025'!D11="ИТ_оборудование_и_комплектующие_ИП",'План Факт 2025'!M11=""),AND('План Факт 2025'!D11="ИТ_оборудование_и_комплектующие",'План Факт 2025'!M11="")),"Требует заполнения","ОК") -> ОК | L11: =IF(OR(AND('План Факт 2025'!D11="Программное_обеспечение_лицензии",'План Факт 2025'!N11="",'План Факт 2025'!M11=""),AND('План Факт 2025'!D11="Приобретение_ПО",'План Факт 2025'!M11="",'План Факт 2025'!N11="",'План Факт 2025'!M11=""),AND('План Факт 2025'!C11<>"",'План Факт 2025'!N11="",'План Факт 2025'!M11="")),"Требует заполнения","ОК") -> ОК | N11: =IF(OR('План Факт 2025'!C11="ФОТ",SUM('План Факт 2025'!Q11,'План Факт 2025'!R11,'План Факт 2025'!Z11,'План Факт 2025'!AA11)>0),"ОК",IF('План Факт 2025'!C11="","ОК","Требует заполнения")) -> ОК | T11: =IF(AND('План Факт 2025'!R11>0,'План Факт 2025'!X11=""),"Требует заполнения","ОК") -> ОК | U11: =IF(AND('План Факт 2025'!R11>0,'План Факт 2025'!Y11=""),"Требует заполнения","ОК") -> ОК
A12: =IF(AND('План Факт 2025'!B12<>"",'План Факт 2025'!A12=""),"Требует заполнения","ОК") -> ОК | C12: =IF(AND('План Факт 2025'!C12="",SUM('План Факт 2025'!Q12,'План Факт 2025'!R12,'План Факт 2025'!Z12,'План Факт 2025'!AA12)>0),"Требует заполнения","ОК") -> ОК | D12: =IF(OR(AND('План Факт 2025'!D12="",'План Факт 2025'!C12="Инвестиционный_проект"),AND('План Факт 2025'!D12="",'План Факт 2025'!C12="Операционный_бюджет")),"Требует заполнения", IF('План Факт 2025'!D12="","ОК",IFERROR(VLOOKUP('План Факт 2025'!C12&'План Факт 2025'!D12,статьи,1,FALSE()),"Требует исправления"))) -> Операционный_бюджетПрограммное_обеспечение_лицензии | E12: =IF(AND('План Факт 2025'!C12="Инвестиционный_проект",'План Факт 2025'!G12=""),"Требует заполнения",IF(AND('План Факт 2025'!C12<>"Инвестиционный_проект",'План Факт 2025'!G12<>""),"Требует изменения","ОК")) -> ОК | G12: =IF(AND('План Факт 2025'!C12="Инвестиционный_проект",'План Факт 2025'!I12=""),"Требует заполнения","ОК") -> ОК | H12: =IF(AND('План Факт 2025'!C12="ФОТ",'План Факт 2025'!J12=""),"Требует заполнения","ОК") -> ОК | J12: =IF(OR(AND('План Факт 2025'!D12="Программное_обеспечение_лицензии",'План Факт 2025'!L12=""),AND('План Факт 2025'!D12="Приобретение_ПО",'План Факт 2025'!L12=""),AND('План Факт 2025'!D12="ИТ_оборудование_и_комплектующие_ИП",'План Факт 2025'!L12=""),AND('План Факт 2025'!D12="ИТ_оборудование_и_комплектующие",'План Факт 2025'!L12="")),"Требует заполнения","ОК") -> ОК | K12: =IF(OR(AND('План Факт 2025'!C12="Операционный_бюджет",'План Факт 2025'!D12="Программное_обеспечение_лицензии",'План Факт 2025'!M12=""),AND('План Факт 2025'!C12="Инвестиционный_проект",'План Факт 2025'!D12="Приобретение_ПО",'План Факт 2025'!M12=""),AND('План Факт 2025'!D12="ИТ_оборудование_и_комплектующие_ИП",'План Факт 2025'!M12=""),AND('План Факт 2025'!D12="ИТ_оборудование_и_комплектующие",'План Факт 2025'!M12="")),"Требует заполнения","ОК") -> ОК | L12: =IF(OR(AND('План Факт 2025'!D12="Программное_обеспечение_лицензии",'План Факт 2025'!N12="",'План Факт 2025'!M12=""),AND('План Факт 2025'!D12="Приобретение_ПО",'План Факт 2025'!M12="",'План Факт 2025'!N12="",'План Факт 2025'!M12=""),AND('План Факт 2025'!C12<>"",'План Факт 2025'!N12="",'План Факт 2025'!M12="")),"Требует заполнения","ОК") -> ОК | N12: =IF(OR('План Факт 2025'!C12="ФОТ",SUM('План Факт 2025'!Q12,'План Факт 2025'!R12,'План Факт 2025'!Z12,'План Факт 2025'!AA12)>0),"ОК",IF('План Факт 2025'!C12="","ОК","Требует заполнения")) -> ОК | T12: =IF(AND('План Факт 2025'!R12>0,'План Факт 2025'!X12=""),"Требует заполнения","ОК") -> ОК | U12: =IF(AND('План Факт 2025'!R12>0,'План Факт 2025'!Y12=""),"Требует заполнения","ОК") -> ОК
A13: =IF(AND('План Факт 2025'!B13<>"",'План Факт 2025'!A13=""),"Требует заполнения","ОК") -> ОК | C13: =IF(AND('План Факт 2025'!C13="",SUM('План Факт 2025'!Q13,'План Факт 2025'!R13,'План Факт 2025'!Z13,'План Факт 2025'!AA13)>0),"Требует заполнения","ОК") -> ОК | D13: =IF(OR(AND('План Факт 2025'!D13="",'План Факт 2025'!C13="Инвестиционный_проект"),AND('План Факт 2025'!D13="",'План Факт 2025'!C13="Операционный_бюджет")),"Требует заполнения", IF('План Факт 2025'!D13="","ОК",IFERROR(VLOOKUP('План Факт 2025'!C13&'План Факт 2025'!D13,статьи,1,FALSE()),"Требует исправления"))) -> Операционный_бюджетПрограммное_обеспечение_лицензии | E13: =IF(AND('План Факт 2025'!C13="Инвестиционный_проект",'План Факт 2025'!G13=""),"Требует заполнения",IF(AND('План Факт 2025'!C13<>"Инвестиционный_проект",'План Факт 2025'!G13<>""),"Требует изменения","ОК")) -> ОК | G13: =IF(AND('План Факт 2025'!C13="Инвестиционный_проект",'План Факт 2025'!I13=""),"Требует заполнения","ОК") -> ОК | H13: =IF(AND('План Факт 2025'!C13="ФОТ",'План Факт 2025'!J13=""),"Требует заполнения","ОК") -> ОК | J13: =IF(OR(AND('План Факт 2025'!D13="Программное_обеспечение_лицензии",'План Факт 2025'!L13=""),AND('План Факт 2025'!D13="Приобретение_ПО",'План Факт 2025'!L13=""),AND('План Факт 2025'!D13="ИТ_оборудование_и_комплектующие_ИП",'План Факт 2025'!L13=""),AND('План Факт 2025'!D13="ИТ_оборудование_и_комплектующие",'План Факт 2025'!L13="")),"Требует заполнения","ОК") -> ОК | K13: =IF(OR(AND('План Факт 2025'!C13="Операционный_бюджет",'План Факт 2025'!D13="Программное_обеспечение_лицензии",'План Факт 2025'!M13=""),AND('План Факт 2025'!C13="Инвестиционный_проект",'План Факт 2025'!D13="Приобретение_ПО",'План Факт 2025'!M13=""),AND('План Факт 2025'!D13="ИТ_оборудование_и_комплектующие_ИП",'План Факт 2025'!M13=""),AND('План Факт 2025'!D13="ИТ_оборудование_и_комплектующие",'План Факт 2025'!M13="")),"Требует заполнения","ОК") -> ОК | L13: =IF(OR(AND('План Факт 2025'!D13="Программное_обеспечение_лицензии",'План Факт 2025'!N13="",'План Факт 2025'!M13=""),AND('План Факт 2025'!D13="Приобретение_ПО",'План Факт 2025'!M13="",'План Факт 2025'!N13="",'План Факт 2025'!M13=""),AND('План Факт 2025'!C13<>"",'План Факт 2025'!N13="",'План Факт 2025'!M13="")),"Требует заполнения","ОК") -> ОК | N13: =IF(OR('План Факт 2025'!C13="ФОТ",SUM('План Факт 2025'!Q13,'План Факт 2025'!R13,'План Факт 2025'!Z13,'План Факт 2025'!AA13)>0),"ОК",IF('План Факт 2025'!C13="","ОК","Требует заполнения")) -> ОК | T13: =IF(AND('План Факт 2025'!R13>0,'План Факт 2025'!X13=""),"Требует заполнения","ОК") -> ОК | U13: =IF(AND('План Факт 2025'!R13>0,'План Факт 2025'!Y13=""),"Требует заполнения","ОК") -> ОК
A14: =IF(AND('План Факт 2025'!B14<>"",'План Факт 2025'!A14=""),"Требует заполнения","ОК") -> ОК | C14: =IF(AND('План Факт 2025'!C14="",SUM('План Факт 2025'!Q14,'План Факт 2025'!R14,'План Факт 2025'!Z14,'План Факт 2025'!AA14)>0),"Требует заполнения","ОК") -> ОК | D14: =IF(OR(AND('План Факт 2025'!D14="",'План Факт 2025'!C14="Инвестиционный_проект"),AND('План Факт 2025'!D14="",'План Факт 2025'!C14="Операционный_бюджет")),"Требует заполнения", IF('План Факт 2025'!D14="","ОК",IFERROR(VLOOKUP('План Факт 2025'!C14&'План Факт 2025'!D14,статьи,1,FALSE()),"Требует исправления"))) -> Операционный_бюджетПрограммное_обеспечение_лицензии | E14: =IF(AND('План Факт 2025'!C14="Инвестиционный_проект",'План Факт 2025'!G14=""),"Требует заполнения",IF(AND('План Факт 2025'!C14<>"Инвестиционный_проект",'План Факт 2025'!G14<>""),"Требует изменения","ОК")) -> ОК | G14: =IF(AND('План Факт 2025'!C14="Инвестиционный_проект",'План Факт 2025'!I14=""),"Требует заполнения","ОК") -> ОК | H14: =IF(AND('План Факт 2025'!C14="ФОТ",'План Факт 2025'!J14=""),"Требует заполнения","ОК") -> ОК | J14: =IF(OR(AND('План Факт 2025'!D14="Программное_обеспечение_лицензии",'План Факт 2025'!L14=""),AND('План Факт 2025'!D14="Приобретение_ПО",'План Факт 2025'!L14=""),AND('План Факт 2025'!D14="ИТ_оборудование_и_комплектующие_ИП",'План Факт 2025'!L14=""),AND('План Факт 2025'!D14="ИТ_оборудование_и_комплектующие",'План Факт 2025'!L14="")),"Требует заполнения","ОК") -> ОК | K14: =IF(OR(AND('План Факт 2025'!C14="Операционный_бюджет",'План Факт 2025'!D14="Программное_обеспечение_лицензии",'План Факт 2025'!M14=""),AND('План Факт 2025'!C14="Инвестиционный_проект",'План Факт 2025'!D14="Приобретение_ПО",'План Факт 2025'!M14=""),AND('План Факт 2025'!D14="ИТ_оборудование_и_комплектующие_ИП",'План Факт 2025'!M14=""),AND('План Факт 2025'!D14="ИТ_оборудование_и_комплектующие",'План Факт 2025'!M14="")),"Требует заполнения","ОК") -> ОК | L14: =IF(OR(AND('План Факт 2025'!D14="Программное_обеспечение_лицензии",'План Факт 2025'!N14="",'План Факт 2025'!M14=""),AND('План Факт 2025'!D14="Приобретение_ПО",'План Факт 2025'!M14="",'План Факт 2025'!N14="",'План Факт 2025'!M14=""),AND('План Факт 2025'!C14<>"",'План Факт 2025'!N14="",'План Факт 2025'!M14="")),"Требует заполнения","ОК") -> ОК | N14: =IF(OR('План Факт 2025'!C14="ФОТ",SUM('План Факт 2025'!Q14,'План Факт 2025'!R14,'План Факт 2025'!Z14,'План Факт 2025'!AA14)>0),"ОК",IF('План Факт 2025'!C14="","ОК","Требует заполнения")) -> ОК | T14: =IF(AND('План Факт 2025'!R14>0,'План Факт 2025'!X14=""),"Требует заполнения","ОК") -> ОК | U14: =IF(AND('План Факт 2025'!R14>0,'План Факт 2025'!Y14=""),"Требует заполнения","ОК") -> ОК
A15: =IF(AND('План Факт 2025'!B15<>"",'План Факт 2025'!A15=""),"Требует заполнения","ОК") -> ОК | C15: =IF(AND('План Факт 2025'!C15="",SUM('План Факт 2025'!Q15,'План Факт 2025'!R15,'План Факт 2025'!Z15,'План Факт 2025'!AA15)>0),"Требует заполнения","ОК") -> ОК | D15: =IF(OR(AND('План Факт 2025'!D15="",'План Факт 2025'!C15="Инвестиционный_проект"),AND('План Факт 2025'!D15="",'План Факт 2025'!C15="Операционный_бюджет")),"Требует заполнения", IF('План Факт 2025'!D15="","ОК",IFERROR(VLOOKUP('План Факт 2025'!C15&'План Факт 2025'!D15,статьи,1,FALSE()),"Требует исправления"))) -> Операционный_бюджетИТ_оборудование_и_комплектующие | E15: =IF(AND('План Факт 2025'!C15="Инвестиционный_проект",'План Факт 2025'!G15=""),"Требует заполнения",IF(AND('План Факт 2025'!C15<>"Инвестиционный_проект",'План Факт 2025'!G15<>""),"Требует изменения","ОК")) -> ОК | G15: =IF(AND('План Факт 2025'!C15="Инвестиционный_проект",'План Факт 2025'!I15=""),"Требует заполнения","ОК") -> ОК | H15: =IF(AND('План Факт 2025'!C15="ФОТ",'План Факт 2025'!J15=""),"Требует заполнения","ОК") -> ОК | J15: =IF(OR(AND('План Факт 2025'!D15="Программное_обеспечение_лицензии",'План Факт 2025'!L15=""),AND('План Факт 2025'!D15="Приобретение_ПО",'План Факт 2025'!L15=""),AND('План Факт 2025'!D15="ИТ_оборудование_и_комплектующие_ИП",'План Факт 2025'!L15=""),AND('План Факт 2025'!D15="ИТ_оборудование_и_комплектующие",'План Факт 2025'!L15="")),"Требует заполнения","ОК") -> ОК | K15: =IF(OR(AND('План Факт 2025'!C15="Операционный_бюджет",'План Факт 2025'!D15="Программное_обеспечение_лицензии",'План Факт 2025'!M15=""),AND('План Факт 2025'!C15="Инвестиционный_проект",'План Факт 2025'!D15="Приобретение_ПО",'План Факт 2025'!M15=""),AND('План Факт 2025'!D15="ИТ_оборудование_и_комплектующие_ИП",'План Факт 2025'!M15=""),AND('План Факт 2025'!D15="ИТ_оборудование_и_комплектующие",'План Факт 2025'!M15="")),"Требует заполнения","ОК") -> ОК | L15: =IF(OR(AND('План Факт 2025'!D15="Программное_обеспечение_лицензии",'План Факт 2025'!N15="",'План Факт 2025'!M15=""),AND('План Факт 2025'!D15="Приобретение_ПО",'План Факт 2025'!M15="",'План Факт 2025'!N15="",'План Факт 2025'!M15=""),AND('План Факт 2025'!C15<>"",'План Факт 2025'!N15="",'План Факт 2025'!M15="")),"Требует заполнения","ОК") -> ОК | N15: =IF(OR('План Факт 2025'!C15="ФОТ",SUM('План Факт 2025'!Q15,'План Факт 2025'!R15,'План Факт 2025'!Z15,'План Факт 2025'!AA15)>0),"ОК",IF('План Факт 2025'!C15="","ОК","Требует заполнения")) -> ОК | T15: =IF(AND('План Факт 2025'!R15>0,'План Факт 2025'!X15=""),"Требует заполнения","ОК") -> ОК | U15: =IF(AND('План Факт 2025'!R15>0,'План Факт 2025'!Y15=""),"Требует заполнения","ОК") -> ОК
A16: =IF(AND('План Факт 2025'!B16<>"",'План Факт 2025'!A16=""),"Требует заполнения","ОК") -> ОК | C16: =IF(AND('План Факт 2025'!C16="",SUM('План Факт 2025'!Q16,'План Факт 2025'!R16,'План Факт 2025'!Z16,'План Факт 2025'!AA16)>0),"Требует заполнения","ОК") -> ОК | D16: =IF(OR(AND('План Факт 2025'!D16="",'План Факт 2025'!C16="Инвестиционный_проект"),AND('План Факт 2025'!D16="",'План Факт 2025'!C16="Операционный_бюджет")),"Требует заполнения", IF('План Факт 2025'!D16="","ОК",IFERROR(VLOOKUP('План Факт 2025'!C16&'План Факт 2025'!D16,статьи,1,FALSE()),"Требует исправления"))) -> Операционный_бюджетУслуги_связи | E16: =IF(AND('План Факт 2025'!C16="Инвестиционный_проект",'План Факт 2025'!G16=""),"Требует заполнения",IF(AND('План Факт 2025'!C16<>"Инвестиционный_проект",'План Факт 2025'!G16<>""),"Требует изменения","ОК")) -> ОК | G16: =IF(AND('План Факт 2025'!C16="Инвестиционный_проект",'План Факт 2025'!I16=""),"Требует заполнения","ОК") -> ОК | H16: =IF(AND('План Факт 2025'!C16="ФОТ",'План Факт 2025'!J16=""),"Требует заполнения","ОК") -> ОК | J16: =IF(OR(AND('План Факт 2025'!D16="Программное_обеспечение_лицензии",'План Факт 2025'!L16=""),AND('План Факт 2025'!D16="Приобретение_ПО",'План Факт 2025'!L16=""),AND('План Факт 2025'!D16="ИТ_оборудование_и_комплектующие_ИП",'План Факт 2025'!L16=""),AND('План Факт 2025'!D16="ИТ_оборудование_и_комплектующие",'План Факт 2025'!L16="")),"Требует заполнения","ОК") -> ОК | K16: =IF(OR(AND('План Факт 2025'!C16="Операционный_бюджет",'План Факт 2025'!D16="Программное_обеспечение_лицензии",'План Факт 2025'!M16=""),AND('План Факт 2025'!C16="Инвестиционный_проект",'План Факт 2025'!D16="Приобретение_ПО",'План Факт 2025'!M16=""),AND('План Факт 2025'!D16="ИТ_оборудование_и_комплектующие_ИП",'План Факт 2025'!M16=""),AND('План Факт 2025'!D16="ИТ_оборудование_и_комплектующие",'План Факт 2025'!M16="")),"Требует заполнения","ОК") -> ОК | L16: =IF(OR(AND('План Факт 2025'!D16="Программное_обеспечение_лицензии",'План Факт 2025'!N16="",'План Факт 2025'!M16=""),AND('План Факт 2025'!D16="Приобретение_ПО",'План Факт 2025'!M16="",'План Факт 2025'!N16="",'План Факт 2025'!M16=""),AND('План Факт 2025'!C16<>"",'План Факт 2025'!N16="",'План Факт 2025'!M16="")),"Требует заполнения","ОК") -> ОК | N16: =IF(OR('План Факт 2025'!C16="ФОТ",SUM('План Факт 2025'!Q16,'План Факт 2025'!R16,'План Факт 2025'!Z16,'План Факт 2025'!AA16)>0),"ОК",IF('План Факт 2025'!C16="","ОК","Требует заполнения")) -> ОК | T16: =IF(AND('План Факт 2025'!R16>0,'План Факт 2025'!X16=""),"Требует заполнения","ОК") -> ОК | U16: =IF(AND('План Факт 2025'!R16>0,'План Факт 2025'!Y16=""),"Требует заполнения","ОК") -> ОК
... A993: =IF(AND('План Факт 2025'!B993<>"",'План Факт 2025'!A993=""),"Требует заполнения","ОК") -> ОК | C993: =IF(AND('План Факт 2025'!C993="",SUM('План Факт 2025'!Q993,'План Факт 2025'!R993,'План Факт 2025'!Z993,'План Факт 2025'!AA993)>0),"Требует заполнения","ОК") -> ОК | D993: =IF(OR(AND('План Факт 2025'!D993="",'План Факт 2025'!C993="Инвестиционный_проект"),AND('План Факт 2025'!D993="",'План Факт 2025'!C993="Операционный_бюджет")),"Требует заполнения", IF('План Факт 2025'!D993="","ОК",IFERROR(VLOOKUP('План Факт 2025'!C993&'План Факт 2025'!D993,статьи,1,FALSE()),"Требует исправления"))) -> ОК | E993: =IF(AND('План Факт 2025'!C993="Инвестиционный_проект",'План Факт 2025'!G993=""),"Требует заполнения",IF(AND('План Факт 2025'!C993<>"Инвестиционный_проект",'План Факт 2025'!G993<>""),"Требует изменения","ОК")) -> ОК | G993: =IF(AND('План Факт 2025'!C993="Инвестиционный_проект",'План Факт 2025'!I993=""),"Требует заполнения","ОК") -> ОК | H993: =IF(AND('План Факт 2025'!C993="ФОТ",'План Факт 2025'!J993=""),"Требует заполнения","ОК") -> ОК | J993: =IF(OR(AND('План Факт 2025'!D993="Программное_обеспечение_лицензии",'План Факт 2025'!L993=""),AND('План Факт 2025'!D993="Приобретение_ПО",'План Факт 2025'!L993=""),AND('План Факт 2025'!D993="ИТ_оборудование_и_комплектующие_ИП",'План Факт 2025'!L993=""),AND('План Факт 2025'!D993="ИТ_оборудование_и_комплектующие",'План Факт 2025'!L993="")),"Требует заполнения","ОК") -> ОК | K993: =IF(OR(AND('План Факт 2025'!C993="Операционный_бюджет",'План Факт 2025'!D993="Программное_обеспечение_лицензии",'План Факт 2025'!M993=""),AND('План Факт 2025'!C993="Инвестиционный_проект",'План Факт 2025'!D993="Приобретение_ПО",'План Факт 2025'!M993=""),AND('План Факт 2025'!D993="ИТ_оборудование_и_комплектующие_ИП",'План Факт 2025'!M993=""),AND('План Факт 2025'!D993="ИТ_оборудование_и_комплектующие",'План Факт 2025'!M993="")),"Требует заполнения","ОК") -> ОК | L993: =IF(OR(AND('План Факт 2025'!D993="Программное_обеспечение_лицензии",'План Факт 2025'!N993="",'План Факт 2025'!M993=""),AND('План Факт 2025'!D993="Приобретение_ПО",'План Факт 2025'!M993="",'План Факт 2025'!N993="",'План Факт 2025'!M993=""),AND('План Факт 2025'!C993<>"",'План Факт 2025'!N993="",'План Факт 2025'!M993="")),"Требует заполнения","ОК") -> ОК | N993: =IF(OR('План Факт 2025'!C993="ФОТ",SUM('План Факт 2025'!Q993,'План Факт 2025'!R993,'План Факт 2025'!Z993,'План Факт 2025'!AA993)>0),"ОК",IF('План Факт 2025'!C993="","ОК","Требует заполнения")) -> ОК | T993: =IF(AND('План Факт 2025'!R993>0,'План Факт 2025'!X993=""),"Требует заполнения","ОК") -> ОК | U993: =IF(AND('План Факт 2025'!R993>0,'План Факт 2025'!Y993=""),"Требует заполнения","ОК") -> ОК
